Workbook

Sheet Data Worksheet
A1: Client Contact | B1: Client Site | C1: Service Provider | D1: Service Type 1 | E1: Service Type 2 | F1: Service Type 3 | G1: Service Type 4 | H1: Service Type 5 | I1: Connection ID | J1: Contract Term | K1: Contract Start Date | L1: Contract End Date | M1: Billing Gateway
A2: 0 | B2: Not Found | C2: Not Found | D2: Not Found | E2: Not Found | F2: Not Found | G2: Not Found | H2: Not Found | I2: Not Found | J2: Not Found | K2: Not Found | L2: Not Found | M2: Not Found
A3: 0 | B3: Not Found | C3: Not Found | D3: Not Found | E3: Not Found | F3: Not Found | G3: Not Found | H3: Not Found | I3: Not Found | J3: Not Found | K3: Not Found | L3: Not Found | M3: Not Found
A4: 0 | B4: Not Found | C4: Not Found | D4: Not Found | E4: Not Found | F4: Not Found | G4: Not Found | H4: Not Found | I4: Not Found | J4: Not Found | K4: Not Found | L4: Not Found | M4: Not Found
A5: 0 | B5: Not Found | C5: Not Found | D5: Not Found | E5: Not Found | F5: Not Found | G5: Not Found | H5: Not Found | I5: Not Found | J5: Not Found | K5: Not Found | L5: Not Found | M5: Not Found
A6: 0 | B6: Not Found | C6: Not Found | D6: Not Found | E6: Not Found | F6: Not Found | G6: Not Found | H6: Not Found | I6: Not Found | J6: Not Found | K6: Not Found | L6: Not Found | M6: Not Found
A7: 0 | B7: Not Found | C7: Not Found | D7: Not Found | E7: Not Found | F7: Not Found | G7: Not Found | H7: Not Found | I7: Not Found | J7: Not Found | K7: Not Found | L7: Not Found | M7: Not Found
A8: 0 | B8: Not Found | C8: Not Found | D8: Not Found | E8: Not Found | F8: Not Found | G8: Not Found | H8: Not Found | I8: Not Found | J8: Not Found | K8: Not Found | L8: Not Found | M8: Not Found
A9: 0 | B9: Not Found | C9: Not Found | D9: Not Found | E9: Not Found | F9: Not Found | G9: Not Found | H9: Not Found | I9: Not Found | J9: Not Found | K9: Not Found | L9: Not Found | M9: Not Found
A10: 0 | B10: Not Found | C10: Not Found | D10: Not Found | E10: Not Found | F10: Not Found | G10: Not Found | H10: Not Found | I10: Not Found | J10: Not Found | K10: Not Found | L10: Not Found | M10: Not Found
A11: 0 | B11: Not Found | C11: Not Found | D11: Not Found | E11: Not Found | F11: Not Found | G11: Not Found | H11: Not Found | I11: Not Found | J11: Not Found | K11: Not Found | L11: Not Found | M11: Not Found
A12: 0 | B12: Not Found | C12: Not Found | D12: Not Found | E12: Not Found | F12: Not Found | G12: Not Found | H12: Not Found | I12: Not Found | J12: Not Found | K12: Not Found | L12: Not Found | M12: Not Found
A13: 0 | B13: Not Found | C13: Not Found | D13: Not Found | E13: Not Found | F13: Not Found | G13: Not Found | H13: Not Found | I13: Not Found | J13: Not Found | K13: Not Found | L13: Not Found | M13: Not Found
... A62: 0 | B62: Not Found | C62: Not Found | D62: Not Found | E62: Not Found | F62: Not Found | G62: Not Found | H62: Not Found | I62: Not Found | J62: Not Found | K62: Not Found | L62: Not Found | M62: Not Found
A63: Salter Bros Balfour Hotel | B63: New Farm | C63: AAPT | D63: Voice Number Inventory | E63: Number Range | F63: 37 BALFOUR ST NEW FARM QLD 4005 | G63: 0 | H63: Not Found | I63: 0 | J63: 0 | K63: 0 | L63: Not Found | M63: Not Found
A64: Salter Bros Balfour Hotel | B64: New Farm | C64: AAPT | D64: Voice Number Inventory | E64: Number Range | F64: 37 BALFOUR ST NEW FARM QLD 4005 | G64: 0 | H64: Not Found | I64: 0 | J64: 0 | K64: 0 | L64: Not Found | M64: Not Found
A65: Salter Bros Balfour Hotel | B65: New Farm | C65: AAPT | D65: Voice Number Inventory | E65: Number Range | F65: 37 BALFOUR ST NEW FARM QLD 4005 | G65: 0 | H65: Not Found | I65: 0 | J65: 0 | K65: 0 | L65: Not Found | M65: Not Found
A66: Salter Bros Balfour Hotel | B66: New Farm | C66: AAPT | D66: Voice Number Inventory | E66: Number Range | F66: 37 BALFOUR ST NEW FARM QLD 4005 | G66: 0 | H66: Not Found | I66: 0 | J66: 0 | K66: 0 | L66: Not Found | M66: Not Found
A67: 0 | B67: Not Found | C67: Not Found | D67: Not Found | E67: Not Found | F67: Not Found | G67: Not Found | H67: Not Found | I67: Not Found | J67: Not Found | K67: Not Found | L67: Not Found | M67: Not Found
A68: 0 | B68: Not Found | C68: Not Found | D68: Not Found | E68: Not Found | F68: Not Found | G68: Not Found | H68: Not Found | I68: Not Found | J68: Not Found | K68: Not Found | L68: Not Found | M68: Not Found
A69: 0 | B69: Not Found | C69: Not Found | D69: Not Found | E69: Not Found | F69: Not Found | G69: Not Found | H69: Not Found | I69: Not Found | J69: Not Found | K69: Not Found | L69: Not Found | M69: Not Found
A70: 0 | B70: Not Found | C70: Not Found | D70: Not Found | E70: Not Found | F70: Not Found | G70: Not Found | H70: Not Found | I70: Not Found | J70: Not Found | K70: Not Found | L70: Not Found | M70: Not Found
A71: Solahart Brisbane | B71: Darra | C71: AAPT | D71: Voice Number Inventory | E71: Number Range | F71: 0 | G71: 0 | H71: Not Found | I71: 0 | J71: 0 | K71: 0 | L71: Not Found | M71: Not Found
A72: 0 | B72: Not Found | C72: Not Found | D72: Not Found | E72: Not Found | F72: Not Found | G72: Not Found | H72: Not Found | I72: Not Found | J72: Not Found | K72: Not Found | L72: Not Found | M72: Not Found
A73: 0 | B73: Not Found | C73: Not Found | D73: Not Found | E73: Not Found | F73: Not Found | G73: Not Found | H73: Not Found | I73: Not Found | J73: Not Found | K73: Not Found | L73: Not Found | M73: Not Found
A74: 0 | B74: Not Found | C74: Not Found | D74: Not Found | E74: Not Found | F74: Not Found | G74: Not Found | H74: Not Found | I74: Not Found | J74: Not Found | K74: Not Found | L74: Not Found | M74: Not Found
A75: 0 | B75: Not Found | C75: Not Found | D75: Not Found | E75: Not Found | F75: Not Found | G75: Not Found | H75: Not Found | I75: Not Found | J75: Not Found | K75: Not Found | L75: Not Found | M75: Not Found
A76: 0 | B76: Not Found | C76: Not Found | D76: Not Found | E76: Not Found | F76: Not Found | G76: Not Found | H76: Not Found | I76: Not Found | J76: Not Found | K76: Not Found | L76: Not Found | M76: Not Found
A77: 0 | B77: Not Found | C77: Not Found | D77: Not Found | E77: Not Found | F77: Not Found | G77: Not Found | H77: Not Found | I77: Not Found | J77: Not Found | K77: Not Found | L77: Not Found | M77: Not Found
A78: 0 | B78: Not Found | C78: Not Found | D78: Not Found | E78: Not Found | F78: Not Found | G78: Not Found | H78: Not Found | I78: Not Found | J78: Not Found | K78: Not Found | L78: Not Found | M78: Not Found
A79: 0 | B79: Not Found | C79: Not Found | D79: Not Found | E79: Not Found | F79: Not Found | G79: Not Found | H79: Not Found | I79: Not Found | J79: Not Found | K79: Not Found | L79: Not Found | M79: Not Found
A80: 0 | B80: Not Found | C80: Not Found | D80: Not Found | E80: Not Found | F80: Not Found | G80: Not Found | H80: Not Found | I80: Not Found | J80: Not Found | K80: Not Found | L80: Not Found | M80: Not Found
A81: 0 | B81: Not Found | C81: Not Found | D81: Not Found | E81: Not Found | F81: Not Found | G81: Not Found | H81: Not Found | I81: Not Found | J81: Not Found | K81: Not Found | L81: Not Found | M81: Not Found
A82: 0 | B82: Not Found | C82: Not Found | D82: Not Found | E82: Not Found | F82: Not Found | G82: Not Found | H82: Not Found | I82: Not Found | J82: Not Found | K82: Not Found | L82: Not Found | M82: Not Found
A83: 0 | B83: Not Found | C83: Not Found | D83: Not Found | E83: Not Found | F83: Not Found | G83: Not Found | H83: Not Found | I83: Not Found | J83: Not Found | K83: Not Found | L83: Not Found | M83: Not Found
... A284: 0 | B284: Not Found | C284: Not Found | D284: Not Found | E284: Not Found | F284: Not Found | G284: Not Found | H284: Not Found | I284: Not Found | J284: Not Found | K284: Not Found | L284: Not Found | M284: Not Found
A285: Emergency Medicine Foundation | B285: Level 1D, 60 Enterprise Place , TINGALPA QLD 4174 | C285: Vocus SIT | D285: Voice Service | E285: 0731128668 | F285: IP Tel Order - Smile Tel - 05/07/2024 Voice (5 Mbps) - Level 1D, 60 Enterprise Place , TINGALPA QLD 4173 | G285: Not Found | H285: Not Found | I285: Not Found | J285: Not Found | K285: 45603 | L285: Not Found | M285: Not Found
A286: 0 | B286: Not Found | C286: Not Found | D286: Not Found | E286: Not Found | F286: Not Found | G286: Not Found | H286: Not Found | I286: Not Found | J286: Not Found | K286: Not Found | L286: Not Found | M286: Not Found
A287: Red Roo Australia | B287: Level 1D, 60 Enterprise Place, Tingalpa QLD 4174 | C287: Vocus SIT | D287: Voice Service | E287: 0732558755 0731534563 0736330230 0731534561 | F287: IP Tel Order - Smile Tel - 18/04/2024 Voice (5 Mbps) - Level 1D, 60 Enterprise Place, Tingalpa QLD 4173 | G287: Not Found | H287: Not Found | I287: Not Found | J287: Not Found | K287: 13/06/2024 | L287: Not Found | M287: Not Found
A288: Swara | B288: Level 1D, 60 Enterprise Place, Tingalpa QLD 4174 | C288: Vocus SIT | D288: Voice Service | E288: 0733914119 0733910900 0733910922 | F288: IP Tel Order - Smile Tel - 03/04/2024 - 591822 - SWARA porting Voice (5 Mbps) - Level 1D, 60 Enterprise Place, Tingalpa QLD 4173 | G288: Not Found | H288: Not Found | I288: Not Found | J288: Not Found | K288: 45329 | L288: Not Found | M288: Not Found
A289: Salter (exact site needed) | B289: Level 1D, 60 Enterprise Place, Tingalpa QLD 4174 | C289: Vocus SIT | D289: Voice Service | E289: n/a | F289: IP Tel Order - Smile Tel - 03/04/2024 - 592190 Salter IP Tel with Webex Basic (Reseller) Voice (5 Mbps) - Level 1D, 60 Enterprise Place, Tingalpa QLD 4173 | G289: Not Found | H289: Not Found | I289: Not Found | J289: Not Found | K289: 45386 | L289: Not Found | M289: Not Found
A290: Red Roo Australia | B290: Level 1D, 60 Enterprise Place, Tingalpa QLD 4174 | C290: Vocus SIT | D290: Voice Service | E290: 0732558755 0731534563 0736330230 0731534561 | F290: IP Tel Order - Smile Tel - 18/04/2024 Voice (5 Mbps) - Level 1D, 60 Enterprise Place, Tingalpa QLD 4173 | G290: Not Found | H290: Not Found | I290: Not Found | J290: Not Found | K290: 13/06/2024 | L290: Not Found | M290: Not Found
A291: Red Roo Australia | B291: Level 1D, 60 Enterprise Place, Tingalpa QLD 4174 | C291: Vocus SIT | D291: Voice Service | E291: 0732558755 0731534563 0736330230 0731534561 | F291: IP Tel Order - Smile Tel - 18/04/2024 Voice (5 Mbps) - Level 1D, 60 Enterprise Place, Tingalpa QLD 4173 | G291: Not Found | H291: Not Found | I291: Not Found | J291: Not Found | K291: 13/06/2024 | L291: Not Found | M291: Not Found
A292: Swara | B292: Level 1D, 60 Enterprise Place, Tingalpa QLD 4174 | C292: Vocus SIT | D292: Voice Service | E292: 0733914119 0733910900 0733910922 | F292: IP Tel Order - Smile Tel - 03/04/2024 - 591822 - SWARA porting Voice (5 Mbps) - Level 1D, 60 Enterprise Place, Tingalpa QLD 4173 | G292: Not Found | H292: Not Found | I292: Not Found | J292: Not Found | K292: 45329 | L292: Not Found | M292: Not Found
A293: 0 | B293: Not Found | C293: Not Found | D293: Not Found | E293: Not Found | F293: Not Found | G293: Not Found | H293: Not Found | I293: Not Found | J293: Not Found | K293: Not Found | L293: Not Found | M293: Not Found
A294: CPM Squirrel Energy | B294: Level 1D, 60 Enterprise Place , TINGALPA QLD 4174 | C294: Vocus SIT | D294: Voice Service | E294: 0 | F294: Smile Tel (TINGALPA, QLD) - Vocus IP Tel [CPM Squirrel Energy] Voice (5 Mbps) - Level 1D, 60 Enterprise Place , TINGALPA QLD 4173 | G294: Not Found | H294: Not Found | I294: Not Found | J294: Not Found | K294: 19/12/2023 | L294: Not Found | M294: Not Found
A295: 0 | B295: Not Found | C295: Not Found | D295: Not Found | E295: Not Found | F295: Not Found | G295: Not Found | H295: Not Found | I295: Not Found | J295: Not Found | K295: Not Found | L295: Not Found | M295: Not Found
A296: ASG Newcastle | B296: Level 1D, 60 Enterprise Place, Tingalpa QLD 4174 | C296: Vocus SIT | D296: Voice Service | E296: 0 | F296: Smile Tel (Tingalpa , QLD) - Vocus IP Tel [ASG Newcastle] 4 IP Tel Standard (Reseller) Voice (5 Mbps) - Level 1D, 60 Enterprise Place, Tingalpa QLD 4173 | G296: Not Found | H296: Not Found | I296: Not Found | J296: Not Found | K296: 21/09/2023 | L296: Not Found | M296: Not Found
A297: ASG Adelaide | B297: Level 1D, 60 Enterprise Place, Tingalpa QLD 4174 | C297: Vocus SIT | D297: Voice Service | E297: 0 | F297: Smile Tel (Tingalpa , QLD) - Vocus IP Tel [ASG Adelaide] 9 IP Tel Standard (Reseller) Voice (5 Mbps) - Level 1D, 60 Enterprise Place, Tingalpa QLD 4173 | G297: Not Found | H297: Not Found | I297: Not Found | J297: Not Found | K297: 21/09/2023 | L297: Not Found | M297: Not Found
A298: Spicers (check exact site) | B298: Level 1D, 60 Enterprise Place, Tingalpa QLD 4174 | C298: Vocus SIT | D298: Voice Service | E298: 0 | F298: Smile Tel (Tingalpa , QLD) - Vocus IP Tel [Spicers] IP Tel with Webex Basic (Reseller) Voice (5 Mbps) - Level 1D, 60 Enterprise Place, Tingalpa QLD 4173 | G298: Not Found | H298: Not Found | I298: Not Found | J298: Not Found | K298: 31/08/2023 | L298: Not Found | M298: Not Found
A299: 0 | B299: Not Found | C299: Not Found | D299: Not Found | E299: Not Found | F299: Not Found | G299: Not Found | H299: Not Found | I299: Not Found | J299: Not Found | K299: Not Found | L299: Not Found | M299: Not Found
A300: 0 | B300: Not Found | C300: Not Found | D300: Not Found | E300: Not Found | F300: Not Found | G300: Not Found | H300: Not Found | I300: Not Found | J300: Not Found | K300: Not Found | L300: Not Found | M300: Not Found
A301: 0 | B301: Not Found | C301: Not Found | D301: Not Found | E301: Not Found | F301: Not Found | G301: Not Found | H301: Not Found | I301: Not Found | J301: Not Found | K301: Not Found | L301: Not Found | M301: Not Found
A302: Action Smart Group | B302: 37 access avenue, YATALA QLD 4208 | C302: Vocus SIT | D302: Voice Service | E302: 0 | F302: Smile Tel (YATALA, QLD) - Vocus IP Tel [Action Smart Group] Voice (5 Mbps) - 37 access avenue, YATALA QLD 4207 | G302: Not Found | H302: Not Found | I302: Not Found | J302: Not Found | K302: 25/07/2023 | L302: Not Found | M302: Not Found
A303: Queensland Children's Gastroenterology | B303: 537 stanley street, SOUTH BRISBANE QLD 4102 | C303: Vocus SIT | D303: Voice Service | E303: 0 | F303: Smile Tel (SOUTH BRISBANE, QLD) - Vocus IP Tel [Queensland Children's Gastroenterology] Voice (5 Mbps) - 537 stanley street, SOUTH BRISBANE QLD 4101 | G303: Not Found | H303: Not Found | I303: Not Found | J303: Not Found | K303: 20/07/2023 | L303: Not Found | M303: Not Found
A304: 0 | B304: Not Found | C304: Not Found | D304: Not Found | E304: Not Found | F304: Not Found | G304: Not Found | H304: Not Found | I304: Not Found | J304: Not Found | K304: Not Found | L304: Not Found | M304: Not Found
A305: 0 | B305: Not Found | C305: Not Found | D305: Not Found | E305: Not Found | F305: Not Found | G305: Not Found | H305: Not Found | I305: Not Found | J305: Not Found | K305: Not Found | L305: Not Found | M305: Not Found
A306: Caravan Fix | B306: 9 SOMERSET ROAD, GRACEMERE QLD 4703 | C306: Vocus SIT | D306: Voice Service | E306: 0 | F306: Smile Tel (GRACEMERE, QLD) - Vocus IP Tel Voice (5 Mbps) - -9 SOMERSET ROAD, GRACEMERE QLD 4702 | G306: Not Found | H306: Not Found | I306: Not Found | J306: Not Found | K306: 17/07/2023 | L306: Not Found | M306: Not Found
A307: Queensland Children's Gastroenterology | B307: 537 stanley street, SOUTH BRISBANE QLD 4102 | C307: Vocus SIT | D307: Voice Service | E307: 0 | F307: Smile Tel (SOUTH BRISBANE, QLD) - Vocus IP Tel [Queensland Children's Gastroenterology] Voice (5 Mbps) - 537 stanley street, SOUTH BRISBANE QLD 4101 | G307: Not Found | H307: Not Found | I307: Not Found | J307: Not Found | K307: 20/07/2023 | L307: Not Found | M307: Not Found
A308: 0 | B308: Not Found | C308: Not Found | D308: Not Found | E308: Not Found | F308: Not Found | G308: Not Found | H308: Not Found | I308: Not Found | J308: Not Found | K308: Not Found | L308: Not Found | M308: Not Found
A309: 0 | B309: Not Found | C309: Not Found | D309: Not Found | E309: Not Found | F309: Not Found | G309: Not Found | H309: Not Found | I309: Not Found | J309: Not Found | K309: Not Found | L309: Not Found | M309: Not Found
A310: Rockwell Technology/Specialist Hail Repairs | B310: 37 access avenue, YATALA QLD 4208 | C310: Vocus SIT | D310: Voice Service | E310: 0 | F310: Smile Tel (YATALA, QLD) - Vocus IP Tel Voice (5 Mbps) - 37 access avenue, YATALA QLD 4207 | G310: Not Found | H310: Not Found | I310: Not Found | J310: Not Found | K310: 45175 | L310: Not Found | M310: Not Found
A311: 0 | B311: Not Found | C311: Not Found | D311: Not Found | E311: Not Found | F311: Not Found | G311: Not Found | H311: Not Found | I311: Not Found | J311: Not Found | K311: Not Found | L311: Not Found | M311: Not Found
A312: 0 | B312: Not Found | C312: Not Found | D312: Not Found | E312: Not Found | F312: Not Found | G312: Not Found | H312: Not Found | I312: Not Found | J312: Not Found | K312: Not Found | L312: Not Found | M312: Not Found
A313: Action Smart Group | B313: 37 access avenue, YATALA QLD 4208 | C313: Vocus SIT | D313: Voice Service | E313: 0 | F313: Smile Tel (YATALA, QLD) - Vocus IP Tel [Action Smart Group] Voice (5 Mbps) - 37 access avenue, YATALA QLD 4207 | G313: Not Found | H313: Not Found | I313: Not Found | J313: Not Found | K313: 25/07/2023 | L313: Not Found | M313: Not Found
A314: Branyan Early Learning Centre | B314: 7 penny lane, BRANYAN QLD 4671 | C314: Vocus SIT | D314: Voice Service | E314: 0 | F314: Smile Tel (BRANYAN, QLD) - Vocus IP Tel [Branyan Early Learning Centre] Voice (5 Mbps) - 7 penny lane, BRANYAN QLD 4670 | G314: Not Found | H314: Not Found | I314: Not Found | J314: Not Found | K314: 18/05/2023 | L314: Not Found | M314: Not Found
A315: 0 | B315: Not Found | C315: Not Found | D315: Not Found | E315: Not Found | F315: Not Found | G315: Not Found | H315: Not Found | I315: Not Found | J315: Not Found | K315: Not Found | L315: Not Found | M315: Not Found
A316: Wattlestone | B316: 16 MARIE STREET, MILTON QLD 4065 | C316: Vocus SIT | D316: Voice Service | E316: 0 | F316: Smile Tel (MILTON, QLD) - Vocus IP Tel [Wattlestone] IP Tel Standard (Reseller) Voice (5 Mbps) - 16 MARIE STREET, MILTON QLD 4064 | G316: Not Found | H316: Not Found | I316: Not Found | J316: Not Found | K316: 13/04/2023 | L316: Not Found | M316: Not Found
A317: 0 | B317: Not Found | C317: Not Found | D317: Not Found | E317: Not Found | F317: Not Found | G317: Not Found | H317: Not Found | I317: Not Found | J317: Not Found | K317: Not Found | L317: Not Found | M317: Not Found
A318: Wattlestone | B318: 16 MARIE STREET, MILTON QLD 4065 | C318: Vocus SIT | D318: Voice Service | E318: 0 | F318: Smile Tel (MILTON, QLD) - Vocus IP Tel [Wattlestone] IP Tel Standard (Reseller) Voice (5 Mbps) - 16 MARIE STREET, MILTON QLD 4064 | G318: Not Found | H318: Not Found | I318: Not Found | J318: Not Found | K318: 13/04/2023 | L318: Not Found | M318: Not Found
A319: Energy Pro Electrical | B319: 60 enterprise place, TINGALPA QLD 4174 | C319: Vocus SIT | D319: Voice Service | E319: 0 | F319: Smile Tel (TINGALPA, QLD) - Vocus IP Tel [Energy Pro Electrical] 3 IP Tel Premium (Reseller) Voice (5 Mbps) - 60 enterprise place, TINGALPA QLD 4173 | G319: Not Found | H319: Not Found | I319: Not Found | J319: Not Found | K319: 21/03/2023 | L319: Not Found | M319: Not Found
A320: Spicers Sangoma | B320: Level 1D, 60 Enterprise Place, Tingalpa QLD 4174 | C320: Vocus SIT | D320: Voice Service | E320: 0 | F320: Smile Tel (TINGALPA, QLD) - Vocus IP Tel [Spicers Sangoma] 8 IP Tel Basic (Reseller) Voice (5 Mbps) - Level 1D, 60 Enterprise Place, TINGALPA QLD 4173 | G320: Not Found | H320: Not Found | I320: Not Found | J320: Not Found | K320: 14/03/2023 | L320: Not Found | M320: Not Found
A321: The Empowering Hive | B321: Level 1D, 60 Enterprise Place, Tingalpa QLD 4174 | C321: Vocus SIT | D321: Voice Service | E321: 0 | F321: Smile Tel (Tingalpa , QLD) - Vocus IP Tel [The Empowering Hive] IP Tel Voicemail Voice (5 Mbps) - Level 1D, 60 Enterprise Place, Tingalpa QLD 4173 | G321: Not Found | H321: Not Found | I321: Not Found | J321: Not Found | K321: 45110 | L321: Not Found | M321: Not Found
A322: 0 | B322: Not Found | C322: Not Found | D322: Not Found | E322: Not Found | F322: Not Found | G322: Not Found | H322: Not Found | I322: Not Found | J322: Not Found | K322: Not Found | L322: Not Found | M322: Not Found
A323: 0 | B323: Not Found | C323: Not Found | D323: Not Found | E323: Not Found | F323: Not Found | G323: Not Found | H323: Not Found | I323: Not Found | J323: Not Found | K323: Not Found | L323: Not Found | M323: Not Found
A324: Stafford Dental Studio | B324: 3/285 Stafford Road, Stafford QLD 4053 | C324: Not Found | D324: Not Found | E324: Not Found | F324: Not Found | G324: Not Found | H324: Not Found | I324: AVC000111679247 | J324: Not Found | K324: Not Found | L324: Not Found | M324: Not Found
A325: Air Restore | B325: 32 DIVIDEND STREET, MANSFIELD, QLD, 4122 | C325: Exetel | D325: NBNEE100 CBD Unlimited 350 | E325: 100/100Mbps | F325: Fibre | G325: Not Found | H325: 220.233.220.51 | I325: Not Found | J325: 36 Months | K325: 10 May 2021 | L325: 10 May 2024 | M325: Not Found
A326: Lead Institute | B326: Level 1D, 60 Enterprise Place, Tingalpa QLD 4174 | C326: Vocus SIT | D326: Voice Service | E326: 0756767766 | F326: IP Tel Order - Smile Tel - 03/02/2023 Voice (5 Mbps) - Level 1D, 60 Enterprise Place , Tingalpa QLD 4173 | G326: Not Found | H326: Not Found | I326: Not Found | J326: Not Found | K326: 45201 | L326: Not Found | M326: Not Found
A327: Action Smart | B327: Level 1D, 60 Enterprise Place, Tingalpa QLD 4174 | C327: Vocus SIT | D327: Voice Service | E327: 0734627617 0734627618 0734627619 0748862250 | F327: IP Tel Order - Smile Tel - 03/02/2023 Voice (5 Mbps) - Level 1D, 60 Enterprise Place , Tingalpa QLD 4173 | G327: Not Found | H327: Not Found | I327: Not Found | J327: Not Found | K327: 14/02/2023 | L327: Not Found | M327: Not Found
A328: The Yiros Shop Southbank | B328: 00 189 Grey ST | C328: 4101 | D328: 4G Backup service | E328: 45891 | F328: 0 | G328: 0 | H328: Not Found | I328: 0 | J328: Not Found | K328: Not Found | L328: Not Found | M328: Not Found
A329: Zambrero Kings Cross | B329: 4 111 Darlinghurst RD | C329: 2011 | D329: 4G Backup service | E329: 45896 | F329: 0 | G329: 0 | H329: Not Found | I329: 0 | J329: Not Found | K329: Not Found | L329: Not Found | M329: Not Found
A330: A M Emerick & T J Morrice | B330: Lot: 2 136 Tarrants Rd | C330: 4670 | D330: 150Mbps/30Mbps | E330: NBN Reseller G4 WLS | F330: 122.151.165.26 | G330: PPPoE | H330: Not Found | I330: AVC000131593506 | J330: Not Found | K330: Not Found | L330: Not Found | M330: Not Found
A331: Hanwha (Aus) | B331: Unit 1, 49 Miller Street, Murarrie QLD 4173 | C331: Vocus SIT | D331: Voice Service | E331: 0734617350 | F331: IP Tel Order - Smile Tel - 13/12/2022 Voice (5 Mbps) - Unit 1, 49 Miller Street, Murarrie QLD 4172 | G331: Not Found | H331: Not Found | I331: Not Found | J331: Not Found | K331: 21/12/2022 | L331: Not Found | M331: Not Found
A332: Hanwha (Aus) | B332: Unit 1, 49 Miller Street, Murarrie QLD 4173 | C332: Vocus SIT | D332: Voice Service | E332: 0734617350 | F332: IP Tel Order - Smile Tel - 13/12/2022 Voice (5 Mbps) - Unit 1, 49 Miller Street, Murarrie QLD 4172 | G332: Not Found | H332: Not Found | I332: Not Found | J332: Not Found | K332: 21/12/2022 | L332: Not Found | M332: Not Found
A333: Hanwha (Aus) | B333: Unit 1, 49 Miller Street, Murarrie QLD 4173 | C333: Vocus SIT | D333: Voice Service | E333: 0734617350 | F333: IP Tel Order - Smile Tel - 13/12/2022 Voice (5 Mbps) - Unit 1, 49 Miller Street, Murarrie QLD 4172 | G333: Not Found | H333: Not Found | I333: Not Found | J333: Not Found | K333: 21/12/2022 | L333: Not Found | M333: Not Found
A334: Hanwha (Aus) | B334: Unit 1, 49 Miller Street, Murarrie QLD 4173 | C334: Vocus SIT | D334: Voice Service | E334: 0734617350 | F334: IP Tel Order - Smile Tel - 13/12/2022 Voice (5 Mbps) - Unit 1, 49 Miller Street, Murarrie QLD 4172 | G334: Not Found | H334: Not Found | I334: Not Found | J334: Not Found | K334: 21/12/2022 | L334: Not Found | M334: Not Found
A335: Hanwha (Aus) | B335: Unit 1, 49 Miller Street, Murarrie QLD 4173 | C335: Vocus SIT | D335: Voice Service | E335: 0734617350 | F335: IP Tel Order - Smile Tel - 13/12/2022 Voice (5 Mbps) - Unit 1, 49 Miller Street, Murarrie QLD 4172 | G335: Not Found | H335: Not Found | I335: Not Found | J335: Not Found | K335: 21/12/2022 | L335: Not Found | M335: Not Found
A336: Hanwha (Aus) | B336: Unit 1, 49 Miller Street, Murarrie QLD 4173 | C336: Vocus SIT | D336: Voice Service | E336: 0734617350 | F336: IP Tel Order - Smile Tel - 13/12/2022 Voice (5 Mbps) - Unit 1, 49 Miller Street, Murarrie QLD 4172 | G336: Not Found | H336: Not Found | I336: Not Found | J336: Not Found | K336: 21/12/2022 | L336: Not Found | M336: Not Found
A337: CPM Advisory and Project Management | B337: Unit 1, 49 Miller Street, Murarrie QLD 4173 | C337: Vocus SIT | D337: Voice Service | E337: 0730735250 0731851340 0732811004 0732811006 0732817591 0732829076 0738102527 0738102528 0738190261 0738190262 0738190264 0738190485 | F337: IP Tel Order - Smile Tel - 05/09/2022 Voice (5 Mbps) - Unit 1, 49 Miller Street, Murarrie QLD 4172 | G337: Not Found | H337: Not Found | I337: Not Found | J337: Not Found | K337: 20/03/2025 | L337: Not Found | M337: Not Found
A338: Hanwha (Aus) | B338: Unit 1, 49 Miller Street, Murarrie QLD 4173 | C338: Vocus SIT | D338: Voice Service | E338: 0734617350 | F338: IP Tel Order - Smile Tel - 13/12/2022 Voice (5 Mbps) - Unit 1, 49 Miller Street, Murarrie QLD 4172 | G338: Not Found | H338: Not Found | I338: Not Found | J338: Not Found | K338: 21/12/2022 | L338: Not Found | M338: Not Found
A339: A&K Ashgrove | B339: 39 MOULTON ST, ASHGROVE QLD | C339: ABB | D339: NBN 250/25 | E339: HFC | F339: 180.181.209.84 | G339: Not Found | H339: Not Found | I339: 39 MOULTON ST, ASHGROVE QLD | J339: Not Found | K339: 30 May 2025 | L339: Not Found | M339: Sasboss
A340: Active Living | B340: UN 3, 81 SIXTH AV, MAROOCHYDORE QLD | C340: ABB | D340: NBN 50/20 | E340: FTTN | F340: 144.6.103.243 | G340: Not Found | H340: Not Found | I340: UN 3, 81 SIXTH AV, MAROOCHYDORE QLD | J340: Not Found | K340: 6 Dec 2024 | L340: Not Found | M340: Sasboss
A341: Agnes Water Beauty Hub | B341: Tncy 14 2875 Round Hill Rd | C341: 4677 | D341: 50Mbps/20Mbps | E341: NBN Reseller G4 | F341: 122.151.163.33 | G341: PPPoE | H341: Not Found | I341: AVC000183920492 | J341: Not Found | K341: Not Found | L341: Not Found | M341: Not Found
A342: Agnes Water Doctors | B342: Tncy 15 2875 Round Hill Rd | C342: 4677 | D342: 100Mbps/40Mbps | E342: NBN Reseller G4 | F342: 0 | G342: PPPoE | H342: Not Found | I342: AVC000180125510 | J342: Not Found | K342: Not Found | L342: Not Found | M342: Not Found
A343: Albany Family Doctors | B343: Shop 3 715 Albany Creek Rd | C343: 4035 | D343: 100Mbps/40Mbps | E343: NBN Reseller G4 HFC | F343: 202.62.138.107 | G343: PPPoE | H343: Not Found | I343: AVC400045677083 | J343: Not Found | K343: Not Found | L343: Not Found | M343: Not Found
A344: All Crops | B344: Lot 7 28672 Bruce Hwy | C344: 4660 | D344: 100Mbps/40Mbps | E344: NBN Reseller G4 FTTC | F344: 125.168.88.232 | G344: PPPoE | H344: Not Found | I344: AVC000123456625 | J344: Not Found | K344: Not Found | L344: Not Found | M344: Not Found
A345: Allegra Property Management | B345: Unit 408/468 Esplanade, Torquay Qld 4655, Australia | C345: Vocus SIT | D345: Vocus Business Unlimited (AUD) | E345: 0 | F345: Vocus Business Unlimited 200 Mbps Unit 408/Unit 408/468 Esplanade, Torquay Qld 4655, Australia | G345: Not Found | H345: Not Found | I345: Not Found | J345: Not Found | K345: 15/03/2023 | L345: Not Found | M345: Not Found
A346: Armani Tobacconist | B346: Tncy 9 2875 Round Hill Rd | C346: 4677 | D346: 50Mbps/20Mbps | E346: NBN Reseller G4 | F346: 0 | G346: PPPoE | H346: Not Found | I346: AVC000181744365 | J346: Not Found | K346: Not Found | L346: Not Found | M346: Not Found
A347: Aromas Noosa | B347: LAGUNA ON HASTINGS SHOP 7, 32 HASTINGS ST, NOOSA HEADS QLD | C347: ABB | D347: NBN 50/20 | E347: FTTN | F347: 144.6.114.214 | G347: Not Found | H347: Not Found | I347: LAGUNA ON HASTINGS SHOP 7, 32 HASTINGS ST, NOOSA HEADS QLD | J347: Not Found | K347: 6 Dec 2024 | L347: Not Found | M347: Sasboss
A348: Aromas Noosa Heads | B348: 0 | C348: Not Found | D348: Not Found | E348: Not Found | F348: Not Found | G348: Not Found | H348: Not Found | I348: 0 | J348: Not Found | K348: Not Found | L348: Not Found | M348: Not Found
...

Sheet Data Feed
A1: Client Name | B1: Client Contact | C1: Client Site | D1: Service Provider | E1: Service Type 1 | F1: Service Type 2 | G1: Service Type 3 | H1: Service Type 4 | I1: Service Type 5 | J1: Connection ID | K1: Contract Term | L1: Contract Start Date | M1: Contract End Date | N1: Billing Gateway
A2: {=_xlfn.VSTACK('AAPT ExDa'!B2:B99,'ABB ExDa'!A2:A186,'Vocus SIT ExDa'!B2:B155,'Telstra ExDa'!B2:B311,'Vocus RVC ExDa'!C2:C156,'Exetel ExDa'!C2:C16,'Fusion ExDa'!B2:B16,'Infinet ExDa'!C2:C15)} -> ASG | B2: =IFERROR(VLOOKUP(A2,'Exetel ExDa'!$C$2:$N$14,4,FALSE),"No Data") -> No Data | C2: =IFERROR(VLOOKUP($A2,'AAPT ExDa'!$B$2:$U$99, 2,FALSE), IFERROR(VLOOKUP($A2,'ABB ExDa'!$A$2:$N$184, 2,FALSE), IFERROR(VLOOKUP($A2,'Vocus SIT ExDa'!$B$2:$J$173, 7,FALSE), IFERROR(VLOOKUP($A2,'Telstra ExDa'!$B$2:$K$310, 2,FALSE), IFERROR(VLOOKUP($A2,'Vocus RVC ExDa'!$C$2:$R$155, 3,FALSE), IFERROR(VLOOKUP($A2,'Fusion ExDa'!$B$2:$D$16, 2,FALSE), IFERROR(VLOOKUP($A2,'Exetel ExDa'!$C$2:$N$14, 2,FALSE), IFERROR(VLOOKUP($A2,'Infinet ExDa'!$B$2:$E$14, 2,FALSE), "Not Found")))))))) -> ASG Pinkenba | D2: =IFERROR(VLOOKUP($A2,'AAPT ExDa'!$B$2:$U$99, 15,FALSE), IFERROR(VLOOKUP($A2,'ABB ExDa'!$A$2:$N$184, 4,FALSE), IFERROR(VLOOKUP($A2,'Vocus SIT ExDa'!$B$2:$J$173, 5,FALSE), IFERROR(VLOOKUP($A2,'Telstra ExDa'!$B$2:$K$310, 8,FALSE), IFERROR(VLOOKUP($A2,'Vocus RVC ExDa'!$C$2:$R$155, 6,FALSE), IFERROR(VLOOKUP($A2,'Fusion ExDa'!$B$2:$D$16, 4,FALSE), IFERROR(VLOOKUP($A2,'Exetel ExDa'!$C$2:$N$14, 3,FALSE), IFERROR(VLOOKUP($A2,'Infinet ExDa'!$B$2:$E$14, 3,FALSE), "Not Found")))))))) -> AAPT | E2: =IFERROR(VLOOKUP($A2,'AAPT ExDa'!$B$2:$U$99, 3,FALSE), IFERROR(VLOOKUP($A2,'ABB ExDa'!$A$2:$N$184, 5,FALSE), IFERROR(VLOOKUP($A2,'Vocus SIT ExDa'!$B$2:$J$173, 2,FALSE), IFERROR(VLOOKUP($A2,'Telstra ExDa'!$B$2:$K$310, 4,FALSE), IFERROR(VLOOKUP($A2,'Vocus RVC ExDa'!$C$2:$R$155, 8,FALSE), IFERROR(VLOOKUP($A2,'Fusion ExDa'!$B$2:$D$16, 4,FALSE), IFERROR(VLOOKUP($A2,'Exetel ExDa'!$C$2:$N$14, 5,FALSE), IFERROR(VLOOKUP($A2,'Infinet ExDa'!$B$2:$E$14, 3,FALSE), "Not Found")))))))) -> IP-Line | F2: =IFERROR(VLOOKUP($A2,'AAPT ExDa'!$B$2:$U$99, 4,FALSE), IFERROR(VLOOKUP($A2,'ABB ExDa'!$A$2:$N$184, 6,FALSE), IFERROR(VLOOKUP($A2,'Vocus SIT ExDa'!$B$2:$J$173, 3,FALSE), IFERROR(VLOOKUP($A2,'Telstra ExDa'!$B$2:$K$310, 5,FALSE), IFERROR(VLOOKUP($A2,'Vocus RVC ExDa'!$C$2:$R$155, 9,FALSE), IFERROR(VLOOKUP($A2,'Fusion ExDa'!$B$2:$D$16, 0,FALSE), IFERROR(VLOOKUP($A2,'Exetel ExDa'!$C$2:$N$14, 6,FALSE), IFERROR(VLOOKUP($A2,'Infinet ExDa'!$B$2:$E$14, 0,FALSE), "Not Found")))))))) -> IP-Line Link | G2: =IFERROR(VLOOKUP($A2,'AAPT ExDa'!$B$2:$U$99, 5,FALSE), IFERROR(VLOOKUP($A2,'ABB ExDa'!$A$2:$N$184, 8,FALSE), IFERROR(VLOOKUP($A2,'Vocus SIT ExDa'!$B$2:$J$173, 6,FALSE), IFERROR(VLOOKUP($A2,'Telstra ExDa'!$B$2:$K$310, 0,FALSE), IFERROR(VLOOKUP($A2,'Vocus RVC ExDa'!$C$2:$R$155, 15,FALSE), IFERROR(VLOOKUP($A2,'Fusion ExDa'!$B$2:$D$16, 0,FALSE), IFERROR(VLOOKUP($A2,'Exetel ExDa'!$C$2:$N$14, 7,FALSE), IFERROR(VLOOKUP($A2,'Infinet ExDa'!$B$2:$E$14, 0,FALSE), "Not Found")))))))) -> Connecting IP-Line 6023265 to Access 100827488 | H2: =IFERROR(VLOOKUP($A2,'AAPT ExDa'!$B$2:$U$99, 6,FALSE), IFERROR(VLOOKUP($A2,'ABB ExDa'!$A$2:$N$184, 0,FALSE), IFERROR(VLOOKUP($A2,'Vocus SIT ExDa'!$B$2:$J$173, 0,FALSE), IFERROR(VLOOKUP($A2,'Telstra ExDa'!$B$2:$K$310, 0,FALSE), IFERROR(VLOOKUP($A2,'Vocus RVC ExDa'!$C$2:$R$155, 16,FALSE), IFERROR(VLOOKUP($A2,'Fusion ExDa'!$B$2:$D$16, 0,FALSE), IFERROR(VLOOKUP($A2,'Exetel ExDa'!$C$2:$N$14, 0,FALSE), IFERROR(VLOOKUP($A2,'Infinet ExDa'!$B$2:$E$14, 0,FALSE), "Not Found")))))))) -> Up to 100/40Mbps; AVC ID:AVC000161725867 | I2: =IFERROR(VLOOKUP($A2,'AAPT ExDa'!$B$2:$U$99, 0,FALSE), IFERROR(VLOOKUP($A2,'ABB ExDa'!$A$2:$N$184, 0,FALSE), IFERROR(VLOOKUP($A2,'Vocus SIT ExDa'!$B$2:$J$173, 0,FALSE), IFERROR(VLOOKUP($A2,'Telstra ExDa'!$B$2:$K$310, 0,FALSE), IFERROR(VLOOKUP($A2,'Vocus RVC ExDa'!$C$2:$R$155, 0,FALSE), IFERROR(VLOOKUP($A2,'Fusion ExDa'!$B$2:$D$16, 0,FALSE), IFERROR(VLOOKUP($A2,'Exetel ExDa'!$C$2:$N$14, 8,FALSE), IFERROR(VLOOKUP($A2,'Infinet ExDa'!$B$2:$E$14, 0,FALSE), "Not Found")))))))) -> Not Found | J2: =IFERROR(VLOOKUP($A2,'AAPT ExDa'!$B$2:$U$99, 7,FALSE), IFERROR(VLOOKUP($A2,'ABB ExDa'!$A$2:$N$184, 2,FALSE), IFERROR(VLOOKUP($A2,'Vocus SIT ExDa'!$B$2:$J$173, 0,FALSE), IFERROR(VLOOKUP($A2,'Telstra ExDa'!$B$2:$K$310, 7,FALSE), IFERROR(VLOOKUP($A2,'Vocus RVC ExDa'!$C$2:$R$155, 2,FALSE), IFERROR(VLOOKUP($A2,'Fusion ExDa'!$B$2:$D$16, 3,FALSE), IFERROR(VLOOKUP($A2,'Exetel ExDa'!$C$2:$N$14, 0,FALSE), IFERROR(VLOOKUP($A2,'Infinet ExDa'!$B$2:$E$14, 0,FALSE), "Not Found")))))))) -> AVC000161725867 | K2: =IFERROR(VLOOKUP($A2,'AAPT ExDa'!$B$2:$U$99, 12,FALSE), IFERROR(VLOOKUP($A2,'ABB ExDa'!$A$2:$N$184, 0,FALSE), IFERROR(VLOOKUP($A2,'Vocus SIT ExDa'!$B$2:$J$173, 0,FALSE), IFERROR(VLOOKUP($A2,'Telstra ExDa'!$B$2:$K$310, 0,FALSE), IFERROR(VLOOKUP($A2,'Vocus RVC ExDa'!$C$2:$R$155, 0,FALSE), IFERROR(VLOOKUP($A2,'Fusion ExDa'!$B$2:$D$16, 0,FALSE), IFERROR(VLOOKUP($A2,'Exetel ExDa'!$C$2:$N$14, 12,FALSE), IFERROR(VLOOKUP($A2,'Infinet ExDa'!$B$2:$E$14, 0,FALSE), "Not Found")))))))) -> 24 Months | L2: =IFERROR(VLOOKUP($A2,'AAPT ExDa'!$B$2:$U$99, 11,FALSE), IFERROR(VLOOKUP($A2,'ABB ExDa'!$A$2:$N$184, 9,FALSE), IFERROR(VLOOKUP($A2,'Vocus SIT ExDa'!$B$2:$J$173, 8,FALSE), IFERROR(VLOOKUP($A2,'Telstra ExDa'!$B$2:$K$310, 0,FALSE), IFERROR(VLOOKUP($A2,'Vocus RVC ExDa'!$C$2:$R$155, 0,FALSE), IFERROR(VLOOKUP($A2,'Fusion ExDa'!$B$2:$D$16, 0,FALSE), IFERROR(VLOOKUP($A2,'Exetel ExDa'!$C$2:$N$14, 9,FALSE), IFERROR(VLOOKUP($A2,'Infinet ExDa'!$B$2:$E$14, 0,FALSE), "Not Found")))))))) -> 45047 | M2: =IFERROR(VLOOKUP($A2,'AAPT ExDa'!$B$2:$U$99, 0,FALSE), IFERROR(VLOOKUP($A2,'ABB ExDa'!$A$2:$N$184, 0,FALSE), IFERROR(VLOOKUP($A2,'Vocus SIT ExDa'!$B$2:$J$173, 0,FALSE), IFERROR(VLOOKUP($A2,'Telstra ExDa'!$B$2:$K$310, 0,FALSE), IFERROR(VLOOKUP($A2,'Vocus RVC ExDa'!$C$2:$R$155, 0,FALSE), IFERROR(VLOOKUP($A2,'Fusion ExDa'!$B$2:$D$16, 0,FALSE), IFERROR(VLOOKUP($A2,'Exetel ExDa'!$C$2:$N$14, 11,FALSE), IFERROR(VLOOKUP($A2,'Infinet ExDa'!$B$2:$E$14, 0,FALSE), "Not Found")))))))) -> Not Found | N2: =IFERROR(VLOOKUP($A2,'AAPT ExDa'!$B$2:$U$99, 0,FALSE), IFERROR(VLOOKUP($A2,'ABB ExDa'!$A$2:$N$184, 13,FALSE), IFERROR(VLOOKUP($A2,'Vocus SIT ExDa'!$B$2:$J$173, 0,FALSE), IFERROR(VLOOKUP($A2,'Telstra ExDa'!$B$2:$K$310, 0,FALSE), IFERROR(VLOOKUP($A2,'Vocus RVC ExDa'!$C$2:$R$155, 0,FALSE), IFERROR(VLOOKUP($A2,'Fusion ExDa'!$B$2:$D$16, 0,FALSE), IFERROR(VLOOKUP($A2,'Exetel ExDa'!$C$2:$N$14, 0,FALSE), IFERROR(VLOOKUP($A2,'Infinet ExDa'!$B$2:$E$14, 0,FALSE), "Not Found")))))))) -> Not Found
A3: ASG | B3: =IFERROR(VLOOKUP(A3,'Exetel ExDa'!$C$2:$N$14,4,FALSE),"No Data") -> No Data | C3: =IFERROR(VLOOKUP(A3,'AAPT ExDa'!$B$2:$U$99, 2,FALSE), IFERROR(VLOOKUP(A3,'ABB ExDa'!$A$2:$N$184, 2,FALSE), IFERROR(VLOOKUP(A3,'Vocus SIT ExDa'!$B$2:$J$173, 7,FALSE), IFERROR(VLOOKUP(A3,'Telstra ExDa'!$B$2:$K$310, 2,FALSE), IFERROR(VLOOKUP(A3,'Vocus RVC ExDa'!$C$2:$R$155, 3,FALSE), IFERROR(VLOOKUP(A3,'Fusion ExDa'!$B$2:$D$16, 2,FALSE), IFERROR(VLOOKUP(A3,'Exetel ExDa'!$C$2:$N$14, 2,FALSE), IFERROR(VLOOKUP(A3,'Infinet ExDa'!$B$2:$E$14, 2,FALSE), "Not Found")))))))) -> ASG Pinkenba | D3: =IFERROR(VLOOKUP($A3,'AAPT ExDa'!$B$2:$U$99, 15,FALSE), IFERROR(VLOOKUP($A3,'ABB ExDa'!$A$2:$N$184, 4,FALSE), IFERROR(VLOOKUP($A3,'Vocus SIT ExDa'!$B$2:$J$173, 5,FALSE), IFERROR(VLOOKUP($A3,'Telstra ExDa'!$B$2:$K$310, 8,FALSE), IFERROR(VLOOKUP($A3,'Vocus RVC ExDa'!$C$2:$R$155, 6,FALSE), IFERROR(VLOOKUP($A3,'Fusion ExDa'!$B$2:$D$16, 4,FALSE), IFERROR(VLOOKUP($A3,'Exetel ExDa'!$C$2:$N$14, 3,FALSE), IFERROR(VLOOKUP($A3,'Infinet ExDa'!$B$2:$E$14, 3,FALSE), "Not Found")))))))) -> AAPT | E3: =IFERROR(VLOOKUP($A3,'AAPT ExDa'!$B$2:$U$99, 3,FALSE), IFERROR(VLOOKUP($A3,'ABB ExDa'!$A$2:$N$184, 5,FALSE), IFERROR(VLOOKUP($A3,'Vocus SIT ExDa'!$B$2:$J$173, 2,FALSE), IFERROR(VLOOKUP($A3,'Telstra ExDa'!$B$2:$K$310, 4,FALSE), IFERROR(VLOOKUP($A3,'Vocus RVC ExDa'!$C$2:$R$155, 8,FALSE), IFERROR(VLOOKUP($A3,'Fusion ExDa'!$B$2:$D$16, 4,FALSE), IFERROR(VLOOKUP($A3,'Exetel ExDa'!$C$2:$N$14, 5,FALSE), IFERROR(VLOOKUP($A3,'Infinet ExDa'!$B$2:$E$14, 3,FALSE), "Not Found")))))))) -> IP-Line | F3: =IFERROR(VLOOKUP($A3,'AAPT ExDa'!$B$2:$U$99, 4,FALSE), IFERROR(VLOOKUP($A3,'ABB ExDa'!$A$2:$N$184, 6,FALSE), IFERROR(VLOOKUP($A3,'Vocus SIT ExDa'!$B$2:$J$173, 3,FALSE), IFERROR(VLOOKUP($A3,'Telstra ExDa'!$B$2:$K$310, 5,FALSE), IFERROR(VLOOKUP($A3,'Vocus RVC ExDa'!$C$2:$R$155, 9,FALSE), IFERROR(VLOOKUP($A3,'Fusion ExDa'!$B$2:$D$16, 0,FALSE), IFERROR(VLOOKUP($A3,'Exetel ExDa'!$C$2:$N$14, 6,FALSE), IFERROR(VLOOKUP($A3,'Infinet ExDa'!$B$2:$E$14, 0,FALSE), "Not Found")))))))) -> IP-Line Link | G3: =IFERROR(VLOOKUP($A3,'AAPT ExDa'!$B$2:$U$99, 5,FALSE), IFERROR(VLOOKUP($A3,'ABB ExDa'!$A$2:$N$184, 8,FALSE), IFERROR(VLOOKUP($A3,'Vocus SIT ExDa'!$B$2:$J$173, 6,FALSE), IFERROR(VLOOKUP($A3,'Telstra ExDa'!$B$2:$K$310, 0,FALSE), IFERROR(VLOOKUP($A3,'Vocus RVC ExDa'!$C$2:$R$155, 15,FALSE), IFERROR(VLOOKUP($A3,'Fusion ExDa'!$B$2:$D$16, 0,FALSE), IFERROR(VLOOKUP($A3,'Exetel ExDa'!$C$2:$N$14, 7,FALSE), IFERROR(VLOOKUP($A3,'Infinet ExDa'!$B$2:$E$14, 0,FALSE), "Not Found")))))))) -> Connecting IP-Line 6023265 to Access 100827488 | H3: =IFERROR(VLOOKUP($A3,'AAPT ExDa'!$B$2:$U$99, 6,FALSE), IFERROR(VLOOKUP($A3,'ABB ExDa'!$A$2:$N$184, 0,FALSE), IFERROR(VLOOKUP($A3,'Vocus SIT ExDa'!$B$2:$J$173, 0,FALSE), IFERROR(VLOOKUP($A3,'Telstra ExDa'!$B$2:$K$310, 0,FALSE), IFERROR(VLOOKUP($A3,'Vocus RVC ExDa'!$C$2:$R$155, 16,FALSE), IFERROR(VLOOKUP($A3,'Fusion ExDa'!$B$2:$D$16, 0,FALSE), IFERROR(VLOOKUP($A3,'Exetel ExDa'!$C$2:$N$14, 0,FALSE), IFERROR(VLOOKUP($A3,'Infinet ExDa'!$B$2:$E$14, 0,FALSE), "Not Found")))))))) -> Up to 100/40Mbps; AVC ID:AVC000161725867 | I3: =IFERROR(VLOOKUP($A3,'AAPT ExDa'!$B$2:$U$99, 0,FALSE), IFERROR(VLOOKUP($A3,'ABB ExDa'!$A$2:$N$184, 0,FALSE), IFERROR(VLOOKUP($A3,'Vocus SIT ExDa'!$B$2:$J$173, 0,FALSE), IFERROR(VLOOKUP($A3,'Telstra ExDa'!$B$2:$K$310, 0,FALSE), IFERROR(VLOOKUP($A3,'Vocus RVC ExDa'!$C$2:$R$155, 0,FALSE), IFERROR(VLOOKUP($A3,'Fusion ExDa'!$B$2:$D$16, 0,FALSE), IFERROR(VLOOKUP($A3,'Exetel ExDa'!$C$2:$N$14, 8,FALSE), IFERROR(VLOOKUP($A3,'Infinet ExDa'!$B$2:$E$14, 0,FALSE), "Not Found")))))))) -> Not Found | J3: =IFERROR(VLOOKUP($A3,'AAPT ExDa'!$B$2:$U$99, 7,FALSE), IFERROR(VLOOKUP($A3,'ABB ExDa'!$A$2:$N$184, 2,FALSE), IFERROR(VLOOKUP($A3,'Vocus SIT ExDa'!$B$2:$J$173, 0,FALSE), IFERROR(VLOOKUP($A3,'Telstra ExDa'!$B$2:$K$310, 7,FALSE), IFERROR(VLOOKUP($A3,'Vocus RVC ExDa'!$C$2:$R$155, 2,FALSE), IFERROR(VLOOKUP($A3,'Fusion ExDa'!$B$2:$D$16, 3,FALSE), IFERROR(VLOOKUP($A3,'Exetel ExDa'!$C$2:$N$14, 0,FALSE), IFERROR(VLOOKUP($A3,'Infinet ExDa'!$B$2:$E$14, 0,FALSE), "Not Found")))))))) -> AVC000161725867 | K3: =IFERROR(VLOOKUP($A3,'AAPT ExDa'!$B$2:$U$99, 12,FALSE), IFERROR(VLOOKUP($A3,'ABB ExDa'!$A$2:$N$184, 0,FALSE), IFERROR(VLOOKUP($A3,'Vocus SIT ExDa'!$B$2:$J$173, 0,FALSE), IFERROR(VLOOKUP($A3,'Telstra ExDa'!$B$2:$K$310, 0,FALSE), IFERROR(VLOOKUP($A3,'Vocus RVC ExDa'!$C$2:$R$155, 0,FALSE), IFERROR(VLOOKUP($A3,'Fusion ExDa'!$B$2:$D$16, 0,FALSE), IFERROR(VLOOKUP($A3,'Exetel ExDa'!$C$2:$N$14, 12,FALSE), IFERROR(VLOOKUP($A3,'Infinet ExDa'!$B$2:$E$14, 0,FALSE), "Not Found")))))))) -> 24 Months | L3: =IFERROR(VLOOKUP($A3,'AAPT ExDa'!$B$2:$U$99, 11,FALSE), IFERROR(VLOOKUP($A3,'ABB ExDa'!$A$2:$N$184, 9,FALSE), IFERROR(VLOOKUP($A3,'Vocus SIT ExDa'!$B$2:$J$173, 8,FALSE), IFERROR(VLOOKUP($A3,'Telstra ExDa'!$B$2:$K$310, 0,FALSE), IFERROR(VLOOKUP($A3,'Vocus RVC ExDa'!$C$2:$R$155, 0,FALSE), IFERROR(VLOOKUP($A3,'Fusion ExDa'!$B$2:$D$16, 0,FALSE), IFERROR(VLOOKUP($A3,'Exetel ExDa'!$C$2:$N$14, 9,FALSE), IFERROR(VLOOKUP($A3,'Infinet ExDa'!$B$2:$E$14, 0,FALSE), "Not Found")))))))) -> 45047 | M3: =IFERROR(VLOOKUP($A3,'AAPT ExDa'!$B$2:$U$99, 0,FALSE), IFERROR(VLOOKUP($A3,'ABB ExDa'!$A$2:$N$184, 0,FALSE), IFERROR(VLOOKUP($A3,'Vocus SIT ExDa'!$B$2:$J$173, 0,FALSE), IFERROR(VLOOKUP($A3,'Telstra ExDa'!$B$2:$K$310, 0,FALSE), IFERROR(VLOOKUP($A3,'Vocus RVC ExDa'!$C$2:$R$155, 0,FALSE), IFERROR(VLOOKUP($A3,'Fusion ExDa'!$B$2:$D$16, 0,FALSE), IFERROR(VLOOKUP($A3,'Exetel ExDa'!$C$2:$N$14, 11,FALSE), IFERROR(VLOOKUP($A3,'Infinet ExDa'!$B$2:$E$14, 0,FALSE), "Not Found")))))))) -> Not Found | N3: =IFERROR(VLOOKUP($A3,'AAPT ExDa'!$B$2:$U$99, 0,FALSE), IFERROR(VLOOKUP($A3,'ABB ExDa'!$A$2:$N$184, 13,FALSE), IFERROR(VLOOKUP($A3,'Vocus SIT ExDa'!$B$2:$J$173, 0,FALSE), IFERROR(VLOOKUP($A3,'Telstra ExDa'!$B$2:$K$310, 0,FALSE), IFERROR(VLOOKUP($A3,'Vocus RVC ExDa'!$C$2:$R$155, 0,FALSE), IFERROR(VLOOKUP($A3,'Fusion ExDa'!$B$2:$D$16, 0,FALSE), IFERROR(VLOOKUP($A3,'Exetel ExDa'!$C$2:$N$14, 0,FALSE), IFERROR(VLOOKUP($A3,'Infinet ExDa'!$B$2:$E$14, 0,FALSE), "Not Found")))))))) -> Not Found
A4: ASG | B4: =IFERROR(VLOOKUP(A4,'Exetel ExDa'!$C$2:$N$14,4,FALSE),"No Data") -> No Data | C4: =IFERROR(VLOOKUP(A4,'AAPT ExDa'!$B$2:$U$99, 2,FALSE), IFERROR(VLOOKUP(A4,'ABB ExDa'!$A$2:$N$184, 2,FALSE), IFERROR(VLOOKUP(A4,'Vocus SIT ExDa'!$B$2:$J$173, 7,FALSE), IFERROR(VLOOKUP(A4,'Telstra ExDa'!$B$2:$K$310, 2,FALSE), IFERROR(VLOOKUP(A4,'Vocus RVC ExDa'!$C$2:$R$155, 3,FALSE), IFERROR(VLOOKUP(A4,'Fusion ExDa'!$B$2:$D$16, 2,FALSE), IFERROR(VLOOKUP(A4,'Exetel ExDa'!$C$2:$N$14, 2,FALSE), IFERROR(VLOOKUP(A4,'Infinet ExDa'!$B$2:$E$14, 2,FALSE), "Not Found")))))))) -> ASG Pinkenba | D4: =IFERROR(VLOOKUP($A4,'AAPT ExDa'!$B$2:$U$99, 15,FALSE), IFERROR(VLOOKUP($A4,'ABB ExDa'!$A$2:$N$184, 4,FALSE), IFERROR(VLOOKUP($A4,'Vocus SIT ExDa'!$B$2:$J$173, 5,FALSE), IFERROR(VLOOKUP($A4,'Telstra ExDa'!$B$2:$K$310, 8,FALSE), IFERROR(VLOOKUP($A4,'Vocus RVC ExDa'!$C$2:$R$155, 6,FALSE), IFERROR(VLOOKUP($A4,'Fusion ExDa'!$B$2:$D$16, 4,FALSE), IFERROR(VLOOKUP($A4,'Exetel ExDa'!$C$2:$N$14, 3,FALSE), IFERROR(VLOOKUP($A4,'Infinet ExDa'!$B$2:$E$14, 3,FALSE), "Not Found")))))))) -> AAPT | E4: =IFERROR(VLOOKUP($A4,'AAPT ExDa'!$B$2:$U$99, 3,FALSE), IFERROR(VLOOKUP($A4,'ABB ExDa'!$A$2:$N$184, 5,FALSE), IFERROR(VLOOKUP($A4,'Vocus SIT ExDa'!$B$2:$J$173, 2,FALSE), IFERROR(VLOOKUP($A4,'Telstra ExDa'!$B$2:$K$310, 4,FALSE), IFERROR(VLOOKUP($A4,'Vocus RVC ExDa'!$C$2:$R$155, 8,FALSE), IFERROR(VLOOKUP($A4,'Fusion ExDa'!$B$2:$D$16, 4,FALSE), IFERROR(VLOOKUP($A4,'Exetel ExDa'!$C$2:$N$14, 5,FALSE), IFERROR(VLOOKUP($A4,'Infinet ExDa'!$B$2:$E$14, 3,FALSE), "Not Found")))))))) -> IP-Line | F4: =IFERROR(VLOOKUP($A4,'AAPT ExDa'!$B$2:$U$99, 4,FALSE), IFERROR(VLOOKUP($A4,'ABB ExDa'!$A$2:$N$184, 6,FALSE), IFERROR(VLOOKUP($A4,'Vocus SIT ExDa'!$B$2:$J$173, 3,FALSE), IFERROR(VLOOKUP($A4,'Telstra ExDa'!$B$2:$K$310, 5,FALSE), IFERROR(VLOOKUP($A4,'Vocus RVC ExDa'!$C$2:$R$155, 9,FALSE), IFERROR(VLOOKUP($A4,'Fusion ExDa'!$B$2:$D$16, 0,FALSE), IFERROR(VLOOKUP($A4,'Exetel ExDa'!$C$2:$N$14, 6,FALSE), IFERROR(VLOOKUP($A4,'Infinet ExDa'!$B$2:$E$14, 0,FALSE), "Not Found")))))))) -> IP-Line Link | G4: =IFERROR(VLOOKUP($A4,'AAPT ExDa'!$B$2:$U$99, 5,FALSE), IFERROR(VLOOKUP($A4,'ABB ExDa'!$A$2:$N$184, 8,FALSE), IFERROR(VLOOKUP($A4,'Vocus SIT ExDa'!$B$2:$J$173, 6,FALSE), IFERROR(VLOOKUP($A4,'Telstra ExDa'!$B$2:$K$310, 0,FALSE), IFERROR(VLOOKUP($A4,'Vocus RVC ExDa'!$C$2:$R$155, 15,FALSE), IFERROR(VLOOKUP($A4,'Fusion ExDa'!$B$2:$D$16, 0,FALSE), IFERROR(VLOOKUP($A4,'Exetel ExDa'!$C$2:$N$14, 7,FALSE), IFERROR(VLOOKUP($A4,'Infinet ExDa'!$B$2:$E$14, 0,FALSE), "Not Found")))))))) -> Connecting IP-Line 6023265 to Access 100827488 | H4: =IFERROR(VLOOKUP($A4,'AAPT ExDa'!$B$2:$U$99, 6,FALSE), IFERROR(VLOOKUP($A4,'ABB ExDa'!$A$2:$N$184, 0,FALSE), IFERROR(VLOOKUP($A4,'Vocus SIT ExDa'!$B$2:$J$173, 0,FALSE), IFERROR(VLOOKUP($A4,'Telstra ExDa'!$B$2:$K$310, 0,FALSE), IFERROR(VLOOKUP($A4,'Vocus RVC ExDa'!$C$2:$R$155, 16,FALSE), IFERROR(VLOOKUP($A4,'Fusion ExDa'!$B$2:$D$16, 0,FALSE), IFERROR(VLOOKUP($A4,'Exetel ExDa'!$C$2:$N$14, 0,FALSE), IFERROR(VLOOKUP($A4,'Infinet ExDa'!$B$2:$E$14, 0,FALSE), "Not Found")))))))) -> Up to 100/40Mbps; AVC ID:AVC000161725867 | I4: =IFERROR(VLOOKUP($A4,'AAPT ExDa'!$B$2:$U$99, 0,FALSE), IFERROR(VLOOKUP($A4,'ABB ExDa'!$A$2:$N$184, 0,FALSE), IFERROR(VLOOKUP($A4,'Vocus SIT ExDa'!$B$2:$J$173, 0,FALSE), IFERROR(VLOOKUP($A4,'Telstra ExDa'!$B$2:$K$310, 0,FALSE), IFERROR(VLOOKUP($A4,'Vocus RVC ExDa'!$C$2:$R$155, 0,FALSE), IFERROR(VLOOKUP($A4,'Fusion ExDa'!$B$2:$D$16, 0,FALSE), IFERROR(VLOOKUP($A4,'Exetel ExDa'!$C$2:$N$14, 8,FALSE), IFERROR(VLOOKUP($A4,'Infinet ExDa'!$B$2:$E$14, 0,FALSE), "Not Found")))))))) -> Not Found | J4: =IFERROR(VLOOKUP($A4,'AAPT ExDa'!$B$2:$U$99, 7,FALSE), IFERROR(VLOOKUP($A4,'ABB ExDa'!$A$2:$N$184, 2,FALSE), IFERROR(VLOOKUP($A4,'Vocus SIT ExDa'!$B$2:$J$173, 0,FALSE), IFERROR(VLOOKUP($A4,'Telstra ExDa'!$B$2:$K$310, 7,FALSE), IFERROR(VLOOKUP($A4,'Vocus RVC ExDa'!$C$2:$R$155, 2,FALSE), IFERROR(VLOOKUP($A4,'Fusion ExDa'!$B$2:$D$16, 3,FALSE), IFERROR(VLOOKUP($A4,'Exetel ExDa'!$C$2:$N$14, 0,FALSE), IFERROR(VLOOKUP($A4,'Infinet ExDa'!$B$2:$E$14, 0,FALSE), "Not Found")))))))) -> AVC000161725867 | K4: =IFERROR(VLOOKUP($A4,'AAPT ExDa'!$B$2:$U$99, 12,FALSE), IFERROR(VLOOKUP($A4,'ABB ExDa'!$A$2:$N$184, 0,FALSE), IFERROR(VLOOKUP($A4,'Vocus SIT ExDa'!$B$2:$J$173, 0,FALSE), IFERROR(VLOOKUP($A4,'Telstra ExDa'!$B$2:$K$310, 0,FALSE), IFERROR(VLOOKUP($A4,'Vocus RVC ExDa'!$C$2:$R$155, 0,FALSE), IFERROR(VLOOKUP($A4,'Fusion ExDa'!$B$2:$D$16, 0,FALSE), IFERROR(VLOOKUP($A4,'Exetel ExDa'!$C$2:$N$14, 12,FALSE), IFERROR(VLOOKUP($A4,'Infinet ExDa'!$B$2:$E$14, 0,FALSE), "Not Found")))))))) -> 24 Months | L4: =IFERROR(VLOOKUP($A4,'AAPT ExDa'!$B$2:$U$99, 11,FALSE), IFERROR(VLOOKUP($A4,'ABB ExDa'!$A$2:$N$184, 9,FALSE), IFERROR(VLOOKUP($A4,'Vocus SIT ExDa'!$B$2:$J$173, 8,FALSE), IFERROR(VLOOKUP($A4,'Telstra ExDa'!$B$2:$K$310, 0,FALSE), IFERROR(VLOOKUP($A4,'Vocus RVC ExDa'!$C$2:$R$155, 0,FALSE), IFERROR(VLOOKUP($A4,'Fusion ExDa'!$B$2:$D$16, 0,FALSE), IFERROR(VLOOKUP($A4,'Exetel ExDa'!$C$2:$N$14, 9,FALSE), IFERROR(VLOOKUP($A4,'Infinet ExDa'!$B$2:$E$14, 0,FALSE), "Not Found")))))))) -> 45047 | M4: =IFERROR(VLOOKUP($A4,'AAPT ExDa'!$B$2:$U$99, 0,FALSE), IFERROR(VLOOKUP($A4,'ABB ExDa'!$A$2:$N$184, 0,FALSE), IFERROR(VLOOKUP($A4,'Vocus SIT ExDa'!$B$2:$J$173, 0,FALSE), IFERROR(VLOOKUP($A4,'Telstra ExDa'!$B$2:$K$310, 0,FALSE), IFERROR(VLOOKUP($A4,'Vocus RVC ExDa'!$C$2:$R$155, 0,FALSE), IFERROR(VLOOKUP($A4,'Fusion ExDa'!$B$2:$D$16, 0,FALSE), IFERROR(VLOOKUP($A4,'Exetel ExDa'!$C$2:$N$14, 11,FALSE), IFERROR(VLOOKUP($A4,'Infinet ExDa'!$B$2:$E$14, 0,FALSE), "Not Found")))))))) -> Not Found | N4: =IFERROR(VLOOKUP($A4,'AAPT ExDa'!$B$2:$U$99, 0,FALSE), IFERROR(VLOOKUP($A4,'ABB ExDa'!$A$2:$N$184, 13,FALSE), IFERROR(VLOOKUP($A4,'Vocus SIT ExDa'!$B$2:$J$173, 0,FALSE), IFERROR(VLOOKUP($A4,'Telstra ExDa'!$B$2:$K$310, 0,FALSE), IFERROR(VLOOKUP($A4,'Vocus RVC ExDa'!$C$2:$R$155, 0,FALSE), IFERROR(VLOOKUP($A4,'Fusion ExDa'!$B$2:$D$16, 0,FALSE), IFERROR(VLOOKUP($A4,'Exetel ExDa'!$C$2:$N$14, 0,FALSE), IFERROR(VLOOKUP($A4,'Infinet ExDa'!$B$2:$E$14, 0,FALSE), "Not Found")))))))) -> Not Found
A5: ASG | B5: =IFERROR(VLOOKUP(A5,'Exetel ExDa'!$C$2:$N$14,4,FALSE),"No Data") -> No Data | C5: =IFERROR(VLOOKUP(A5,'AAPT ExDa'!$B$2:$U$99, 2,FALSE), IFERROR(VLOOKUP(A5,'ABB ExDa'!$A$2:$N$184, 2,FALSE), IFERROR(VLOOKUP(A5,'Vocus SIT ExDa'!$B$2:$J$173, 7,FALSE), IFERROR(VLOOKUP(A5,'Telstra ExDa'!$B$2:$K$310, 2,FALSE), IFERROR(VLOOKUP(A5,'Vocus RVC ExDa'!$C$2:$R$155, 3,FALSE), IFERROR(VLOOKUP(A5,'Fusion ExDa'!$B$2:$D$16, 2,FALSE), IFERROR(VLOOKUP(A5,'Exetel ExDa'!$C$2:$N$14, 2,FALSE), IFERROR(VLOOKUP(A5,'Infinet ExDa'!$B$2:$E$14, 2,FALSE), "Not Found")))))))) -> ASG Pinkenba | D5: =IFERROR(VLOOKUP($A5,'AAPT ExDa'!$B$2:$U$99, 15,FALSE), IFERROR(VLOOKUP($A5,'ABB ExDa'!$A$2:$N$184, 4,FALSE), IFERROR(VLOOKUP($A5,'Vocus SIT ExDa'!$B$2:$J$173, 5,FALSE), IFERROR(VLOOKUP($A5,'Telstra ExDa'!$B$2:$K$310, 8,FALSE), IFERROR(VLOOKUP($A5,'Vocus RVC ExDa'!$C$2:$R$155, 6,FALSE), IFERROR(VLOOKUP($A5,'Fusion ExDa'!$B$2:$D$16, 4,FALSE), IFERROR(VLOOKUP($A5,'Exetel ExDa'!$C$2:$N$14, 3,FALSE), IFERROR(VLOOKUP($A5,'Infinet ExDa'!$B$2:$E$14, 3,FALSE), "Not Found")))))))) -> AAPT | E5: =IFERROR(VLOOKUP($A5,'AAPT ExDa'!$B$2:$U$99, 3,FALSE), IFERROR(VLOOKUP($A5,'ABB ExDa'!$A$2:$N$184, 5,FALSE), IFERROR(VLOOKUP($A5,'Vocus SIT ExDa'!$B$2:$J$173, 2,FALSE), IFERROR(VLOOKUP($A5,'Telstra ExDa'!$B$2:$K$310, 4,FALSE), IFERROR(VLOOKUP($A5,'Vocus RVC ExDa'!$C$2:$R$155, 8,FALSE), IFERROR(VLOOKUP($A5,'Fusion ExDa'!$B$2:$D$16, 4,FALSE), IFERROR(VLOOKUP($A5,'Exetel ExDa'!$C$2:$N$14, 5,FALSE), IFERROR(VLOOKUP($A5,'Infinet ExDa'!$B$2:$E$14, 3,FALSE), "Not Found")))))))) -> IP-Line | F5: =IFERROR(VLOOKUP($A5,'AAPT ExDa'!$B$2:$U$99, 4,FALSE), IFERROR(VLOOKUP($A5,'ABB ExDa'!$A$2:$N$184, 6,FALSE), IFERROR(VLOOKUP($A5,'Vocus SIT ExDa'!$B$2:$J$173, 3,FALSE), IFERROR(VLOOKUP($A5,'Telstra ExDa'!$B$2:$K$310, 5,FALSE), IFERROR(VLOOKUP($A5,'Vocus RVC ExDa'!$C$2:$R$155, 9,FALSE), IFERROR(VLOOKUP($A5,'Fusion ExDa'!$B$2:$D$16, 0,FALSE), IFERROR(VLOOKUP($A5,'Exetel ExDa'!$C$2:$N$14, 6,FALSE), IFERROR(VLOOKUP($A5,'Infinet ExDa'!$B$2:$E$14, 0,FALSE), "Not Found")))))))) -> IP-Line Link | G5: =IFERROR(VLOOKUP($A5,'AAPT ExDa'!$B$2:$U$99, 5,FALSE), IFERROR(VLOOKUP($A5,'ABB ExDa'!$A$2:$N$184, 8,FALSE), IFERROR(VLOOKUP($A5,'Vocus SIT ExDa'!$B$2:$J$173, 6,FALSE), IFERROR(VLOOKUP($A5,'Telstra ExDa'!$B$2:$K$310, 0,FALSE), IFERROR(VLOOKUP($A5,'Vocus RVC ExDa'!$C$2:$R$155, 15,FALSE), IFERROR(VLOOKUP($A5,'Fusion ExDa'!$B$2:$D$16, 0,FALSE), IFERROR(VLOOKUP($A5,'Exetel ExDa'!$C$2:$N$14, 7,FALSE), IFERROR(VLOOKUP($A5,'Infinet ExDa'!$B$2:$E$14, 0,FALSE), "Not Found")))))))) -> Connecting IP-Line 6023265 to Access 100827488 | H5: =IFERROR(VLOOKUP($A5,'AAPT ExDa'!$B$2:$U$99, 6,FALSE), IFERROR(VLOOKUP($A5,'ABB ExDa'!$A$2:$N$184, 0,FALSE), IFERROR(VLOOKUP($A5,'Vocus SIT ExDa'!$B$2:$J$173, 0,FALSE), IFERROR(VLOOKUP($A5,'Telstra ExDa'!$B$2:$K$310, 0,FALSE), IFERROR(VLOOKUP($A5,'Vocus RVC ExDa'!$C$2:$R$155, 16,FALSE), IFERROR(VLOOKUP($A5,'Fusion ExDa'!$B$2:$D$16, 0,FALSE), IFERROR(VLOOKUP($A5,'Exetel ExDa'!$C$2:$N$14, 0,FALSE), IFERROR(VLOOKUP($A5,'Infinet ExDa'!$B$2:$E$14, 0,FALSE), "Not Found")))))))) -> Up to 100/40Mbps; AVC ID:AVC000161725867 | I5: =IFERROR(VLOOKUP($A5,'AAPT ExDa'!$B$2:$U$99, 0,FALSE), IFERROR(VLOOKUP($A5,'ABB ExDa'!$A$2:$N$184, 0,FALSE), IFERROR(VLOOKUP($A5,'Vocus SIT ExDa'!$B$2:$J$173, 0,FALSE), IFERROR(VLOOKUP($A5,'Telstra ExDa'!$B$2:$K$310, 0,FALSE), IFERROR(VLOOKUP($A5,'Vocus RVC ExDa'!$C$2:$R$155, 0,FALSE), IFERROR(VLOOKUP($A5,'Fusion ExDa'!$B$2:$D$16, 0,FALSE), IFERROR(VLOOKUP($A5,'Exetel ExDa'!$C$2:$N$14, 8,FALSE), IFERROR(VLOOKUP($A5,'Infinet ExDa'!$B$2:$E$14, 0,FALSE), "Not Found")))))))) -> Not Found | J5: =IFERROR(VLOOKUP($A5,'AAPT ExDa'!$B$2:$U$99, 7,FALSE), IFERROR(VLOOKUP($A5,'ABB ExDa'!$A$2:$N$184, 2,FALSE), IFERROR(VLOOKUP($A5,'Vocus SIT ExDa'!$B$2:$J$173, 0,FALSE), IFERROR(VLOOKUP($A5,'Telstra ExDa'!$B$2:$K$310, 7,FALSE), IFERROR(VLOOKUP($A5,'Vocus RVC ExDa'!$C$2:$R$155, 2,FALSE), IFERROR(VLOOKUP($A5,'Fusion ExDa'!$B$2:$D$16, 3,FALSE), IFERROR(VLOOKUP($A5,'Exetel ExDa'!$C$2:$N$14, 0,FALSE), IFERROR(VLOOKUP($A5,'Infinet ExDa'!$B$2:$E$14, 0,FALSE), "Not Found")))))))) -> AVC000161725867 | K5: =IFERROR(VLOOKUP($A5,'AAPT ExDa'!$B$2:$U$99, 12,FALSE), IFERROR(VLOOKUP($A5,'ABB ExDa'!$A$2:$N$184, 0,FALSE), IFERROR(VLOOKUP($A5,'Vocus SIT ExDa'!$B$2:$J$173, 0,FALSE), IFERROR(VLOOKUP($A5,'Telstra ExDa'!$B$2:$K$310, 0,FALSE), IFERROR(VLOOKUP($A5,'Vocus RVC ExDa'!$C$2:$R$155, 0,FALSE), IFERROR(VLOOKUP($A5,'Fusion ExDa'!$B$2:$D$16, 0,FALSE), IFERROR(VLOOKUP($A5,'Exetel ExDa'!$C$2:$N$14, 12,FALSE), IFERROR(VLOOKUP($A5,'Infinet ExDa'!$B$2:$E$14, 0,FALSE), "Not Found")))))))) -> 24 Months | L5: =IFERROR(VLOOKUP($A5,'AAPT ExDa'!$B$2:$U$99, 11,FALSE), IFERROR(VLOOKUP($A5,'ABB ExDa'!$A$2:$N$184, 9,FALSE), IFERROR(VLOOKUP($A5,'Vocus SIT ExDa'!$B$2:$J$173, 8,FALSE), IFERROR(VLOOKUP($A5,'Telstra ExDa'!$B$2:$K$310, 0,FALSE), IFERROR(VLOOKUP($A5,'Vocus RVC ExDa'!$C$2:$R$155, 0,FALSE), IFERROR(VLOOKUP($A5,'Fusion ExDa'!$B$2:$D$16, 0,FALSE), IFERROR(VLOOKUP($A5,'Exetel ExDa'!$C$2:$N$14, 9,FALSE), IFERROR(VLOOKUP($A5,'Infinet ExDa'!$B$2:$E$14, 0,FALSE), "Not Found")))))))) -> 45047 | M5: =IFERROR(VLOOKUP($A5,'AAPT ExDa'!$B$2:$U$99, 0,FALSE), IFERROR(VLOOKUP($A5,'ABB ExDa'!$A$2:$N$184, 0,FALSE), IFERROR(VLOOKUP($A5,'Vocus SIT ExDa'!$B$2:$J$173, 0,FALSE), IFERROR(VLOOKUP($A5,'Telstra ExDa'!$B$2:$K$310, 0,FALSE), IFERROR(VLOOKUP($A5,'Vocus RVC ExDa'!$C$2:$R$155, 0,FALSE), IFERROR(VLOOKUP($A5,'Fusion ExDa'!$B$2:$D$16, 0,FALSE), IFERROR(VLOOKUP($A5,'Exetel ExDa'!$C$2:$N$14, 11,FALSE), IFERROR(VLOOKUP($A5,'Infinet ExDa'!$B$2:$E$14, 0,FALSE), "Not Found")))))))) -> Not Found | N5: =IFERROR(VLOOKUP($A5,'AAPT ExDa'!$B$2:$U$99, 0,FALSE), IFERROR(VLOOKUP($A5,'ABB ExDa'!$A$2:$N$184, 13,FALSE), IFERROR(VLOOKUP($A5,'Vocus SIT ExDa'!$B$2:$J$173, 0,FALSE), IFERROR(VLOOKUP($A5,'Telstra ExDa'!$B$2:$K$310, 0,FALSE), IFERROR(VLOOKUP($A5,'Vocus RVC ExDa'!$C$2:$R$155, 0,FALSE), IFERROR(VLOOKUP($A5,'Fusion ExDa'!$B$2:$D$16, 0,FALSE), IFERROR(VLOOKUP($A5,'Exetel ExDa'!$C$2:$N$14, 0,FALSE), IFERROR(VLOOKUP($A5,'Infinet ExDa'!$B$2:$E$14, 0,FALSE), "Not Found")))))))) -> Not Found
A6: Auriga Group | B6: =IFERROR(VLOOKUP(A6,'Exetel ExDa'!$C$2:$N$14,4,FALSE),"No Data") -> No Data | C6: =IFERROR(VLOOKUP(A6,'AAPT ExDa'!$B$2:$U$99, 2,FALSE), IFERROR(VLOOKUP(A6,'ABB ExDa'!$A$2:$N$184, 2,FALSE), IFERROR(VLOOKUP(A6,'Vocus SIT ExDa'!$B$2:$J$173, 7,FALSE), IFERROR(VLOOKUP(A6,'Telstra ExDa'!$B$2:$K$310, 2,FALSE), IFERROR(VLOOKUP(A6,'Vocus RVC ExDa'!$C$2:$R$155, 3,FALSE), IFERROR(VLOOKUP(A6,'Fusion ExDa'!$B$2:$D$16, 2,FALSE), IFERROR(VLOOKUP(A6,'Exetel ExDa'!$C$2:$N$14, 2,FALSE), IFERROR(VLOOKUP(A6,'Infinet ExDa'!$B$2:$E$14, 2,FALSE), "Not Found")))))))) -> Albion | D6: =IFERROR(VLOOKUP($A6,'AAPT ExDa'!$B$2:$U$99, 15,FALSE), IFERROR(VLOOKUP($A6,'ABB ExDa'!$A$2:$N$184, 4,FALSE), IFERROR(VLOOKUP($A6,'Vocus SIT ExDa'!$B$2:$J$173, 5,FALSE), IFERROR(VLOOKUP($A6,'Telstra ExDa'!$B$2:$K$310, 8,FALSE), IFERROR(VLOOKUP($A6,'Vocus RVC ExDa'!$C$2:$R$155, 6,FALSE), IFERROR(VLOOKUP($A6,'Fusion ExDa'!$B$2:$D$16, 4,FALSE), IFERROR(VLOOKUP($A6,'Exetel ExDa'!$C$2:$N$14, 3,FALSE), IFERROR(VLOOKUP($A6,'Infinet ExDa'!$B$2:$E$14, 3,FALSE), "Not Found")))))))) -> AAPT | E6: =IFERROR(VLOOKUP($A6,'AAPT ExDa'!$B$2:$U$99, 3,FALSE), IFERROR(VLOOKUP($A6,'ABB ExDa'!$A$2:$N$184, 5,FALSE), IFERROR(VLOOKUP($A6,'Vocus SIT ExDa'!$B$2:$J$173, 2,FALSE), IFERROR(VLOOKUP($A6,'Telstra ExDa'!$B$2:$K$310, 4,FALSE), IFERROR(VLOOKUP($A6,'Vocus RVC ExDa'!$C$2:$R$155, 8,FALSE), IFERROR(VLOOKUP($A6,'Fusion ExDa'!$B$2:$D$16, 4,FALSE), IFERROR(VLOOKUP($A6,'Exetel ExDa'!$C$2:$N$14, 5,FALSE), IFERROR(VLOOKUP($A6,'Infinet ExDa'!$B$2:$E$14, 3,FALSE), "Not Found")))))))) -> FAST Fibre | F6: =IFERROR(VLOOKUP($A6,'AAPT ExDa'!$B$2:$U$99, 4,FALSE), IFERROR(VLOOKUP($A6,'ABB ExDa'!$A$2:$N$184, 6,FALSE), IFERROR(VLOOKUP($A6,'Vocus SIT ExDa'!$B$2:$J$173, 3,FALSE), IFERROR(VLOOKUP($A6,'Telstra ExDa'!$B$2:$K$310, 5,FALSE), IFERROR(VLOOKUP($A6,'Vocus RVC ExDa'!$C$2:$R$155, 9,FALSE), IFERROR(VLOOKUP($A6,'Fusion ExDa'!$B$2:$D$16, 0,FALSE), IFERROR(VLOOKUP($A6,'Exetel ExDa'!$C$2:$N$14, 6,FALSE), IFERROR(VLOOKUP($A6,'Infinet ExDa'!$B$2:$E$14, 0,FALSE), "Not Found")))))))) -> FAST Fibre (NTU) | G6: =IFERROR(VLOOKUP($A6,'AAPT ExDa'!$B$2:$U$99, 5,FALSE), IFERROR(VLOOKUP($A6,'ABB ExDa'!$A$2:$N$184, 8,FALSE), IFERROR(VLOOKUP($A6,'Vocus SIT ExDa'!$B$2:$J$173, 6,FALSE), IFERROR(VLOOKUP($A6,'Telstra ExDa'!$B$2:$K$310, 0,FALSE), IFERROR(VLOOKUP($A6,'Vocus RVC ExDa'!$C$2:$R$155, 15,FALSE), IFERROR(VLOOKUP($A6,'Fusion ExDa'!$B$2:$D$16, 0,FALSE), IFERROR(VLOOKUP($A6,'Exetel ExDa'!$C$2:$N$14, 7,FALSE), IFERROR(VLOOKUP($A6,'Infinet ExDa'!$B$2:$E$14, 0,FALSE), "Not Found")))))))) -> 0 | H6: =IFERROR(VLOOKUP($A6,'AAPT ExDa'!$B$2:$U$99, 6,FALSE), IFERROR(VLOOKUP($A6,'ABB ExDa'!$A$2:$N$184, 0,FALSE), IFERROR(VLOOKUP($A6,'Vocus SIT ExDa'!$B$2:$J$173, 0,FALSE), IFERROR(VLOOKUP($A6,'Telstra ExDa'!$B$2:$K$310, 0,FALSE), IFERROR(VLOOKUP($A6,'Vocus RVC ExDa'!$C$2:$R$155, 16,FALSE), IFERROR(VLOOKUP($A6,'Fusion ExDa'!$B$2:$D$16, 0,FALSE), IFERROR(VLOOKUP($A6,'Exetel ExDa'!$C$2:$N$14, 0,FALSE), IFERROR(VLOOKUP($A6,'Infinet ExDa'!$B$2:$E$14, 0,FALSE), "Not Found")))))))) -> 400 Mbps; 36 Months | I6: =IFERROR(VLOOKUP($A6,'AAPT ExDa'!$B$2:$U$99, 0,FALSE), IFERROR(VLOOKUP($A6,'ABB ExDa'!$A$2:$N$184, 0,FALSE), IFERROR(VLOOKUP($A6,'Vocus SIT ExDa'!$B$2:$J$173, 0,FALSE), IFERROR(VLOOKUP($A6,'Telstra ExDa'!$B$2:$K$310, 0,FALSE), IFERROR(VLOOKUP($A6,'Vocus RVC ExDa'!$C$2:$R$155, 0,FALSE), IFERROR(VLOOKUP($A6,'Fusion ExDa'!$B$2:$D$16, 0,FALSE), IFERROR(VLOOKUP($A6,'Exetel ExDa'!$C$2:$N$14, 8,FALSE), IFERROR(VLOOKUP($A6,'Infinet ExDa'!$B$2:$E$14, 0,FALSE), "Not Found")))))))) -> Not Found | J6: =IFERROR(VLOOKUP($A6,'AAPT ExDa'!$B$2:$U$99, 7,FALSE), IFERROR(VLOOKUP($A6,'ABB ExDa'!$A$2:$N$184, 2,FALSE), IFERROR(VLOOKUP($A6,'Vocus SIT ExDa'!$B$2:$J$173, 0,FALSE), IFERROR(VLOOKUP($A6,'Telstra ExDa'!$B$2:$K$310, 7,FALSE), IFERROR(VLOOKUP($A6,'Vocus RVC ExDa'!$C$2:$R$155, 2,FALSE), IFERROR(VLOOKUP($A6,'Fusion ExDa'!$B$2:$D$16, 3,FALSE), IFERROR(VLOOKUP($A6,'Exetel ExDa'!$C$2:$N$14, 0,FALSE), IFERROR(VLOOKUP($A6,'Infinet ExDa'!$B$2:$E$14, 0,FALSE), "Not Found")))))))) -> 0 | K6: =IFERROR(VLOOKUP($A6,'AAPT ExDa'!$B$2:$U$99, 12,FALSE), IFERROR(VLOOKUP($A6,'ABB ExDa'!$A$2:$N$184, 0,FALSE), IFERROR(VLOOKUP($A6,'Vocus SIT ExDa'!$B$2:$J$173, 0,FALSE), IFERROR(VLOOKUP($A6,'Telstra ExDa'!$B$2:$K$310, 0,FALSE), IFERROR(VLOOKUP($A6,'Vocus RVC ExDa'!$C$2:$R$155, 0,FALSE), IFERROR(VLOOKUP($A6,'Fusion ExDa'!$B$2:$D$16, 0,FALSE), IFERROR(VLOOKUP($A6,'Exetel ExDa'!$C$2:$N$14, 12,FALSE), IFERROR(VLOOKUP($A6,'Infinet ExDa'!$B$2:$E$14, 0,FALSE), "Not Found")))))))) -> 36 Months | L6: =IFERROR(VLOOKUP($A6,'AAPT ExDa'!$B$2:$U$99, 11,FALSE), IFERROR(VLOOKUP($A6,'ABB ExDa'!$A$2:$N$184, 9,FALSE), IFERROR(VLOOKUP($A6,'Vocus SIT ExDa'!$B$2:$J$173, 8,FALSE), IFERROR(VLOOKUP($A6,'Telstra ExDa'!$B$2:$K$310, 0,FALSE), IFERROR(VLOOKUP($A6,'Vocus RVC ExDa'!$C$2:$R$155, 0,FALSE), IFERROR(VLOOKUP($A6,'Fusion ExDa'!$B$2:$D$16, 0,FALSE), IFERROR(VLOOKUP($A6,'Exetel ExDa'!$C$2:$N$14, 9,FALSE), IFERROR(VLOOKUP($A6,'Infinet ExDa'!$B$2:$E$14, 0,FALSE), "Not Found")))))))) -> 15/04/2022 | M6: =IFERROR(VLOOKUP($A6,'AAPT ExDa'!$B$2:$U$99, 0,FALSE), IFERROR(VLOOKUP($A6,'ABB ExDa'!$A$2:$N$184, 0,FALSE), IFERROR(VLOOKUP($A6,'Vocus SIT ExDa'!$B$2:$J$173, 0,FALSE), IFERROR(VLOOKUP($A6,'Telstra ExDa'!$B$2:$K$310, 0,FALSE), IFERROR(VLOOKUP($A6,'Vocus RVC ExDa'!$C$2:$R$155, 0,FALSE), IFERROR(VLOOKUP($A6,'Fusion ExDa'!$B$2:$D$16, 0,FALSE), IFERROR(VLOOKUP($A6,'Exetel ExDa'!$C$2:$N$14, 11,FALSE), IFERROR(VLOOKUP($A6,'Infinet ExDa'!$B$2:$E$14, 0,FALSE), "Not Found")))))))) -> Not Found | N6: =IFERROR(VLOOKUP($A6,'AAPT ExDa'!$B$2:$U$99, 0,FALSE), IFERROR(VLOOKUP($A6,'ABB ExDa'!$A$2:$N$184, 13,FALSE), IFERROR(VLOOKUP($A6,'Vocus SIT ExDa'!$B$2:$J$173, 0,FALSE), IFERROR(VLOOKUP($A6,'Telstra ExDa'!$B$2:$K$310, 0,FALSE), IFERROR(VLOOKUP($A6,'Vocus RVC ExDa'!$C$2:$R$155, 0,FALSE), IFERROR(VLOOKUP($A6,'Fusion ExDa'!$B$2:$D$16, 0,FALSE), IFERROR(VLOOKUP($A6,'Exetel ExDa'!$C$2:$N$14, 0,FALSE), IFERROR(VLOOKUP($A6,'Infinet ExDa'!$B$2:$E$14, 0,FALSE), "Not Found")))))))) -> Not Found
A7: Auriga Group | B7: =IFERROR(VLOOKUP(A7,'Exetel ExDa'!$C$2:$N$14,4,FALSE),"No Data") -> No Data | C7: =IFERROR(VLOOKUP(A7,'AAPT ExDa'!$B$2:$U$99, 2,FALSE), IFERROR(VLOOKUP(A7,'ABB ExDa'!$A$2:$N$184, 2,FALSE), IFERROR(VLOOKUP(A7,'Vocus SIT ExDa'!$B$2:$J$173, 7,FALSE), IFERROR(VLOOKUP(A7,'Telstra ExDa'!$B$2:$K$310, 2,FALSE), IFERROR(VLOOKUP(A7,'Vocus RVC ExDa'!$C$2:$R$155, 3,FALSE), IFERROR(VLOOKUP(A7,'Fusion ExDa'!$B$2:$D$16, 2,FALSE), IFERROR(VLOOKUP(A7,'Exetel ExDa'!$C$2:$N$14, 2,FALSE), IFERROR(VLOOKUP(A7,'Infinet ExDa'!$B$2:$E$14, 2,FALSE), "Not Found")))))))) -> Albion | D7: =IFERROR(VLOOKUP($A7,'AAPT ExDa'!$B$2:$U$99, 15,FALSE), IFERROR(VLOOKUP($A7,'ABB ExDa'!$A$2:$N$184, 4,FALSE), IFERROR(VLOOKUP($A7,'Vocus SIT ExDa'!$B$2:$J$173, 5,FALSE), IFERROR(VLOOKUP($A7,'Telstra ExDa'!$B$2:$K$310, 8,FALSE), IFERROR(VLOOKUP($A7,'Vocus RVC ExDa'!$C$2:$R$155, 6,FALSE), IFERROR(VLOOKUP($A7,'Fusion ExDa'!$B$2:$D$16, 4,FALSE), IFERROR(VLOOKUP($A7,'Exetel ExDa'!$C$2:$N$14, 3,FALSE), IFERROR(VLOOKUP($A7,'Infinet ExDa'!$B$2:$E$14, 3,FALSE), "Not Found")))))))) -> AAPT | E7: =IFERROR(VLOOKUP($A7,'AAPT ExDa'!$B$2:$U$99, 3,FALSE), IFERROR(VLOOKUP($A7,'ABB ExDa'!$A$2:$N$184, 5,FALSE), IFERROR(VLOOKUP($A7,'Vocus SIT ExDa'!$B$2:$J$173, 2,FALSE), IFERROR(VLOOKUP($A7,'Telstra ExDa'!$B$2:$K$310, 4,FALSE), IFERROR(VLOOKUP($A7,'Vocus RVC ExDa'!$C$2:$R$155, 8,FALSE), IFERROR(VLOOKUP($A7,'Fusion ExDa'!$B$2:$D$16, 4,FALSE), IFERROR(VLOOKUP($A7,'Exetel ExDa'!$C$2:$N$14, 5,FALSE), IFERROR(VLOOKUP($A7,'Infinet ExDa'!$B$2:$E$14, 3,FALSE), "Not Found")))))))) -> FAST Fibre | F7: =IFERROR(VLOOKUP($A7,'AAPT ExDa'!$B$2:$U$99, 4,FALSE), IFERROR(VLOOKUP($A7,'ABB ExDa'!$A$2:$N$184, 6,FALSE), IFERROR(VLOOKUP($A7,'Vocus SIT ExDa'!$B$2:$J$173, 3,FALSE), IFERROR(VLOOKUP($A7,'Telstra ExDa'!$B$2:$K$310, 5,FALSE), IFERROR(VLOOKUP($A7,'Vocus RVC ExDa'!$C$2:$R$155, 9,FALSE), IFERROR(VLOOKUP($A7,'Fusion ExDa'!$B$2:$D$16, 0,FALSE), IFERROR(VLOOKUP($A7,'Exetel ExDa'!$C$2:$N$14, 6,FALSE), IFERROR(VLOOKUP($A7,'Infinet ExDa'!$B$2:$E$14, 0,FALSE), "Not Found")))))))) -> FAST Fibre (NTU) | G7: =IFERROR(VLOOKUP($A7,'AAPT ExDa'!$B$2:$U$99, 5,FALSE), IFERROR(VLOOKUP($A7,'ABB ExDa'!$A$2:$N$184, 8,FALSE), IFERROR(VLOOKUP($A7,'Vocus SIT ExDa'!$B$2:$J$173, 6,FALSE), IFERROR(VLOOKUP($A7,'Telstra ExDa'!$B$2:$K$310, 0,FALSE), IFERROR(VLOOKUP($A7,'Vocus RVC ExDa'!$C$2:$R$155, 15,FALSE), IFERROR(VLOOKUP($A7,'Fusion ExDa'!$B$2:$D$16, 0,FALSE), IFERROR(VLOOKUP($A7,'Exetel ExDa'!$C$2:$N$14, 7,FALSE), IFERROR(VLOOKUP($A7,'Infinet ExDa'!$B$2:$E$14, 0,FALSE), "Not Found")))))))) -> 0 | H7: =IFERROR(VLOOKUP($A7,'AAPT ExDa'!$B$2:$U$99, 6,FALSE), IFERROR(VLOOKUP($A7,'ABB ExDa'!$A$2:$N$184, 0,FALSE), IFERROR(VLOOKUP($A7,'Vocus SIT ExDa'!$B$2:$J$173, 0,FALSE), IFERROR(VLOOKUP($A7,'Telstra ExDa'!$B$2:$K$310, 0,FALSE), IFERROR(VLOOKUP($A7,'Vocus RVC ExDa'!$C$2:$R$155, 16,FALSE), IFERROR(VLOOKUP($A7,'Fusion ExDa'!$B$2:$D$16, 0,FALSE), IFERROR(VLOOKUP($A7,'Exetel ExDa'!$C$2:$N$14, 0,FALSE), IFERROR(VLOOKUP($A7,'Infinet ExDa'!$B$2:$E$14, 0,FALSE), "Not Found")))))))) -> 400 Mbps; 36 Months | I7: =IFERROR(VLOOKUP($A7,'AAPT ExDa'!$B$2:$U$99, 0,FALSE), IFERROR(VLOOKUP($A7,'ABB ExDa'!$A$2:$N$184, 0,FALSE), IFERROR(VLOOKUP($A7,'Vocus SIT ExDa'!$B$2:$J$173, 0,FALSE), IFERROR(VLOOKUP($A7,'Telstra ExDa'!$B$2:$K$310, 0,FALSE), IFERROR(VLOOKUP($A7,'Vocus RVC ExDa'!$C$2:$R$155, 0,FALSE), IFERROR(VLOOKUP($A7,'Fusion ExDa'!$B$2:$D$16, 0,FALSE), IFERROR(VLOOKUP($A7,'Exetel ExDa'!$C$2:$N$14, 8,FALSE), IFERROR(VLOOKUP($A7,'Infinet ExDa'!$B$2:$E$14, 0,FALSE), "Not Found")))))))) -> Not Found | J7: =IFERROR(VLOOKUP($A7,'AAPT ExDa'!$B$2:$U$99, 7,FALSE), IFERROR(VLOOKUP($A7,'ABB ExDa'!$A$2:$N$184, 2,FALSE), IFERROR(VLOOKUP($A7,'Vocus SIT ExDa'!$B$2:$J$173, 0,FALSE), IFERROR(VLOOKUP($A7,'Telstra ExDa'!$B$2:$K$310, 7,FALSE), IFERROR(VLOOKUP($A7,'Vocus RVC ExDa'!$C$2:$R$155, 2,FALSE), IFERROR(VLOOKUP($A7,'Fusion ExDa'!$B$2:$D$16, 3,FALSE), IFERROR(VLOOKUP($A7,'Exetel ExDa'!$C$2:$N$14, 0,FALSE), IFERROR(VLOOKUP($A7,'Infinet ExDa'!$B$2:$E$14, 0,FALSE), "Not Found")))))))) -> 0 | K7: =IFERROR(VLOOKUP($A7,'AAPT ExDa'!$B$2:$U$99, 12,FALSE), IFERROR(VLOOKUP($A7,'ABB ExDa'!$A$2:$N$184, 0,FALSE), IFERROR(VLOOKUP($A7,'Vocus SIT ExDa'!$B$2:$J$173, 0,FALSE), IFERROR(VLOOKUP($A7,'Telstra ExDa'!$B$2:$K$310, 0,FALSE), IFERROR(VLOOKUP($A7,'Vocus RVC ExDa'!$C$2:$R$155, 0,FALSE), IFERROR(VLOOKUP($A7,'Fusion ExDa'!$B$2:$D$16, 0,FALSE), IFERROR(VLOOKUP($A7,'Exetel ExDa'!$C$2:$N$14, 12,FALSE), IFERROR(VLOOKUP($A7,'Infinet ExDa'!$B$2:$E$14, 0,FALSE), "Not Found")))))))) -> 36 Months | L7: =IFERROR(VLOOKUP($A7,'AAPT ExDa'!$B$2:$U$99, 11,FALSE), IFERROR(VLOOKUP($A7,'ABB ExDa'!$A$2:$N$184, 9,FALSE), IFERROR(VLOOKUP($A7,'Vocus SIT ExDa'!$B$2:$J$173, 8,FALSE), IFERROR(VLOOKUP($A7,'Telstra ExDa'!$B$2:$K$310, 0,FALSE), IFERROR(VLOOKUP($A7,'Vocus RVC ExDa'!$C$2:$R$155, 0,FALSE), IFERROR(VLOOKUP($A7,'Fusion ExDa'!$B$2:$D$16, 0,FALSE), IFERROR(VLOOKUP($A7,'Exetel ExDa'!$C$2:$N$14, 9,FALSE), IFERROR(VLOOKUP($A7,'Infinet ExDa'!$B$2:$E$14, 0,FALSE), "Not Found")))))))) -> 15/04/2022 | M7: =IFERROR(VLOOKUP($A7,'AAPT ExDa'!$B$2:$U$99, 0,FALSE), IFERROR(VLOOKUP($A7,'ABB ExDa'!$A$2:$N$184, 0,FALSE), IFERROR(VLOOKUP($A7,'Vocus SIT ExDa'!$B$2:$J$173, 0,FALSE), IFERROR(VLOOKUP($A7,'Telstra ExDa'!$B$2:$K$310, 0,FALSE), IFERROR(VLOOKUP($A7,'Vocus RVC ExDa'!$C$2:$R$155, 0,FALSE), IFERROR(VLOOKUP($A7,'Fusion ExDa'!$B$2:$D$16, 0,FALSE), IFERROR(VLOOKUP($A7,'Exetel ExDa'!$C$2:$N$14, 11,FALSE), IFERROR(VLOOKUP($A7,'Infinet ExDa'!$B$2:$E$14, 0,FALSE), "Not Found")))))))) -> Not Found | N7: =IFERROR(VLOOKUP($A7,'AAPT ExDa'!$B$2:$U$99, 0,FALSE), IFERROR(VLOOKUP($A7,'ABB ExDa'!$A$2:$N$184, 13,FALSE), IFERROR(VLOOKUP($A7,'Vocus SIT ExDa'!$B$2:$J$173, 0,FALSE), IFERROR(VLOOKUP($A7,'Telstra ExDa'!$B$2:$K$310, 0,FALSE), IFERROR(VLOOKUP($A7,'Vocus RVC ExDa'!$C$2:$R$155, 0,FALSE), IFERROR(VLOOKUP($A7,'Fusion ExDa'!$B$2:$D$16, 0,FALSE), IFERROR(VLOOKUP($A7,'Exetel ExDa'!$C$2:$N$14, 0,FALSE), IFERROR(VLOOKUP($A7,'Infinet ExDa'!$B$2:$E$14, 0,FALSE), "Not Found")))))))) -> Not Found
A8: Auriga Group | B8: =IFERROR(VLOOKUP(A8,'Exetel ExDa'!$C$2:$N$14,4,FALSE),"No Data") -> No Data | C8: =IFERROR(VLOOKUP(A8,'AAPT ExDa'!$B$2:$U$99, 2,FALSE), IFERROR(VLOOKUP(A8,'ABB ExDa'!$A$2:$N$184, 2,FALSE), IFERROR(VLOOKUP(A8,'Vocus SIT ExDa'!$B$2:$J$173, 7,FALSE), IFERROR(VLOOKUP(A8,'Telstra ExDa'!$B$2:$K$310, 2,FALSE), IFERROR(VLOOKUP(A8,'Vocus RVC ExDa'!$C$2:$R$155, 3,FALSE), IFERROR(VLOOKUP(A8,'Fusion ExDa'!$B$2:$D$16, 2,FALSE), IFERROR(VLOOKUP(A8,'Exetel ExDa'!$C$2:$N$14, 2,FALSE), IFERROR(VLOOKUP(A8,'Infinet ExDa'!$B$2:$E$14, 2,FALSE), "Not Found")))))))) -> Albion | D8: =IFERROR(VLOOKUP($A8,'AAPT ExDa'!$B$2:$U$99, 15,FALSE), IFERROR(VLOOKUP($A8,'ABB ExDa'!$A$2:$N$184, 4,FALSE), IFERROR(VLOOKUP($A8,'Vocus SIT ExDa'!$B$2:$J$173, 5,FALSE), IFERROR(VLOOKUP($A8,'Telstra ExDa'!$B$2:$K$310, 8,FALSE), IFERROR(VLOOKUP($A8,'Vocus RVC ExDa'!$C$2:$R$155, 6,FALSE), IFERROR(VLOOKUP($A8,'Fusion ExDa'!$B$2:$D$16, 4,FALSE), IFERROR(VLOOKUP($A8,'Exetel ExDa'!$C$2:$N$14, 3,FALSE), IFERROR(VLOOKUP($A8,'Infinet ExDa'!$B$2:$E$14, 3,FALSE), "Not Found")))))))) -> AAPT | E8: =IFERROR(VLOOKUP($A8,'AAPT ExDa'!$B$2:$U$99, 3,FALSE), IFERROR(VLOOKUP($A8,'ABB ExDa'!$A$2:$N$184, 5,FALSE), IFERROR(VLOOKUP($A8,'Vocus SIT ExDa'!$B$2:$J$173, 2,FALSE), IFERROR(VLOOKUP($A8,'Telstra ExDa'!$B$2:$K$310, 4,FALSE), IFERROR(VLOOKUP($A8,'Vocus RVC ExDa'!$C$2:$R$155, 8,FALSE), IFERROR(VLOOKUP($A8,'Fusion ExDa'!$B$2:$D$16, 4,FALSE), IFERROR(VLOOKUP($A8,'Exetel ExDa'!$C$2:$N$14, 5,FALSE), IFERROR(VLOOKUP($A8,'Infinet ExDa'!$B$2:$E$14, 3,FALSE), "Not Found")))))))) -> FAST Fibre | F8: =IFERROR(VLOOKUP($A8,'AAPT ExDa'!$B$2:$U$99, 4,FALSE), IFERROR(VLOOKUP($A8,'ABB ExDa'!$A$2:$N$184, 6,FALSE), IFERROR(VLOOKUP($A8,'Vocus SIT ExDa'!$B$2:$J$173, 3,FALSE), IFERROR(VLOOKUP($A8,'Telstra ExDa'!$B$2:$K$310, 5,FALSE), IFERROR(VLOOKUP($A8,'Vocus RVC ExDa'!$C$2:$R$155, 9,FALSE), IFERROR(VLOOKUP($A8,'Fusion ExDa'!$B$2:$D$16, 0,FALSE), IFERROR(VLOOKUP($A8,'Exetel ExDa'!$C$2:$N$14, 6,FALSE), IFERROR(VLOOKUP($A8,'Infinet ExDa'!$B$2:$E$14, 0,FALSE), "Not Found")))))))) -> FAST Fibre (NTU) | G8: =IFERROR(VLOOKUP($A8,'AAPT ExDa'!$B$2:$U$99, 5,FALSE), IFERROR(VLOOKUP($A8,'ABB ExDa'!$A$2:$N$184, 8,FALSE), IFERROR(VLOOKUP($A8,'Vocus SIT ExDa'!$B$2:$J$173, 6,FALSE), IFERROR(VLOOKUP($A8,'Telstra ExDa'!$B$2:$K$310, 0,FALSE), IFERROR(VLOOKUP($A8,'Vocus RVC ExDa'!$C$2:$R$155, 15,FALSE), IFERROR(VLOOKUP($A8,'Fusion ExDa'!$B$2:$D$16, 0,FALSE), IFERROR(VLOOKUP($A8,'Exetel ExDa'!$C$2:$N$14, 7,FALSE), IFERROR(VLOOKUP($A8,'Infinet ExDa'!$B$2:$E$14, 0,FALSE), "Not Found")))))))) -> 0 | H8: =IFERROR(VLOOKUP($A8,'AAPT ExDa'!$B$2:$U$99, 6,FALSE), IFERROR(VLOOKUP($A8,'ABB ExDa'!$A$2:$N$184, 0,FALSE), IFERROR(VLOOKUP($A8,'Vocus SIT ExDa'!$B$2:$J$173, 0,FALSE), IFERROR(VLOOKUP($A8,'Telstra ExDa'!$B$2:$K$310, 0,FALSE), IFERROR(VLOOKUP($A8,'Vocus RVC ExDa'!$C$2:$R$155, 16,FALSE), IFERROR(VLOOKUP($A8,'Fusion ExDa'!$B$2:$D$16, 0,FALSE), IFERROR(VLOOKUP($A8,'Exetel ExDa'!$C$2:$N$14, 0,FALSE), IFERROR(VLOOKUP($A8,'Infinet ExDa'!$B$2:$E$14, 0,FALSE), "Not Found")))))))) -> 400 Mbps; 36 Months | I8: =IFERROR(VLOOKUP($A8,'AAPT ExDa'!$B$2:$U$99, 0,FALSE), IFERROR(VLOOKUP($A8,'ABB ExDa'!$A$2:$N$184, 0,FALSE), IFERROR(VLOOKUP($A8,'Vocus SIT ExDa'!$B$2:$J$173, 0,FALSE), IFERROR(VLOOKUP($A8,'Telstra ExDa'!$B$2:$K$310, 0,FALSE), IFERROR(VLOOKUP($A8,'Vocus RVC ExDa'!$C$2:$R$155, 0,FALSE), IFERROR(VLOOKUP($A8,'Fusion ExDa'!$B$2:$D$16, 0,FALSE), IFERROR(VLOOKUP($A8,'Exetel ExDa'!$C$2:$N$14, 8,FALSE), IFERROR(VLOOKUP($A8,'Infinet ExDa'!$B$2:$E$14, 0,FALSE), "Not Found")))))))) -> Not Found | J8: =IFERROR(VLOOKUP($A8,'AAPT ExDa'!$B$2:$U$99, 7,FALSE), IFERROR(VLOOKUP($A8,'ABB ExDa'!$A$2:$N$184, 2,FALSE), IFERROR(VLOOKUP($A8,'Vocus SIT ExDa'!$B$2:$J$173, 0,FALSE), IFERROR(VLOOKUP($A8,'Telstra ExDa'!$B$2:$K$310, 7,FALSE), IFERROR(VLOOKUP($A8,'Vocus RVC ExDa'!$C$2:$R$155, 2,FALSE), IFERROR(VLOOKUP($A8,'Fusion ExDa'!$B$2:$D$16, 3,FALSE), IFERROR(VLOOKUP($A8,'Exetel ExDa'!$C$2:$N$14, 0,FALSE), IFERROR(VLOOKUP($A8,'Infinet ExDa'!$B$2:$E$14, 0,FALSE), "Not Found")))))))) -> 0 | K8: =IFERROR(VLOOKUP($A8,'AAPT ExDa'!$B$2:$U$99, 12,FALSE), IFERROR(VLOOKUP($A8,'ABB ExDa'!$A$2:$N$184, 0,FALSE), IFERROR(VLOOKUP($A8,'Vocus SIT ExDa'!$B$2:$J$173, 0,FALSE), IFERROR(VLOOKUP($A8,'Telstra ExDa'!$B$2:$K$310, 0,FALSE), IFERROR(VLOOKUP($A8,'Vocus RVC ExDa'!$C$2:$R$155, 0,FALSE), IFERROR(VLOOKUP($A8,'Fusion ExDa'!$B$2:$D$16, 0,FALSE), IFERROR(VLOOKUP($A8,'Exetel ExDa'!$C$2:$N$14, 12,FALSE), IFERROR(VLOOKUP($A8,'Infinet ExDa'!$B$2:$E$14, 0,FALSE), "Not Found")))))))) -> 36 Months | L8: =IFERROR(VLOOKUP($A8,'AAPT ExDa'!$B$2:$U$99, 11,FALSE), IFERROR(VLOOKUP($A8,'ABB ExDa'!$A$2:$N$184, 9,FALSE), IFERROR(VLOOKUP($A8,'Vocus SIT ExDa'!$B$2:$J$173, 8,FALSE), IFERROR(VLOOKUP($A8,'Telstra ExDa'!$B$2:$K$310, 0,FALSE), IFERROR(VLOOKUP($A8,'Vocus RVC ExDa'!$C$2:$R$155, 0,FALSE), IFERROR(VLOOKUP($A8,'Fusion ExDa'!$B$2:$D$16, 0,FALSE), IFERROR(VLOOKUP($A8,'Exetel ExDa'!$C$2:$N$14, 9,FALSE), IFERROR(VLOOKUP($A8,'Infinet ExDa'!$B$2:$E$14, 0,FALSE), "Not Found")))))))) -> 15/04/2022 | M8: =IFERROR(VLOOKUP($A8,'AAPT ExDa'!$B$2:$U$99, 0,FALSE), IFERROR(VLOOKUP($A8,'ABB ExDa'!$A$2:$N$184, 0,FALSE), IFERROR(VLOOKUP($A8,'Vocus SIT ExDa'!$B$2:$J$173, 0,FALSE), IFERROR(VLOOKUP($A8,'Telstra ExDa'!$B$2:$K$310, 0,FALSE), IFERROR(VLOOKUP($A8,'Vocus RVC ExDa'!$C$2:$R$155, 0,FALSE), IFERROR(VLOOKUP($A8,'Fusion ExDa'!$B$2:$D$16, 0,FALSE), IFERROR(VLOOKUP($A8,'Exetel ExDa'!$C$2:$N$14, 11,FALSE), IFERROR(VLOOKUP($A8,'Infinet ExDa'!$B$2:$E$14, 0,FALSE), "Not Found")))))))) -> Not Found | N8: =IFERROR(VLOOKUP($A8,'AAPT ExDa'!$B$2:$U$99, 0,FALSE), IFERROR(VLOOKUP($A8,'ABB ExDa'!$A$2:$N$184, 13,FALSE), IFERROR(VLOOKUP($A8,'Vocus SIT ExDa'!$B$2:$J$173, 0,FALSE), IFERROR(VLOOKUP($A8,'Telstra ExDa'!$B$2:$K$310, 0,FALSE), IFERROR(VLOOKUP($A8,'Vocus RVC ExDa'!$C$2:$R$155, 0,FALSE), IFERROR(VLOOKUP($A8,'Fusion ExDa'!$B$2:$D$16, 0,FALSE), IFERROR(VLOOKUP($A8,'Exetel ExDa'!$C$2:$N$14, 0,FALSE), IFERROR(VLOOKUP($A8,'Infinet ExDa'!$B$2:$E$14, 0,FALSE), "Not Found")))))))) -> Not Found
A9: Auriga Group | B9: =IFERROR(VLOOKUP(A9,'Exetel ExDa'!$C$2:$N$14,4,FALSE),"No Data") -> No Data | C9: =IFERROR(VLOOKUP(A9,'AAPT ExDa'!$B$2:$U$99, 2,FALSE), IFERROR(VLOOKUP(A9,'ABB ExDa'!$A$2:$N$184, 2,FALSE), IFERROR(VLOOKUP(A9,'Vocus SIT ExDa'!$B$2:$J$173, 7,FALSE), IFERROR(VLOOKUP(A9,'Telstra ExDa'!$B$2:$K$310, 2,FALSE), IFERROR(VLOOKUP(A9,'Vocus RVC ExDa'!$C$2:$R$155, 3,FALSE), IFERROR(VLOOKUP(A9,'Fusion ExDa'!$B$2:$D$16, 2,FALSE), IFERROR(VLOOKUP(A9,'Exetel ExDa'!$C$2:$N$14, 2,FALSE), IFERROR(VLOOKUP(A9,'Infinet ExDa'!$B$2:$E$14, 2,FALSE), "Not Found")))))))) -> Albion | D9: =IFERROR(VLOOKUP($A9,'AAPT ExDa'!$B$2:$U$99, 15,FALSE), IFERROR(VLOOKUP($A9,'ABB ExDa'!$A$2:$N$184, 4,FALSE), IFERROR(VLOOKUP($A9,'Vocus SIT ExDa'!$B$2:$J$173, 5,FALSE), IFERROR(VLOOKUP($A9,'Telstra ExDa'!$B$2:$K$310, 8,FALSE), IFERROR(VLOOKUP($A9,'Vocus RVC ExDa'!$C$2:$R$155, 6,FALSE), IFERROR(VLOOKUP($A9,'Fusion ExDa'!$B$2:$D$16, 4,FALSE), IFERROR(VLOOKUP($A9,'Exetel ExDa'!$C$2:$N$14, 3,FALSE), IFERROR(VLOOKUP($A9,'Infinet ExDa'!$B$2:$E$14, 3,FALSE), "Not Found")))))))) -> AAPT | E9: =IFERROR(VLOOKUP($A9,'AAPT ExDa'!$B$2:$U$99, 3,FALSE), IFERROR(VLOOKUP($A9,'ABB ExDa'!$A$2:$N$184, 5,FALSE), IFERROR(VLOOKUP($A9,'Vocus SIT ExDa'!$B$2:$J$173, 2,FALSE), IFERROR(VLOOKUP($A9,'Telstra ExDa'!$B$2:$K$310, 4,FALSE), IFERROR(VLOOKUP($A9,'Vocus RVC ExDa'!$C$2:$R$155, 8,FALSE), IFERROR(VLOOKUP($A9,'Fusion ExDa'!$B$2:$D$16, 4,FALSE), IFERROR(VLOOKUP($A9,'Exetel ExDa'!$C$2:$N$14, 5,FALSE), IFERROR(VLOOKUP($A9,'Infinet ExDa'!$B$2:$E$14, 3,FALSE), "Not Found")))))))) -> FAST Fibre | F9: =IFERROR(VLOOKUP($A9,'AAPT ExDa'!$B$2:$U$99, 4,FALSE), IFERROR(VLOOKUP($A9,'ABB ExDa'!$A$2:$N$184, 6,FALSE), IFERROR(VLOOKUP($A9,'Vocus SIT ExDa'!$B$2:$J$173, 3,FALSE), IFERROR(VLOOKUP($A9,'Telstra ExDa'!$B$2:$K$310, 5,FALSE), IFERROR(VLOOKUP($A9,'Vocus RVC ExDa'!$C$2:$R$155, 9,FALSE), IFERROR(VLOOKUP($A9,'Fusion ExDa'!$B$2:$D$16, 0,FALSE), IFERROR(VLOOKUP($A9,'Exetel ExDa'!$C$2:$N$14, 6,FALSE), IFERROR(VLOOKUP($A9,'Infinet ExDa'!$B$2:$E$14, 0,FALSE), "Not Found")))))))) -> FAST Fibre (NTU) | G9: =IFERROR(VLOOKUP($A9,'AAPT ExDa'!$B$2:$U$99, 5,FALSE), IFERROR(VLOOKUP($A9,'ABB ExDa'!$A$2:$N$184, 8,FALSE), IFERROR(VLOOKUP($A9,'Vocus SIT ExDa'!$B$2:$J$173, 6,FALSE), IFERROR(VLOOKUP($A9,'Telstra ExDa'!$B$2:$K$310, 0,FALSE), IFERROR(VLOOKUP($A9,'Vocus RVC ExDa'!$C$2:$R$155, 15,FALSE), IFERROR(VLOOKUP($A9,'Fusion ExDa'!$B$2:$D$16, 0,FALSE), IFERROR(VLOOKUP($A9,'Exetel ExDa'!$C$2:$N$14, 7,FALSE), IFERROR(VLOOKUP($A9,'Infinet ExDa'!$B$2:$E$14, 0,FALSE), "Not Found")))))))) -> 0 | H9: =IFERROR(VLOOKUP($A9,'AAPT ExDa'!$B$2:$U$99, 6,FALSE), IFERROR(VLOOKUP($A9,'ABB ExDa'!$A$2:$N$184, 0,FALSE), IFERROR(VLOOKUP($A9,'Vocus SIT ExDa'!$B$2:$J$173, 0,FALSE), IFERROR(VLOOKUP($A9,'Telstra ExDa'!$B$2:$K$310, 0,FALSE), IFERROR(VLOOKUP($A9,'Vocus RVC ExDa'!$C$2:$R$155, 16,FALSE), IFERROR(VLOOKUP($A9,'Fusion ExDa'!$B$2:$D$16, 0,FALSE), IFERROR(VLOOKUP($A9,'Exetel ExDa'!$C$2:$N$14, 0,FALSE), IFERROR(VLOOKUP($A9,'Infinet ExDa'!$B$2:$E$14, 0,FALSE), "Not Found")))))))) -> 400 Mbps; 36 Months | I9: =IFERROR(VLOOKUP($A9,'AAPT ExDa'!$B$2:$U$99, 0,FALSE), IFERROR(VLOOKUP($A9,'ABB ExDa'!$A$2:$N$184, 0,FALSE), IFERROR(VLOOKUP($A9,'Vocus SIT ExDa'!$B$2:$J$173, 0,FALSE), IFERROR(VLOOKUP($A9,'Telstra ExDa'!$B$2:$K$310, 0,FALSE), IFERROR(VLOOKUP($A9,'Vocus RVC ExDa'!$C$2:$R$155, 0,FALSE), IFERROR(VLOOKUP($A9,'Fusion ExDa'!$B$2:$D$16, 0,FALSE), IFERROR(VLOOKUP($A9,'Exetel ExDa'!$C$2:$N$14, 8,FALSE), IFERROR(VLOOKUP($A9,'Infinet ExDa'!$B$2:$E$14, 0,FALSE), "Not Found")))))))) -> Not Found | J9: =IFERROR(VLOOKUP($A9,'AAPT ExDa'!$B$2:$U$99, 7,FALSE), IFERROR(VLOOKUP($A9,'ABB ExDa'!$A$2:$N$184, 2,FALSE), IFERROR(VLOOKUP($A9,'Vocus SIT ExDa'!$B$2:$J$173, 0,FALSE), IFERROR(VLOOKUP($A9,'Telstra ExDa'!$B$2:$K$310, 7,FALSE), IFERROR(VLOOKUP($A9,'Vocus RVC ExDa'!$C$2:$R$155, 2,FALSE), IFERROR(VLOOKUP($A9,'Fusion ExDa'!$B$2:$D$16, 3,FALSE), IFERROR(VLOOKUP($A9,'Exetel ExDa'!$C$2:$N$14, 0,FALSE), IFERROR(VLOOKUP($A9,'Infinet ExDa'!$B$2:$E$14, 0,FALSE), "Not Found")))))))) -> 0 | K9: =IFERROR(VLOOKUP($A9,'AAPT ExDa'!$B$2:$U$99, 12,FALSE), IFERROR(VLOOKUP($A9,'ABB ExDa'!$A$2:$N$184, 0,FALSE), IFERROR(VLOOKUP($A9,'Vocus SIT ExDa'!$B$2:$J$173, 0,FALSE), IFERROR(VLOOKUP($A9,'Telstra ExDa'!$B$2:$K$310, 0,FALSE), IFERROR(VLOOKUP($A9,'Vocus RVC ExDa'!$C$2:$R$155, 0,FALSE), IFERROR(VLOOKUP($A9,'Fusion ExDa'!$B$2:$D$16, 0,FALSE), IFERROR(VLOOKUP($A9,'Exetel ExDa'!$C$2:$N$14, 12,FALSE), IFERROR(VLOOKUP($A9,'Infinet ExDa'!$B$2:$E$14, 0,FALSE), "Not Found")))))))) -> 36 Months | L9: =IFERROR(VLOOKUP($A9,'AAPT ExDa'!$B$2:$U$99, 11,FALSE), IFERROR(VLOOKUP($A9,'ABB ExDa'!$A$2:$N$184, 9,FALSE), IFERROR(VLOOKUP($A9,'Vocus SIT ExDa'!$B$2:$J$173, 8,FALSE), IFERROR(VLOOKUP($A9,'Telstra ExDa'!$B$2:$K$310, 0,FALSE), IFERROR(VLOOKUP($A9,'Vocus RVC ExDa'!$C$2:$R$155, 0,FALSE), IFERROR(VLOOKUP($A9,'Fusion ExDa'!$B$2:$D$16, 0,FALSE), IFERROR(VLOOKUP($A9,'Exetel ExDa'!$C$2:$N$14, 9,FALSE), IFERROR(VLOOKUP($A9,'Infinet ExDa'!$B$2:$E$14, 0,FALSE), "Not Found")))))))) -> 15/04/2022 | M9: =IFERROR(VLOOKUP($A9,'AAPT ExDa'!$B$2:$U$99, 0,FALSE), IFERROR(VLOOKUP($A9,'ABB ExDa'!$A$2:$N$184, 0,FALSE), IFERROR(VLOOKUP($A9,'Vocus SIT ExDa'!$B$2:$J$173, 0,FALSE), IFERROR(VLOOKUP($A9,'Telstra ExDa'!$B$2:$K$310, 0,FALSE), IFERROR(VLOOKUP($A9,'Vocus RVC ExDa'!$C$2:$R$155, 0,FALSE), IFERROR(VLOOKUP($A9,'Fusion ExDa'!$B$2:$D$16, 0,FALSE), IFERROR(VLOOKUP($A9,'Exetel ExDa'!$C$2:$N$14, 11,FALSE), IFERROR(VLOOKUP($A9,'Infinet ExDa'!$B$2:$E$14, 0,FALSE), "Not Found")))))))) -> Not Found | N9: =IFERROR(VLOOKUP($A9,'AAPT ExDa'!$B$2:$U$99, 0,FALSE), IFERROR(VLOOKUP($A9,'ABB ExDa'!$A$2:$N$184, 13,FALSE), IFERROR(VLOOKUP($A9,'Vocus SIT ExDa'!$B$2:$J$173, 0,FALSE), IFERROR(VLOOKUP($A9,'Telstra ExDa'!$B$2:$K$310, 0,FALSE), IFERROR(VLOOKUP($A9,'Vocus RVC ExDa'!$C$2:$R$155, 0,FALSE), IFERROR(VLOOKUP($A9,'Fusion ExDa'!$B$2:$D$16, 0,FALSE), IFERROR(VLOOKUP($A9,'Exetel ExDa'!$C$2:$N$14, 0,FALSE), IFERROR(VLOOKUP($A9,'Infinet ExDa'!$B$2:$E$14, 0,FALSE), "Not Found")))))))) -> Not Found
A10: Auriga Group | B10: =IFERROR(VLOOKUP(A10,'Exetel ExDa'!$C$2:$N$14,4,FALSE),"No Data") -> No Data | C10: =IFERROR(VLOOKUP(A10,'AAPT ExDa'!$B$2:$U$99, 2,FALSE), IFERROR(VLOOKUP(A10,'ABB ExDa'!$A$2:$N$184, 2,FALSE), IFERROR(VLOOKUP(A10,'Vocus SIT ExDa'!$B$2:$J$173, 7,FALSE), IFERROR(VLOOKUP(A10,'Telstra ExDa'!$B$2:$K$310, 2,FALSE), IFERROR(VLOOKUP(A10,'Vocus RVC ExDa'!$C$2:$R$155, 3,FALSE), IFERROR(VLOOKUP(A10,'Fusion ExDa'!$B$2:$D$16, 2,FALSE), IFERROR(VLOOKUP(A10,'Exetel ExDa'!$C$2:$N$14, 2,FALSE), IFERROR(VLOOKUP(A10,'Infinet ExDa'!$B$2:$E$14, 2,FALSE), "Not Found")))))))) -> Albion | D10: =IFERROR(VLOOKUP($A10,'AAPT ExDa'!$B$2:$U$99, 15,FALSE), IFERROR(VLOOKUP($A10,'ABB ExDa'!$A$2:$N$184, 4,FALSE), IFERROR(VLOOKUP($A10,'Vocus SIT ExDa'!$B$2:$J$173, 5,FALSE), IFERROR(VLOOKUP($A10,'Telstra ExDa'!$B$2:$K$310, 8,FALSE), IFERROR(VLOOKUP($A10,'Vocus RVC ExDa'!$C$2:$R$155, 6,FALSE), IFERROR(VLOOKUP($A10,'Fusion ExDa'!$B$2:$D$16, 4,FALSE), IFERROR(VLOOKUP($A10,'Exetel ExDa'!$C$2:$N$14, 3,FALSE), IFERROR(VLOOKUP($A10,'Infinet ExDa'!$B$2:$E$14, 3,FALSE), "Not Found")))))))) -> AAPT | E10: =IFERROR(VLOOKUP($A10,'AAPT ExDa'!$B$2:$U$99, 3,FALSE), IFERROR(VLOOKUP($A10,'ABB ExDa'!$A$2:$N$184, 5,FALSE), IFERROR(VLOOKUP($A10,'Vocus SIT ExDa'!$B$2:$J$173, 2,FALSE), IFERROR(VLOOKUP($A10,'Telstra ExDa'!$B$2:$K$310, 4,FALSE), IFERROR(VLOOKUP($A10,'Vocus RVC ExDa'!$C$2:$R$155, 8,FALSE), IFERROR(VLOOKUP($A10,'Fusion ExDa'!$B$2:$D$16, 4,FALSE), IFERROR(VLOOKUP($A10,'Exetel ExDa'!$C$2:$N$14, 5,FALSE), IFERROR(VLOOKUP($A10,'Infinet ExDa'!$B$2:$E$14, 3,FALSE), "Not Found")))))))) -> FAST Fibre | F10: =IFERROR(VLOOKUP($A10,'AAPT ExDa'!$B$2:$U$99, 4,FALSE), IFERROR(VLOOKUP($A10,'ABB ExDa'!$A$2:$N$184, 6,FALSE), IFERROR(VLOOKUP($A10,'Vocus SIT ExDa'!$B$2:$J$173, 3,FALSE), IFERROR(VLOOKUP($A10,'Telstra ExDa'!$B$2:$K$310, 5,FALSE), IFERROR(VLOOKUP($A10,'Vocus RVC ExDa'!$C$2:$R$155, 9,FALSE), IFERROR(VLOOKUP($A10,'Fusion ExDa'!$B$2:$D$16, 0,FALSE), IFERROR(VLOOKUP($A10,'Exetel ExDa'!$C$2:$N$14, 6,FALSE), IFERROR(VLOOKUP($A10,'Infinet ExDa'!$B$2:$E$14, 0,FALSE), "Not Found")))))))) -> FAST Fibre (NTU) | G10: =IFERROR(VLOOKUP($A10,'AAPT ExDa'!$B$2:$U$99, 5,FALSE), IFERROR(VLOOKUP($A10,'ABB ExDa'!$A$2:$N$184, 8,FALSE), IFERROR(VLOOKUP($A10,'Vocus SIT ExDa'!$B$2:$J$173, 6,FALSE), IFERROR(VLOOKUP($A10,'Telstra ExDa'!$B$2:$K$310, 0,FALSE), IFERROR(VLOOKUP($A10,'Vocus RVC ExDa'!$C$2:$R$155, 15,FALSE), IFERROR(VLOOKUP($A10,'Fusion ExDa'!$B$2:$D$16, 0,FALSE), IFERROR(VLOOKUP($A10,'Exetel ExDa'!$C$2:$N$14, 7,FALSE), IFERROR(VLOOKUP($A10,'Infinet ExDa'!$B$2:$E$14, 0,FALSE), "Not Found")))))))) -> 0 | H10: =IFERROR(VLOOKUP($A10,'AAPT ExDa'!$B$2:$U$99, 6,FALSE), IFERROR(VLOOKUP($A10,'ABB ExDa'!$A$2:$N$184, 0,FALSE), IFERROR(VLOOKUP($A10,'Vocus SIT ExDa'!$B$2:$J$173, 0,FALSE), IFERROR(VLOOKUP($A10,'Telstra ExDa'!$B$2:$K$310, 0,FALSE), IFERROR(VLOOKUP($A10,'Vocus RVC ExDa'!$C$2:$R$155, 16,FALSE), IFERROR(VLOOKUP($A10,'Fusion ExDa'!$B$2:$D$16, 0,FALSE), IFERROR(VLOOKUP($A10,'Exetel ExDa'!$C$2:$N$14, 0,FALSE), IFERROR(VLOOKUP($A10,'Infinet ExDa'!$B$2:$E$14, 0,FALSE), "Not Found")))))))) -> 400 Mbps; 36 Months | I10: =IFERROR(VLOOKUP($A10,'AAPT ExDa'!$B$2:$U$99, 0,FALSE), IFERROR(VLOOKUP($A10,'ABB ExDa'!$A$2:$N$184, 0,FALSE), IFERROR(VLOOKUP($A10,'Vocus SIT ExDa'!$B$2:$J$173, 0,FALSE), IFERROR(VLOOKUP($A10,'Telstra ExDa'!$B$2:$K$310, 0,FALSE), IFERROR(VLOOKUP($A10,'Vocus RVC ExDa'!$C$2:$R$155, 0,FALSE), IFERROR(VLOOKUP($A10,'Fusion ExDa'!$B$2:$D$16, 0,FALSE), IFERROR(VLOOKUP($A10,'Exetel ExDa'!$C$2:$N$14, 8,FALSE), IFERROR(VLOOKUP($A10,'Infinet ExDa'!$B$2:$E$14, 0,FALSE), "Not Found")))))))) -> Not Found | J10: =IFERROR(VLOOKUP($A10,'AAPT ExDa'!$B$2:$U$99, 7,FALSE), IFERROR(VLOOKUP($A10,'ABB ExDa'!$A$2:$N$184, 2,FALSE), IFERROR(VLOOKUP($A10,'Vocus SIT ExDa'!$B$2:$J$173, 0,FALSE), IFERROR(VLOOKUP($A10,'Telstra ExDa'!$B$2:$K$310, 7,FALSE), IFERROR(VLOOKUP($A10,'Vocus RVC ExDa'!$C$2:$R$155, 2,FALSE), IFERROR(VLOOKUP($A10,'Fusion ExDa'!$B$2:$D$16, 3,FALSE), IFERROR(VLOOKUP($A10,'Exetel ExDa'!$C$2:$N$14, 0,FALSE), IFERROR(VLOOKUP($A10,'Infinet ExDa'!$B$2:$E$14, 0,FALSE), "Not Found")))))))) -> 0 | K10: =IFERROR(VLOOKUP($A10,'AAPT ExDa'!$B$2:$U$99, 12,FALSE), IFERROR(VLOOKUP($A10,'ABB ExDa'!$A$2:$N$184, 0,FALSE), IFERROR(VLOOKUP($A10,'Vocus SIT ExDa'!$B$2:$J$173, 0,FALSE), IFERROR(VLOOKUP($A10,'Telstra ExDa'!$B$2:$K$310, 0,FALSE), IFERROR(VLOOKUP($A10,'Vocus RVC ExDa'!$C$2:$R$155, 0,FALSE), IFERROR(VLOOKUP($A10,'Fusion ExDa'!$B$2:$D$16, 0,FALSE), IFERROR(VLOOKUP($A10,'Exetel ExDa'!$C$2:$N$14, 12,FALSE), IFERROR(VLOOKUP($A10,'Infinet ExDa'!$B$2:$E$14, 0,FALSE), "Not Found")))))))) -> 36 Months | L10: =IFERROR(VLOOKUP($A10,'AAPT ExDa'!$B$2:$U$99, 11,FALSE), IFERROR(VLOOKUP($A10,'ABB ExDa'!$A$2:$N$184, 9,FALSE), IFERROR(VLOOKUP($A10,'Vocus SIT ExDa'!$B$2:$J$173, 8,FALSE), IFERROR(VLOOKUP($A10,'Telstra ExDa'!$B$2:$K$310, 0,FALSE), IFERROR(VLOOKUP($A10,'Vocus RVC ExDa'!$C$2:$R$155, 0,FALSE), IFERROR(VLOOKUP($A10,'Fusion ExDa'!$B$2:$D$16, 0,FALSE), IFERROR(VLOOKUP($A10,'Exetel ExDa'!$C$2:$N$14, 9,FALSE), IFERROR(VLOOKUP($A10,'Infinet ExDa'!$B$2:$E$14, 0,FALSE), "Not Found")))))))) -> 15/04/2022 | M10: =IFERROR(VLOOKUP($A10,'AAPT ExDa'!$B$2:$U$99, 0,FALSE), IFERROR(VLOOKUP($A10,'ABB ExDa'!$A$2:$N$184, 0,FALSE), IFERROR(VLOOKUP($A10,'Vocus SIT ExDa'!$B$2:$J$173, 0,FALSE), IFERROR(VLOOKUP($A10,'Telstra ExDa'!$B$2:$K$310, 0,FALSE), IFERROR(VLOOKUP($A10,'Vocus RVC ExDa'!$C$2:$R$155, 0,FALSE), IFERROR(VLOOKUP($A10,'Fusion ExDa'!$B$2:$D$16, 0,FALSE), IFERROR(VLOOKUP($A10,'Exetel ExDa'!$C$2:$N$14, 11,FALSE), IFERROR(VLOOKUP($A10,'Infinet ExDa'!$B$2:$E$14, 0,FALSE), "Not Found")))))))) -> Not Found | N10: =IFERROR(VLOOKUP($A10,'AAPT ExDa'!$B$2:$U$99, 0,FALSE), IFERROR(VLOOKUP($A10,'ABB ExDa'!$A$2:$N$184, 13,FALSE), IFERROR(VLOOKUP($A10,'Vocus SIT ExDa'!$B$2:$J$173, 0,FALSE), IFERROR(VLOOKUP($A10,'Telstra ExDa'!$B$2:$K$310, 0,FALSE), IFERROR(VLOOKUP($A10,'Vocus RVC ExDa'!$C$2:$R$155, 0,FALSE), IFERROR(VLOOKUP($A10,'Fusion ExDa'!$B$2:$D$16, 0,FALSE), IFERROR(VLOOKUP($A10,'Exetel ExDa'!$C$2:$N$14, 0,FALSE), IFERROR(VLOOKUP($A10,'Infinet ExDa'!$B$2:$E$14, 0,FALSE), "Not Found")))))))) -> Not Found
A11: Auriga Group | B11: =IFERROR(VLOOKUP(A11,'Exetel ExDa'!$C$2:$N$14,4,FALSE),"No Data") -> No Data | C11: =IFERROR(VLOOKUP(A11,'AAPT ExDa'!$B$2:$U$99, 2,FALSE), IFERROR(VLOOKUP(A11,'ABB ExDa'!$A$2:$N$184, 2,FALSE), IFERROR(VLOOKUP(A11,'Vocus SIT ExDa'!$B$2:$J$173, 7,FALSE), IFERROR(VLOOKUP(A11,'Telstra ExDa'!$B$2:$K$310, 2,FALSE), IFERROR(VLOOKUP(A11,'Vocus RVC ExDa'!$C$2:$R$155, 3,FALSE), IFERROR(VLOOKUP(A11,'Fusion ExDa'!$B$2:$D$16, 2,FALSE), IFERROR(VLOOKUP(A11,'Exetel ExDa'!$C$2:$N$14, 2,FALSE), IFERROR(VLOOKUP(A11,'Infinet ExDa'!$B$2:$E$14, 2,FALSE), "Not Found")))))))) -> Albion | D11: =IFERROR(VLOOKUP($A11,'AAPT ExDa'!$B$2:$U$99, 15,FALSE), IFERROR(VLOOKUP($A11,'ABB ExDa'!$A$2:$N$184, 4,FALSE), IFERROR(VLOOKUP($A11,'Vocus SIT ExDa'!$B$2:$J$173, 5,FALSE), IFERROR(VLOOKUP($A11,'Telstra ExDa'!$B$2:$K$310, 8,FALSE), IFERROR(VLOOKUP($A11,'Vocus RVC ExDa'!$C$2:$R$155, 6,FALSE), IFERROR(VLOOKUP($A11,'Fusion ExDa'!$B$2:$D$16, 4,FALSE), IFERROR(VLOOKUP($A11,'Exetel ExDa'!$C$2:$N$14, 3,FALSE), IFERROR(VLOOKUP($A11,'Infinet ExDa'!$B$2:$E$14, 3,FALSE), "Not Found")))))))) -> AAPT | E11: =IFERROR(VLOOKUP($A11,'AAPT ExDa'!$B$2:$U$99, 3,FALSE), IFERROR(VLOOKUP($A11,'ABB ExDa'!$A$2:$N$184, 5,FALSE), IFERROR(VLOOKUP($A11,'Vocus SIT ExDa'!$B$2:$J$173, 2,FALSE), IFERROR(VLOOKUP($A11,'Telstra ExDa'!$B$2:$K$310, 4,FALSE), IFERROR(VLOOKUP($A11,'Vocus RVC ExDa'!$C$2:$R$155, 8,FALSE), IFERROR(VLOOKUP($A11,'Fusion ExDa'!$B$2:$D$16, 4,FALSE), IFERROR(VLOOKUP($A11,'Exetel ExDa'!$C$2:$N$14, 5,FALSE), IFERROR(VLOOKUP($A11,'Infinet ExDa'!$B$2:$E$14, 3,FALSE), "Not Found")))))))) -> FAST Fibre | F11: =IFERROR(VLOOKUP($A11,'AAPT ExDa'!$B$2:$U$99, 4,FALSE), IFERROR(VLOOKUP($A11,'ABB ExDa'!$A$2:$N$184, 6,FALSE), IFERROR(VLOOKUP($A11,'Vocus SIT ExDa'!$B$2:$J$173, 3,FALSE), IFERROR(VLOOKUP($A11,'Telstra ExDa'!$B$2:$K$310, 5,FALSE), IFERROR(VLOOKUP($A11,'Vocus RVC ExDa'!$C$2:$R$155, 9,FALSE), IFERROR(VLOOKUP($A11,'Fusion ExDa'!$B$2:$D$16, 0,FALSE), IFERROR(VLOOKUP($A11,'Exetel ExDa'!$C$2:$N$14, 6,FALSE), IFERROR(VLOOKUP($A11,'Infinet ExDa'!$B$2:$E$14, 0,FALSE), "Not Found")))))))) -> FAST Fibre (NTU) | G11: =IFERROR(VLOOKUP($A11,'AAPT ExDa'!$B$2:$U$99, 5,FALSE), IFERROR(VLOOKUP($A11,'ABB ExDa'!$A$2:$N$184, 8,FALSE), IFERROR(VLOOKUP($A11,'Vocus SIT ExDa'!$B$2:$J$173, 6,FALSE), IFERROR(VLOOKUP($A11,'Telstra ExDa'!$B$2:$K$310, 0,FALSE), IFERROR(VLOOKUP($A11,'Vocus RVC ExDa'!$C$2:$R$155, 15,FALSE), IFERROR(VLOOKUP($A11,'Fusion ExDa'!$B$2:$D$16, 0,FALSE), IFERROR(VLOOKUP($A11,'Exetel ExDa'!$C$2:$N$14, 7,FALSE), IFERROR(VLOOKUP($A11,'Infinet ExDa'!$B$2:$E$14, 0,FALSE), "Not Found")))))))) -> 0 | H11: =IFERROR(VLOOKUP($A11,'AAPT ExDa'!$B$2:$U$99, 6,FALSE), IFERROR(VLOOKUP($A11,'ABB ExDa'!$A$2:$N$184, 0,FALSE), IFERROR(VLOOKUP($A11,'Vocus SIT ExDa'!$B$2:$J$173, 0,FALSE), IFERROR(VLOOKUP($A11,'Telstra ExDa'!$B$2:$K$310, 0,FALSE), IFERROR(VLOOKUP($A11,'Vocus RVC ExDa'!$C$2:$R$155, 16,FALSE), IFERROR(VLOOKUP($A11,'Fusion ExDa'!$B$2:$D$16, 0,FALSE), IFERROR(VLOOKUP($A11,'Exetel ExDa'!$C$2:$N$14, 0,FALSE), IFERROR(VLOOKUP($A11,'Infinet ExDa'!$B$2:$E$14, 0,FALSE), "Not Found")))))))) -> 400 Mbps; 36 Months | I11: =IFERROR(VLOOKUP($A11,'AAPT ExDa'!$B$2:$U$99, 0,FALSE), IFERROR(VLOOKUP($A11,'ABB ExDa'!$A$2:$N$184, 0,FALSE), IFERROR(VLOOKUP($A11,'Vocus SIT ExDa'!$B$2:$J$173, 0,FALSE), IFERROR(VLOOKUP($A11,'Telstra ExDa'!$B$2:$K$310, 0,FALSE), IFERROR(VLOOKUP($A11,'Vocus RVC ExDa'!$C$2:$R$155, 0,FALSE), IFERROR(VLOOKUP($A11,'Fusion ExDa'!$B$2:$D$16, 0,FALSE), IFERROR(VLOOKUP($A11,'Exetel ExDa'!$C$2:$N$14, 8,FALSE), IFERROR(VLOOKUP($A11,'Infinet ExDa'!$B$2:$E$14, 0,FALSE), "Not Found")))))))) -> Not Found | J11: =IFERROR(VLOOKUP($A11,'AAPT ExDa'!$B$2:$U$99, 7,FALSE), IFERROR(VLOOKUP($A11,'ABB ExDa'!$A$2:$N$184, 2,FALSE), IFERROR(VLOOKUP($A11,'Vocus SIT ExDa'!$B$2:$J$173, 0,FALSE), IFERROR(VLOOKUP($A11,'Telstra ExDa'!$B$2:$K$310, 7,FALSE), IFERROR(VLOOKUP($A11,'Vocus RVC ExDa'!$C$2:$R$155, 2,FALSE), IFERROR(VLOOKUP($A11,'Fusion ExDa'!$B$2:$D$16, 3,FALSE), IFERROR(VLOOKUP($A11,'Exetel ExDa'!$C$2:$N$14, 0,FALSE), IFERROR(VLOOKUP($A11,'Infinet ExDa'!$B$2:$E$14, 0,FALSE), "Not Found")))))))) -> 0 | K11: =IFERROR(VLOOKUP($A11,'AAPT ExDa'!$B$2:$U$99, 12,FALSE), IFERROR(VLOOKUP($A11,'ABB ExDa'!$A$2:$N$184, 0,FALSE), IFERROR(VLOOKUP($A11,'Vocus SIT ExDa'!$B$2:$J$173, 0,FALSE), IFERROR(VLOOKUP($A11,'Telstra ExDa'!$B$2:$K$310, 0,FALSE), IFERROR(VLOOKUP($A11,'Vocus RVC ExDa'!$C$2:$R$155, 0,FALSE), IFERROR(VLOOKUP($A11,'Fusion ExDa'!$B$2:$D$16, 0,FALSE), IFERROR(VLOOKUP($A11,'Exetel ExDa'!$C$2:$N$14, 12,FALSE), IFERROR(VLOOKUP($A11,'Infinet ExDa'!$B$2:$E$14, 0,FALSE), "Not Found")))))))) -> 36 Months | L11: =IFERROR(VLOOKUP($A11,'AAPT ExDa'!$B$2:$U$99, 11,FALSE), IFERROR(VLOOKUP($A11,'ABB ExDa'!$A$2:$N$184, 9,FALSE), IFERROR(VLOOKUP($A11,'Vocus SIT ExDa'!$B$2:$J$173, 8,FALSE), IFERROR(VLOOKUP($A11,'Telstra ExDa'!$B$2:$K$310, 0,FALSE), IFERROR(VLOOKUP($A11,'Vocus RVC ExDa'!$C$2:$R$155, 0,FALSE), IFERROR(VLOOKUP($A11,'Fusion ExDa'!$B$2:$D$16, 0,FALSE), IFERROR(VLOOKUP($A11,'Exetel ExDa'!$C$2:$N$14, 9,FALSE), IFERROR(VLOOKUP($A11,'Infinet ExDa'!$B$2:$E$14, 0,FALSE), "Not Found")))))))) -> 15/04/2022 | M11: =IFERROR(VLOOKUP($A11,'AAPT ExDa'!$B$2:$U$99, 0,FALSE), IFERROR(VLOOKUP($A11,'ABB ExDa'!$A$2:$N$184, 0,FALSE), IFERROR(VLOOKUP($A11,'Vocus SIT ExDa'!$B$2:$J$173, 0,FALSE), IFERROR(VLOOKUP($A11,'Telstra ExDa'!$B$2:$K$310, 0,FALSE), IFERROR(VLOOKUP($A11,'Vocus RVC ExDa'!$C$2:$R$155, 0,FALSE), IFERROR(VLOOKUP($A11,'Fusion ExDa'!$B$2:$D$16, 0,FALSE), IFERROR(VLOOKUP($A11,'Exetel ExDa'!$C$2:$N$14, 11,FALSE), IFERROR(VLOOKUP($A11,'Infinet ExDa'!$B$2:$E$14, 0,FALSE), "Not Found")))))))) -> Not Found | N11: =IFERROR(VLOOKUP($A11,'AAPT ExDa'!$B$2:$U$99, 0,FALSE), IFERROR(VLOOKUP($A11,'ABB ExDa'!$A$2:$N$184, 13,FALSE), IFERROR(VLOOKUP($A11,'Vocus SIT ExDa'!$B$2:$J$173, 0,FALSE), IFERROR(VLOOKUP($A11,'Telstra ExDa'!$B$2:$K$310, 0,FALSE), IFERROR(VLOOKUP($A11,'Vocus RVC ExDa'!$C$2:$R$155, 0,FALSE), IFERROR(VLOOKUP($A11,'Fusion ExDa'!$B$2:$D$16, 0,FALSE), IFERROR(VLOOKUP($A11,'Exetel ExDa'!$C$2:$N$14, 0,FALSE), IFERROR(VLOOKUP($A11,'Infinet ExDa'!$B$2:$E$14, 0,FALSE), "Not Found")))))))) -> Not Found
A12: BBA | B12: =IFERROR(VLOOKUP(A12,'Exetel ExDa'!$C$2:$N$14,4,FALSE),"No Data") -> No Data | C12: =IFERROR(VLOOKUP(A12,'AAPT ExDa'!$B$2:$U$99, 2,FALSE), IFERROR(VLOOKUP(A12,'ABB ExDa'!$A$2:$N$184, 2,FALSE), IFERROR(VLOOKUP(A12,'Vocus SIT ExDa'!$B$2:$J$173, 7,FALSE), IFERROR(VLOOKUP(A12,'Telstra ExDa'!$B$2:$K$310, 2,FALSE), IFERROR(VLOOKUP(A12,'Vocus RVC ExDa'!$C$2:$R$155, 3,FALSE), IFERROR(VLOOKUP(A12,'Fusion ExDa'!$B$2:$D$16, 2,FALSE), IFERROR(VLOOKUP(A12,'Exetel ExDa'!$C$2:$N$14, 2,FALSE), IFERROR(VLOOKUP(A12,'Infinet ExDa'!$B$2:$E$14, 2,FALSE), "Not Found")))))))) -> 0 | D12: =IFERROR(VLOOKUP($A12,'AAPT ExDa'!$B$2:$U$99, 15,FALSE), IFERROR(VLOOKUP($A12,'ABB ExDa'!$A$2:$N$184, 4,FALSE), IFERROR(VLOOKUP($A12,'Vocus SIT ExDa'!$B$2:$J$173, 5,FALSE), IFERROR(VLOOKUP($A12,'Telstra ExDa'!$B$2:$K$310, 8,FALSE), IFERROR(VLOOKUP($A12,'Vocus RVC ExDa'!$C$2:$R$155, 6,FALSE), IFERROR(VLOOKUP($A12,'Fusion ExDa'!$B$2:$D$16, 4,FALSE), IFERROR(VLOOKUP($A12,'Exetel ExDa'!$C$2:$N$14, 3,FALSE), IFERROR(VLOOKUP($A12,'Infinet ExDa'!$B$2:$E$14, 3,FALSE), "Not Found")))))))) -> AAPT | E12: =IFERROR(VLOOKUP($A12,'AAPT ExDa'!$B$2:$U$99, 3,FALSE), IFERROR(VLOOKUP($A12,'ABB ExDa'!$A$2:$N$184, 5,FALSE), IFERROR(VLOOKUP($A12,'Vocus SIT ExDa'!$B$2:$J$173, 2,FALSE), IFERROR(VLOOKUP($A12,'Telstra ExDa'!$B$2:$K$310, 4,FALSE), IFERROR(VLOOKUP($A12,'Vocus RVC ExDa'!$C$2:$R$155, 8,FALSE), IFERROR(VLOOKUP($A12,'Fusion ExDa'!$B$2:$D$16, 4,FALSE), IFERROR(VLOOKUP($A12,'Exetel ExDa'!$C$2:$N$14, 5,FALSE), IFERROR(VLOOKUP($A12,'Infinet ExDa'!$B$2:$E$14, 3,FALSE), "Not Found")))))))) -> IP-Line | F12: =IFERROR(VLOOKUP($A12,'AAPT ExDa'!$B$2:$U$99, 4,FALSE), IFERROR(VLOOKUP($A12,'ABB ExDa'!$A$2:$N$184, 6,FALSE), IFERROR(VLOOKUP($A12,'Vocus SIT ExDa'!$B$2:$J$173, 3,FALSE), IFERROR(VLOOKUP($A12,'Telstra ExDa'!$B$2:$K$310, 5,FALSE), IFERROR(VLOOKUP($A12,'Vocus RVC ExDa'!$C$2:$R$155, 9,FALSE), IFERROR(VLOOKUP($A12,'Fusion ExDa'!$B$2:$D$16, 0,FALSE), IFERROR(VLOOKUP($A12,'Exetel ExDa'!$C$2:$N$14, 6,FALSE), IFERROR(VLOOKUP($A12,'Infinet ExDa'!$B$2:$E$14, 0,FALSE), "Not Found")))))))) -> IP-Line Link | G12: =IFERROR(VLOOKUP($A12,'AAPT ExDa'!$B$2:$U$99, 5,FALSE), IFERROR(VLOOKUP($A12,'ABB ExDa'!$A$2:$N$184, 8,FALSE), IFERROR(VLOOKUP($A12,'Vocus SIT ExDa'!$B$2:$J$173, 6,FALSE), IFERROR(VLOOKUP($A12,'Telstra ExDa'!$B$2:$K$310, 0,FALSE), IFERROR(VLOOKUP($A12,'Vocus RVC ExDa'!$C$2:$R$155, 15,FALSE), IFERROR(VLOOKUP($A12,'Fusion ExDa'!$B$2:$D$16, 0,FALSE), IFERROR(VLOOKUP($A12,'Exetel ExDa'!$C$2:$N$14, 7,FALSE), IFERROR(VLOOKUP($A12,'Infinet ExDa'!$B$2:$E$14, 0,FALSE), "Not Found")))))))) -> Connecting IP-Line 6023265 to Access 1491923 | H12: =IFERROR(VLOOKUP($A12,'AAPT ExDa'!$B$2:$U$99, 6,FALSE), IFERROR(VLOOKUP($A12,'ABB ExDa'!$A$2:$N$184, 0,FALSE), IFERROR(VLOOKUP($A12,'Vocus SIT ExDa'!$B$2:$J$173, 0,FALSE), IFERROR(VLOOKUP($A12,'Telstra ExDa'!$B$2:$K$310, 0,FALSE), IFERROR(VLOOKUP($A12,'Vocus RVC ExDa'!$C$2:$R$155, 16,FALSE), IFERROR(VLOOKUP($A12,'Fusion ExDa'!$B$2:$D$16, 0,FALSE), IFERROR(VLOOKUP($A12,'Exetel ExDa'!$C$2:$N$14, 0,FALSE), IFERROR(VLOOKUP($A12,'Infinet ExDa'!$B$2:$E$14, 0,FALSE), "Not Found")))))))) -> Up to 100/40Mbps; AVC ID:AVC000043186325 | I12: =IFERROR(VLOOKUP($A12,'AAPT ExDa'!$B$2:$U$99, 0,FALSE), IFERROR(VLOOKUP($A12,'ABB ExDa'!$A$2:$N$184, 0,FALSE), IFERROR(VLOOKUP($A12,'Vocus SIT ExDa'!$B$2:$J$173, 0,FALSE), IFERROR(VLOOKUP($A12,'Telstra ExDa'!$B$2:$K$310, 0,FALSE), IFERROR(VLOOKUP($A12,'Vocus RVC ExDa'!$C$2:$R$155, 0,FALSE), IFERROR(VLOOKUP($A12,'Fusion ExDa'!$B$2:$D$16, 0,FALSE), IFERROR(VLOOKUP($A12,'Exetel ExDa'!$C$2:$N$14, 8,FALSE), IFERROR(VLOOKUP($A12,'Infinet ExDa'!$B$2:$E$14, 0,FALSE), "Not Found")))))))) -> Not Found | J12: =IFERROR(VLOOKUP($A12,'AAPT ExDa'!$B$2:$U$99, 7,FALSE), IFERROR(VLOOKUP($A12,'ABB ExDa'!$A$2:$N$184, 2,FALSE), IFERROR(VLOOKUP($A12,'Vocus SIT ExDa'!$B$2:$J$173, 0,FALSE), IFERROR(VLOOKUP($A12,'Telstra ExDa'!$B$2:$K$310, 7,FALSE), IFERROR(VLOOKUP($A12,'Vocus RVC ExDa'!$C$2:$R$155, 2,FALSE), IFERROR(VLOOKUP($A12,'Fusion ExDa'!$B$2:$D$16, 3,FALSE), IFERROR(VLOOKUP($A12,'Exetel ExDa'!$C$2:$N$14, 0,FALSE), IFERROR(VLOOKUP($A12,'Infinet ExDa'!$B$2:$E$14, 0,FALSE), "Not Found")))))))) -> AVC000043186325 | K12: =IFERROR(VLOOKUP($A12,'AAPT ExDa'!$B$2:$U$99, 12,FALSE), IFERROR(VLOOKUP($A12,'ABB ExDa'!$A$2:$N$184, 0,FALSE), IFERROR(VLOOKUP($A12,'Vocus SIT ExDa'!$B$2:$J$173, 0,FALSE), IFERROR(VLOOKUP($A12,'Telstra ExDa'!$B$2:$K$310, 0,FALSE), IFERROR(VLOOKUP($A12,'Vocus RVC ExDa'!$C$2:$R$155, 0,FALSE), IFERROR(VLOOKUP($A12,'Fusion ExDa'!$B$2:$D$16, 0,FALSE), IFERROR(VLOOKUP($A12,'Exetel ExDa'!$C$2:$N$14, 12,FALSE), IFERROR(VLOOKUP($A12,'Infinet ExDa'!$B$2:$E$14, 0,FALSE), "Not Found")))))))) -> 24 Months | L12: =IFERROR(VLOOKUP($A12,'AAPT ExDa'!$B$2:$U$99, 11,FALSE), IFERROR(VLOOKUP($A12,'ABB ExDa'!$A$2:$N$184, 9,FALSE), IFERROR(VLOOKUP($A12,'Vocus SIT ExDa'!$B$2:$J$173, 8,FALSE), IFERROR(VLOOKUP($A12,'Telstra ExDa'!$B$2:$K$310, 0,FALSE), IFERROR(VLOOKUP($A12,'Vocus RVC ExDa'!$C$2:$R$155, 0,FALSE), IFERROR(VLOOKUP($A12,'Fusion ExDa'!$B$2:$D$16, 0,FALSE), IFERROR(VLOOKUP($A12,'Exetel ExDa'!$C$2:$N$14, 9,FALSE), IFERROR(VLOOKUP($A12,'Infinet ExDa'!$B$2:$E$14, 0,FALSE), "Not Found")))))))) -> 42744 | M12: =IFERROR(VLOOKUP($A12,'AAPT ExDa'!$B$2:$U$99, 0,FALSE), IFERROR(VLOOKUP($A12,'ABB ExDa'!$A$2:$N$184, 0,FALSE), IFERROR(VLOOKUP($A12,'Vocus SIT ExDa'!$B$2:$J$173, 0,FALSE), IFERROR(VLOOKUP($A12,'Telstra ExDa'!$B$2:$K$310, 0,FALSE), IFERROR(VLOOKUP($A12,'Vocus RVC ExDa'!$C$2:$R$155, 0,FALSE), IFERROR(VLOOKUP($A12,'Fusion ExDa'!$B$2:$D$16, 0,FALSE), IFERROR(VLOOKUP($A12,'Exetel ExDa'!$C$2:$N$14, 11,FALSE), IFERROR(VLOOKUP($A12,'Infinet ExDa'!$B$2:$E$14, 0,FALSE), "Not Found")))))))) -> Not Found | N12: =IFERROR(VLOOKUP($A12,'AAPT ExDa'!$B$2:$U$99, 0,FALSE), IFERROR(VLOOKUP($A12,'ABB ExDa'!$A$2:$N$184, 13,FALSE), IFERROR(VLOOKUP($A12,'Vocus SIT ExDa'!$B$2:$J$173, 0,FALSE), IFERROR(VLOOKUP($A12,'Telstra ExDa'!$B$2:$K$310, 0,FALSE), IFERROR(VLOOKUP($A12,'Vocus RVC ExDa'!$C$2:$R$155, 0,FALSE), IFERROR(VLOOKUP($A12,'Fusion ExDa'!$B$2:$D$16, 0,FALSE), IFERROR(VLOOKUP($A12,'Exetel ExDa'!$C$2:$N$14, 0,FALSE), IFERROR(VLOOKUP($A12,'Infinet ExDa'!$B$2:$E$14, 0,FALSE), "Not Found")))))))) -> Not Found
A13: Body Corporate Systems | B13: =IFERROR(VLOOKUP(A13,'Exetel ExDa'!$C$2:$N$14,4,FALSE),"No Data") -> No Data | C13: =IFERROR(VLOOKUP(A13,'AAPT ExDa'!$B$2:$U$99, 2,FALSE), IFERROR(VLOOKUP(A13,'ABB ExDa'!$A$2:$N$184, 2,FALSE), IFERROR(VLOOKUP(A13,'Vocus SIT ExDa'!$B$2:$J$173, 7,FALSE), IFERROR(VLOOKUP(A13,'Telstra ExDa'!$B$2:$K$310, 2,FALSE), IFERROR(VLOOKUP(A13,'Vocus RVC ExDa'!$C$2:$R$155, 3,FALSE), IFERROR(VLOOKUP(A13,'Fusion ExDa'!$B$2:$D$16, 2,FALSE), IFERROR(VLOOKUP(A13,'Exetel ExDa'!$C$2:$N$14, 2,FALSE), IFERROR(VLOOKUP(A13,'Infinet ExDa'!$B$2:$E$14, 2,FALSE), "Not Found")))))))) -> Morningside | D13: =IFERROR(VLOOKUP($A13,'AAPT ExDa'!$B$2:$U$99, 15,FALSE), IFERROR(VLOOKUP($A13,'ABB ExDa'!$A$2:$N$184, 4,FALSE), IFERROR(VLOOKUP($A13,'Vocus SIT ExDa'!$B$2:$J$173, 5,FALSE), IFERROR(VLOOKUP($A13,'Telstra ExDa'!$B$2:$K$310, 8,FALSE), IFERROR(VLOOKUP($A13,'Vocus RVC ExDa'!$C$2:$R$155, 6,FALSE), IFERROR(VLOOKUP($A13,'Fusion ExDa'!$B$2:$D$16, 4,FALSE), IFERROR(VLOOKUP($A13,'Exetel ExDa'!$C$2:$N$14, 3,FALSE), IFERROR(VLOOKUP($A13,'Infinet ExDa'!$B$2:$E$14, 3,FALSE), "Not Found")))))))) -> AAPT | E13: =IFERROR(VLOOKUP($A13,'AAPT ExDa'!$B$2:$U$99, 3,FALSE), IFERROR(VLOOKUP($A13,'ABB ExDa'!$A$2:$N$184, 5,FALSE), IFERROR(VLOOKUP($A13,'Vocus SIT ExDa'!$B$2:$J$173, 2,FALSE), IFERROR(VLOOKUP($A13,'Telstra ExDa'!$B$2:$K$310, 4,FALSE), IFERROR(VLOOKUP($A13,'Vocus RVC ExDa'!$C$2:$R$155, 8,FALSE), IFERROR(VLOOKUP($A13,'Fusion ExDa'!$B$2:$D$16, 4,FALSE), IFERROR(VLOOKUP($A13,'Exetel ExDa'!$C$2:$N$14, 5,FALSE), IFERROR(VLOOKUP($A13,'Infinet ExDa'!$B$2:$E$14, 3,FALSE), "Not Found")))))))) -> IP-Line | F13: =IFERROR(VLOOKUP($A13,'AAPT ExDa'!$B$2:$U$99, 4,FALSE), IFERROR(VLOOKUP($A13,'ABB ExDa'!$A$2:$N$184, 6,FALSE), IFERROR(VLOOKUP($A13,'Vocus SIT ExDa'!$B$2:$J$173, 3,FALSE), IFERROR(VLOOKUP($A13,'Telstra ExDa'!$B$2:$K$310, 5,FALSE), IFERROR(VLOOKUP($A13,'Vocus RVC ExDa'!$C$2:$R$155, 9,FALSE), IFERROR(VLOOKUP($A13,'Fusion ExDa'!$B$2:$D$16, 0,FALSE), IFERROR(VLOOKUP($A13,'Exetel ExDa'!$C$2:$N$14, 6,FALSE), IFERROR(VLOOKUP($A13,'Infinet ExDa'!$B$2:$E$14, 0,FALSE), "Not Found")))))))) -> IP-Line | G13: =IFERROR(VLOOKUP($A13,'AAPT ExDa'!$B$2:$U$99, 5,FALSE), IFERROR(VLOOKUP($A13,'ABB ExDa'!$A$2:$N$184, 8,FALSE), IFERROR(VLOOKUP($A13,'Vocus SIT ExDa'!$B$2:$J$173, 6,FALSE), IFERROR(VLOOKUP($A13,'Telstra ExDa'!$B$2:$K$310, 0,FALSE), IFERROR(VLOOKUP($A13,'Vocus RVC ExDa'!$C$2:$R$155, 15,FALSE), IFERROR(VLOOKUP($A13,'Fusion ExDa'!$B$2:$D$16, 0,FALSE), IFERROR(VLOOKUP($A13,'Exetel ExDa'!$C$2:$N$14, 7,FALSE), IFERROR(VLOOKUP($A13,'Infinet ExDa'!$B$2:$E$14, 0,FALSE), "Not Found")))))))) -> 0 | H13: =IFERROR(VLOOKUP($A13,'AAPT ExDa'!$B$2:$U$99, 6,FALSE), IFERROR(VLOOKUP($A13,'ABB ExDa'!$A$2:$N$184, 0,FALSE), IFERROR(VLOOKUP($A13,'Vocus SIT ExDa'!$B$2:$J$173, 0,FALSE), IFERROR(VLOOKUP($A13,'Telstra ExDa'!$B$2:$K$310, 0,FALSE), IFERROR(VLOOKUP($A13,'Vocus RVC ExDa'!$C$2:$R$155, 16,FALSE), IFERROR(VLOOKUP($A13,'Fusion ExDa'!$B$2:$D$16, 0,FALSE), IFERROR(VLOOKUP($A13,'Exetel ExDa'!$C$2:$N$14, 0,FALSE), IFERROR(VLOOKUP($A13,'Infinet ExDa'!$B$2:$E$14, 0,FALSE), "Not Found")))))))) -> 0 | I13: =IFERROR(VLOOKUP($A13,'AAPT ExDa'!$B$2:$U$99, 0,FALSE), IFERROR(VLOOKUP($A13,'ABB ExDa'!$A$2:$N$184, 0,FALSE), IFERROR(VLOOKUP($A13,'Vocus SIT ExDa'!$B$2:$J$173, 0,FALSE), IFERROR(VLOOKUP($A13,'Telstra ExDa'!$B$2:$K$310, 0,FALSE), IFERROR(VLOOKUP($A13,'Vocus RVC ExDa'!$C$2:$R$155, 0,FALSE), IFERROR(VLOOKUP($A13,'Fusion ExDa'!$B$2:$D$16, 0,FALSE), IFERROR(VLOOKUP($A13,'Exetel ExDa'!$C$2:$N$14, 8,FALSE), IFERROR(VLOOKUP($A13,'Infinet ExDa'!$B$2:$E$14, 0,FALSE), "Not Found")))))))) -> Not Found | J13: =IFERROR(VLOOKUP($A13,'AAPT ExDa'!$B$2:$U$99, 7,FALSE), IFERROR(VLOOKUP($A13,'ABB ExDa'!$A$2:$N$184, 2,FALSE), IFERROR(VLOOKUP($A13,'Vocus SIT ExDa'!$B$2:$J$173, 0,FALSE), IFERROR(VLOOKUP($A13,'Telstra ExDa'!$B$2:$K$310, 7,FALSE), IFERROR(VLOOKUP($A13,'Vocus RVC ExDa'!$C$2:$R$155, 2,FALSE), IFERROR(VLOOKUP($A13,'Fusion ExDa'!$B$2:$D$16, 3,FALSE), IFERROR(VLOOKUP($A13,'Exetel ExDa'!$C$2:$N$14, 0,FALSE), IFERROR(VLOOKUP($A13,'Infinet ExDa'!$B$2:$E$14, 0,FALSE), "Not Found")))))))) -> 0 | K13: =IFERROR(VLOOKUP($A13,'AAPT ExDa'!$B$2:$U$99, 12,FALSE), IFERROR(VLOOKUP($A13,'ABB ExDa'!$A$2:$N$184, 0,FALSE), IFERROR(VLOOKUP($A13,'Vocus SIT ExDa'!$B$2:$J$173, 0,FALSE), IFERROR(VLOOKUP($A13,'Telstra ExDa'!$B$2:$K$310, 0,FALSE), IFERROR(VLOOKUP($A13,'Vocus RVC ExDa'!$C$2:$R$155, 0,FALSE), IFERROR(VLOOKUP($A13,'Fusion ExDa'!$B$2:$D$16, 0,FALSE), IFERROR(VLOOKUP($A13,'Exetel ExDa'!$C$2:$N$14, 12,FALSE), IFERROR(VLOOKUP($A13,'Infinet ExDa'!$B$2:$E$14, 0,FALSE), "Not Found")))))))) -> 36 Months | L13: =IFERROR(VLOOKUP($A13,'AAPT ExDa'!$B$2:$U$99, 11,FALSE), IFERROR(VLOOKUP($A13,'ABB ExDa'!$A$2:$N$184, 9,FALSE), IFERROR(VLOOKUP($A13,'Vocus SIT ExDa'!$B$2:$J$173, 8,FALSE), IFERROR(VLOOKUP($A13,'Telstra ExDa'!$B$2:$K$310, 0,FALSE), IFERROR(VLOOKUP($A13,'Vocus RVC ExDa'!$C$2:$R$155, 0,FALSE), IFERROR(VLOOKUP($A13,'Fusion ExDa'!$B$2:$D$16, 0,FALSE), IFERROR(VLOOKUP($A13,'Exetel ExDa'!$C$2:$N$14, 9,FALSE), IFERROR(VLOOKUP($A13,'Infinet ExDa'!$B$2:$E$14, 0,FALSE), "Not Found")))))))) -> 44904 | M13: =IFERROR(VLOOKUP($A13,'AAPT ExDa'!$B$2:$U$99, 0,FALSE), IFERROR(VLOOKUP($A13,'ABB ExDa'!$A$2:$N$184, 0,FALSE), IFERROR(VLOOKUP($A13,'Vocus SIT ExDa'!$B$2:$J$173, 0,FALSE), IFERROR(VLOOKUP($A13,'Telstra ExDa'!$B$2:$K$310, 0,FALSE), IFERROR(VLOOKUP($A13,'Vocus RVC ExDa'!$C$2:$R$155, 0,FALSE), IFERROR(VLOOKUP($A13,'Fusion ExDa'!$B$2:$D$16, 0,FALSE), IFERROR(VLOOKUP($A13,'Exetel ExDa'!$C$2:$N$14, 11,FALSE), IFERROR(VLOOKUP($A13,'Infinet ExDa'!$B$2:$E$14, 0,FALSE), "Not Found")))))))) -> Not Found | N13: =IFERROR(VLOOKUP($A13,'AAPT ExDa'!$B$2:$U$99, 0,FALSE), IFERROR(VLOOKUP($A13,'ABB ExDa'!$A$2:$N$184, 13,FALSE), IFERROR(VLOOKUP($A13,'Vocus SIT ExDa'!$B$2:$J$173, 0,FALSE), IFERROR(VLOOKUP($A13,'Telstra ExDa'!$B$2:$K$310, 0,FALSE), IFERROR(VLOOKUP($A13,'Vocus RVC ExDa'!$C$2:$R$155, 0,FALSE), IFERROR(VLOOKUP($A13,'Fusion ExDa'!$B$2:$D$16, 0,FALSE), IFERROR(VLOOKUP($A13,'Exetel ExDa'!$C$2:$N$14, 0,FALSE), IFERROR(VLOOKUP($A13,'Infinet ExDa'!$B$2:$E$14, 0,FALSE), "Not Found")))))))) -> Not Found
A14: Body Corporate Systems | B14: =IFERROR(VLOOKUP(A14,'Exetel ExDa'!$C$2:$N$14,4,FALSE),"No Data") -> No Data | C14: =IFERROR(VLOOKUP(A14,'AAPT ExDa'!$B$2:$U$99, 2,FALSE), IFERROR(VLOOKUP(A14,'ABB ExDa'!$A$2:$N$184, 2,FALSE), IFERROR(VLOOKUP(A14,'Vocus SIT ExDa'!$B$2:$J$173, 7,FALSE), IFERROR(VLOOKUP(A14,'Telstra ExDa'!$B$2:$K$310, 2,FALSE), IFERROR(VLOOKUP(A14,'Vocus RVC ExDa'!$C$2:$R$155, 3,FALSE), IFERROR(VLOOKUP(A14,'Fusion ExDa'!$B$2:$D$16, 2,FALSE), IFERROR(VLOOKUP(A14,'Exetel ExDa'!$C$2:$N$14, 2,FALSE), IFERROR(VLOOKUP(A14,'Infinet ExDa'!$B$2:$E$14, 2,FALSE), "Not Found")))))))) -> Morningside | D14: =IFERROR(VLOOKUP($A14,'AAPT ExDa'!$B$2:$U$99, 15,FALSE), IFERROR(VLOOKUP($A14,'ABB ExDa'!$A$2:$N$184, 4,FALSE), IFERROR(VLOOKUP($A14,'Vocus SIT ExDa'!$B$2:$J$173, 5,FALSE), IFERROR(VLOOKUP($A14,'Telstra ExDa'!$B$2:$K$310, 8,FALSE), IFERROR(VLOOKUP($A14,'Vocus RVC ExDa'!$C$2:$R$155, 6,FALSE), IFERROR(VLOOKUP($A14,'Fusion ExDa'!$B$2:$D$16, 4,FALSE), IFERROR(VLOOKUP($A14,'Exetel ExDa'!$C$2:$N$14, 3,FALSE), IFERROR(VLOOKUP($A14,'Infinet ExDa'!$B$2:$E$14, 3,FALSE), "Not Found")))))))) -> AAPT | E14: =IFERROR(VLOOKUP($A14,'AAPT ExDa'!$B$2:$U$99, 3,FALSE), IFERROR(VLOOKUP($A14,'ABB ExDa'!$A$2:$N$184, 5,FALSE), IFERROR(VLOOKUP($A14,'Vocus SIT ExDa'!$B$2:$J$173, 2,FALSE), IFERROR(VLOOKUP($A14,'Telstra ExDa'!$B$2:$K$310, 4,FALSE), IFERROR(VLOOKUP($A14,'Vocus RVC ExDa'!$C$2:$R$155, 8,FALSE), IFERROR(VLOOKUP($A14,'Fusion ExDa'!$B$2:$D$16, 4,FALSE), IFERROR(VLOOKUP($A14,'Exetel ExDa'!$C$2:$N$14, 5,FALSE), IFERROR(VLOOKUP($A14,'Infinet ExDa'!$B$2:$E$14, 3,FALSE), "Not Found")))))))) -> IP-Line | F14: =IFERROR(VLOOKUP($A14,'AAPT ExDa'!$B$2:$U$99, 4,FALSE), IFERROR(VLOOKUP($A14,'ABB ExDa'!$A$2:$N$184, 6,FALSE), IFERROR(VLOOKUP($A14,'Vocus SIT ExDa'!$B$2:$J$173, 3,FALSE), IFERROR(VLOOKUP($A14,'Telstra ExDa'!$B$2:$K$310, 5,FALSE), IFERROR(VLOOKUP($A14,'Vocus RVC ExDa'!$C$2:$R$155, 9,FALSE), IFERROR(VLOOKUP($A14,'Fusion ExDa'!$B$2:$D$16, 0,FALSE), IFERROR(VLOOKUP($A14,'Exetel ExDa'!$C$2:$N$14, 6,FALSE), IFERROR(VLOOKUP($A14,'Infinet ExDa'!$B$2:$E$14, 0,FALSE), "Not Found")))))))) -> IP-Line | G14: =IFERROR(VLOOKUP($A14,'AAPT ExDa'!$B$2:$U$99, 5,FALSE), IFERROR(VLOOKUP($A14,'ABB ExDa'!$A$2:$N$184, 8,FALSE), IFERROR(VLOOKUP($A14,'Vocus SIT ExDa'!$B$2:$J$173, 6,FALSE), IFERROR(VLOOKUP($A14,'Telstra ExDa'!$B$2:$K$310, 0,FALSE), IFERROR(VLOOKUP($A14,'Vocus RVC ExDa'!$C$2:$R$155, 15,FALSE), IFERROR(VLOOKUP($A14,'Fusion ExDa'!$B$2:$D$16, 0,FALSE), IFERROR(VLOOKUP($A14,'Exetel ExDa'!$C$2:$N$14, 7,FALSE), IFERROR(VLOOKUP($A14,'Infinet ExDa'!$B$2:$E$14, 0,FALSE), "Not Found")))))))) -> 0 | H14: =IFERROR(VLOOKUP($A14,'AAPT ExDa'!$B$2:$U$99, 6,FALSE), IFERROR(VLOOKUP($A14,'ABB ExDa'!$A$2:$N$184, 0,FALSE), IFERROR(VLOOKUP($A14,'Vocus SIT ExDa'!$B$2:$J$173, 0,FALSE), IFERROR(VLOOKUP($A14,'Telstra ExDa'!$B$2:$K$310, 0,FALSE), IFERROR(VLOOKUP($A14,'Vocus RVC ExDa'!$C$2:$R$155, 16,FALSE), IFERROR(VLOOKUP($A14,'Fusion ExDa'!$B$2:$D$16, 0,FALSE), IFERROR(VLOOKUP($A14,'Exetel ExDa'!$C$2:$N$14, 0,FALSE), IFERROR(VLOOKUP($A14,'Infinet ExDa'!$B$2:$E$14, 0,FALSE), "Not Found")))))))) -> 0 | I14: =IFERROR(VLOOKUP($A14,'AAPT ExDa'!$B$2:$U$99, 0,FALSE), IFERROR(VLOOKUP($A14,'ABB ExDa'!$A$2:$N$184, 0,FALSE), IFERROR(VLOOKUP($A14,'Vocus SIT ExDa'!$B$2:$J$173, 0,FALSE), IFERROR(VLOOKUP($A14,'Telstra ExDa'!$B$2:$K$310, 0,FALSE), IFERROR(VLOOKUP($A14,'Vocus RVC ExDa'!$C$2:$R$155, 0,FALSE), IFERROR(VLOOKUP($A14,'Fusion ExDa'!$B$2:$D$16, 0,FALSE), IFERROR(VLOOKUP($A14,'Exetel ExDa'!$C$2:$N$14, 8,FALSE), IFERROR(VLOOKUP($A14,'Infinet ExDa'!$B$2:$E$14, 0,FALSE), "Not Found")))))))) -> Not Found | J14: =IFERROR(VLOOKUP($A14,'AAPT ExDa'!$B$2:$U$99, 7,FALSE), IFERROR(VLOOKUP($A14,'ABB ExDa'!$A$2:$N$184, 2,FALSE), IFERROR(VLOOKUP($A14,'Vocus SIT ExDa'!$B$2:$J$173, 0,FALSE), IFERROR(VLOOKUP($A14,'Telstra ExDa'!$B$2:$K$310, 7,FALSE), IFERROR(VLOOKUP($A14,'Vocus RVC ExDa'!$C$2:$R$155, 2,FALSE), IFERROR(VLOOKUP($A14,'Fusion ExDa'!$B$2:$D$16, 3,FALSE), IFERROR(VLOOKUP($A14,'Exetel ExDa'!$C$2:$N$14, 0,FALSE), IFERROR(VLOOKUP($A14,'Infinet ExDa'!$B$2:$E$14, 0,FALSE), "Not Found")))))))) -> 0 | K14: =IFERROR(VLOOKUP($A14,'AAPT ExDa'!$B$2:$U$99, 12,FALSE), IFERROR(VLOOKUP($A14,'ABB ExDa'!$A$2:$N$184, 0,FALSE), IFERROR(VLOOKUP($A14,'Vocus SIT ExDa'!$B$2:$J$173, 0,FALSE), IFERROR(VLOOKUP($A14,'Telstra ExDa'!$B$2:$K$310, 0,FALSE), IFERROR(VLOOKUP($A14,'Vocus RVC ExDa'!$C$2:$R$155, 0,FALSE), IFERROR(VLOOKUP($A14,'Fusion ExDa'!$B$2:$D$16, 0,FALSE), IFERROR(VLOOKUP($A14,'Exetel ExDa'!$C$2:$N$14, 12,FALSE), IFERROR(VLOOKUP($A14,'Infinet ExDa'!$B$2:$E$14, 0,FALSE), "Not Found")))))))) -> 36 Months | L14: =IFERROR(VLOOKUP($A14,'AAPT ExDa'!$B$2:$U$99, 11,FALSE), IFERROR(VLOOKUP($A14,'ABB ExDa'!$A$2:$N$184, 9,FALSE), IFERROR(VLOOKUP($A14,'Vocus SIT ExDa'!$B$2:$J$173, 8,FALSE), IFERROR(VLOOKUP($A14,'Telstra ExDa'!$B$2:$K$310, 0,FALSE), IFERROR(VLOOKUP($A14,'Vocus RVC ExDa'!$C$2:$R$155, 0,FALSE), IFERROR(VLOOKUP($A14,'Fusion ExDa'!$B$2:$D$16, 0,FALSE), IFERROR(VLOOKUP($A14,'Exetel ExDa'!$C$2:$N$14, 9,FALSE), IFERROR(VLOOKUP($A14,'Infinet ExDa'!$B$2:$E$14, 0,FALSE), "Not Found")))))))) -> 44904 | M14: =IFERROR(VLOOKUP($A14,'AAPT ExDa'!$B$2:$U$99, 0,FALSE), IFERROR(VLOOKUP($A14,'ABB ExDa'!$A$2:$N$184, 0,FALSE), IFERROR(VLOOKUP($A14,'Vocus SIT ExDa'!$B$2:$J$173, 0,FALSE), IFERROR(VLOOKUP($A14,'Telstra ExDa'!$B$2:$K$310, 0,FALSE), IFERROR(VLOOKUP($A14,'Vocus RVC ExDa'!$C$2:$R$155, 0,FALSE), IFERROR(VLOOKUP($A14,'Fusion ExDa'!$B$2:$D$16, 0,FALSE), IFERROR(VLOOKUP($A14,'Exetel ExDa'!$C$2:$N$14, 11,FALSE), IFERROR(VLOOKUP($A14,'Infinet ExDa'!$B$2:$E$14, 0,FALSE), "Not Found")))))))) -> Not Found | N14: =IFERROR(VLOOKUP($A14,'AAPT ExDa'!$B$2:$U$99, 0,FALSE), IFERROR(VLOOKUP($A14,'ABB ExDa'!$A$2:$N$184, 13,FALSE), IFERROR(VLOOKUP($A14,'Vocus SIT ExDa'!$B$2:$J$173, 0,FALSE), IFERROR(VLOOKUP($A14,'Telstra ExDa'!$B$2:$K$310, 0,FALSE), IFERROR(VLOOKUP($A14,'Vocus RVC ExDa'!$C$2:$R$155, 0,FALSE), IFERROR(VLOOKUP($A14,'Fusion ExDa'!$B$2:$D$16, 0,FALSE), IFERROR(VLOOKUP($A14,'Exetel ExDa'!$C$2:$N$14, 0,FALSE), IFERROR(VLOOKUP($A14,'Infinet ExDa'!$B$2:$E$14, 0,FALSE), "Not Found")))))))) -> Not Found
... A241: Zambrero Yarraville | B241: =IFERROR(VLOOKUP(A241,'Exetel ExDa'!$C$2:$N$14,4,FALSE),"No Data") -> No Data | C241: =IFERROR(VLOOKUP(A241,'AAPT ExDa'!$B$2:$U$99, 2,FALSE), IFERROR(VLOOKUP(A241,'ABB ExDa'!$A$2:$N$184, 2,FALSE), IFERROR(VLOOKUP(A241,'Vocus SIT ExDa'!$B$2:$J$173, 7,FALSE), IFERROR(VLOOKUP(A241,'Telstra ExDa'!$B$2:$K$310, 2,FALSE), IFERROR(VLOOKUP(A241,'Vocus RVC ExDa'!$C$2:$R$155, 3,FALSE), IFERROR(VLOOKUP(A241,'Fusion ExDa'!$B$2:$D$16, 2,FALSE), IFERROR(VLOOKUP(A241,'Exetel ExDa'!$C$2:$N$14, 2,FALSE), IFERROR(VLOOKUP(A241,'Infinet ExDa'!$B$2:$E$14, 2,FALSE), "Not Found")))))))) -> 27A ANDERSON ST, YARRAVILLE VIC | D241: =IFERROR(VLOOKUP($A241,'AAPT ExDa'!$B$2:$U$99, 15,FALSE), IFERROR(VLOOKUP($A241,'ABB ExDa'!$A$2:$N$184, 4,FALSE), IFERROR(VLOOKUP($A241,'Vocus SIT ExDa'!$B$2:$J$173, 5,FALSE), IFERROR(VLOOKUP($A241,'Telstra ExDa'!$B$2:$K$310, 8,FALSE), IFERROR(VLOOKUP($A241,'Vocus RVC ExDa'!$C$2:$R$155, 6,FALSE), IFERROR(VLOOKUP($A241,'Fusion ExDa'!$B$2:$D$16, 4,FALSE), IFERROR(VLOOKUP($A241,'Exetel ExDa'!$C$2:$N$14, 3,FALSE), IFERROR(VLOOKUP($A241,'Infinet ExDa'!$B$2:$E$14, 3,FALSE), "Not Found")))))))) -> ABB | E241: =IFERROR(VLOOKUP($A241,'AAPT ExDa'!$B$2:$U$99, 3,FALSE), IFERROR(VLOOKUP($A241,'ABB ExDa'!$A$2:$N$184, 5,FALSE), IFERROR(VLOOKUP($A241,'Vocus SIT ExDa'!$B$2:$J$173, 2,FALSE), IFERROR(VLOOKUP($A241,'Telstra ExDa'!$B$2:$K$310, 4,FALSE), IFERROR(VLOOKUP($A241,'Vocus RVC ExDa'!$C$2:$R$155, 8,FALSE), IFERROR(VLOOKUP($A241,'Fusion ExDa'!$B$2:$D$16, 4,FALSE), IFERROR(VLOOKUP($A241,'Exetel ExDa'!$C$2:$N$14, 5,FALSE), IFERROR(VLOOKUP($A241,'Infinet ExDa'!$B$2:$E$14, 3,FALSE), "Not Found")))))))) -> NBN 25/10 | F241: =IFERROR(VLOOKUP($A241,'AAPT ExDa'!$B$2:$U$99, 4,FALSE), IFERROR(VLOOKUP($A241,'ABB ExDa'!$A$2:$N$184, 6,FALSE), IFERROR(VLOOKUP($A241,'Vocus SIT ExDa'!$B$2:$J$173, 3,FALSE), IFERROR(VLOOKUP($A241,'Telstra ExDa'!$B$2:$K$310, 5,FALSE), IFERROR(VLOOKUP($A241,'Vocus RVC ExDa'!$C$2:$R$155, 9,FALSE), IFERROR(VLOOKUP($A241,'Fusion ExDa'!$B$2:$D$16, 0,FALSE), IFERROR(VLOOKUP($A241,'Exetel ExDa'!$C$2:$N$14, 6,FALSE), IFERROR(VLOOKUP($A241,'Infinet ExDa'!$B$2:$E$14, 0,FALSE), "Not Found")))))))) -> Fibre | G241: =IFERROR(VLOOKUP($A241,'AAPT ExDa'!$B$2:$U$99, 5,FALSE), IFERROR(VLOOKUP($A241,'ABB ExDa'!$A$2:$N$184, 8,FALSE), IFERROR(VLOOKUP($A241,'Vocus SIT ExDa'!$B$2:$J$173, 6,FALSE), IFERROR(VLOOKUP($A241,'Telstra ExDa'!$B$2:$K$310, 0,FALSE), IFERROR(VLOOKUP($A241,'Vocus RVC ExDa'!$C$2:$R$155, 15,FALSE), IFERROR(VLOOKUP($A241,'Fusion ExDa'!$B$2:$D$16, 0,FALSE), IFERROR(VLOOKUP($A241,'Exetel ExDa'!$C$2:$N$14, 7,FALSE), IFERROR(VLOOKUP($A241,'Infinet ExDa'!$B$2:$E$14, 0,FALSE), "Not Found")))))))) -> 144.6.216.156 | H241: =IFERROR(VLOOKUP($A241,'AAPT ExDa'!$B$2:$U$99, 6,FALSE), IFERROR(VLOOKUP($A241,'ABB ExDa'!$A$2:$N$184, 0,FALSE), IFERROR(VLOOKUP($A241,'Vocus SIT ExDa'!$B$2:$J$173, 0,FALSE), IFERROR(VLOOKUP($A241,'Telstra ExDa'!$B$2:$K$310, 0,FALSE), IFERROR(VLOOKUP($A241,'Vocus RVC ExDa'!$C$2:$R$155, 16,FALSE), IFERROR(VLOOKUP($A241,'Fusion ExDa'!$B$2:$D$16, 0,FALSE), IFERROR(VLOOKUP($A241,'Exetel ExDa'!$C$2:$N$14, 0,FALSE), IFERROR(VLOOKUP($A241,'Infinet ExDa'!$B$2:$E$14, 0,FALSE), "Not Found")))))))) -> Not Found | I241: =IFERROR(VLOOKUP($A241,'AAPT ExDa'!$B$2:$U$99, 0,FALSE), IFERROR(VLOOKUP($A241,'ABB ExDa'!$A$2:$N$184, 0,FALSE), IFERROR(VLOOKUP($A241,'Vocus SIT ExDa'!$B$2:$J$173, 0,FALSE), IFERROR(VLOOKUP($A241,'Telstra ExDa'!$B$2:$K$310, 0,FALSE), IFERROR(VLOOKUP($A241,'Vocus RVC ExDa'!$C$2:$R$155, 0,FALSE), IFERROR(VLOOKUP($A241,'Fusion ExDa'!$B$2:$D$16, 0,FALSE), IFERROR(VLOOKUP($A241,'Exetel ExDa'!$C$2:$N$14, 8,FALSE), IFERROR(VLOOKUP($A241,'Infinet ExDa'!$B$2:$E$14, 0,FALSE), "Not Found")))))))) -> Not Found | J241: =IFERROR(VLOOKUP($A241,'AAPT ExDa'!$B$2:$U$99, 7,FALSE), IFERROR(VLOOKUP($A241,'ABB ExDa'!$A$2:$N$184, 2,FALSE), IFERROR(VLOOKUP($A241,'Vocus SIT ExDa'!$B$2:$J$173, 0,FALSE), IFERROR(VLOOKUP($A241,'Telstra ExDa'!$B$2:$K$310, 7,FALSE), IFERROR(VLOOKUP($A241,'Vocus RVC ExDa'!$C$2:$R$155, 2,FALSE), IFERROR(VLOOKUP($A241,'Fusion ExDa'!$B$2:$D$16, 3,FALSE), IFERROR(VLOOKUP($A241,'Exetel ExDa'!$C$2:$N$14, 0,FALSE), IFERROR(VLOOKUP($A241,'Infinet ExDa'!$B$2:$E$14, 0,FALSE), "Not Found")))))))) -> 27A ANDERSON ST, YARRAVILLE VIC | K241: =IFERROR(VLOOKUP($A241,'AAPT ExDa'!$B$2:$U$99, 12,FALSE), IFERROR(VLOOKUP($A241,'ABB ExDa'!$A$2:$N$184, 0,FALSE), IFERROR(VLOOKUP($A241,'Vocus SIT ExDa'!$B$2:$J$173, 0,FALSE), IFERROR(VLOOKUP($A241,'Telstra ExDa'!$B$2:$K$310, 0,FALSE), IFERROR(VLOOKUP($A241,'Vocus RVC ExDa'!$C$2:$R$155, 0,FALSE), IFERROR(VLOOKUP($A241,'Fusion ExDa'!$B$2:$D$16, 0,FALSE), IFERROR(VLOOKUP($A241,'Exetel ExDa'!$C$2:$N$14, 12,FALSE), IFERROR(VLOOKUP($A241,'Infinet ExDa'!$B$2:$E$14, 0,FALSE), "Not Found")))))))) -> Not Found | L241: =IFERROR(VLOOKUP($A241,'AAPT ExDa'!$B$2:$U$99, 11,FALSE), IFERROR(VLOOKUP($A241,'ABB ExDa'!$A$2:$N$184, 9,FALSE), IFERROR(VLOOKUP($A241,'Vocus SIT ExDa'!$B$2:$J$173, 8,FALSE), IFERROR(VLOOKUP($A241,'Telstra ExDa'!$B$2:$K$310, 0,FALSE), IFERROR(VLOOKUP($A241,'Vocus RVC ExDa'!$C$2:$R$155, 0,FALSE), IFERROR(VLOOKUP($A241,'Fusion ExDa'!$B$2:$D$16, 0,FALSE), IFERROR(VLOOKUP($A241,'Exetel ExDa'!$C$2:$N$14, 9,FALSE), IFERROR(VLOOKUP($A241,'Infinet ExDa'!$B$2:$E$14, 0,FALSE), "Not Found")))))))) -> 05 Sept 2024 | M241: =IFERROR(VLOOKUP($A241,'AAPT ExDa'!$B$2:$U$99, 0,FALSE), IFERROR(VLOOKUP($A241,'ABB ExDa'!$A$2:$N$184, 0,FALSE), IFERROR(VLOOKUP($A241,'Vocus SIT ExDa'!$B$2:$J$173, 0,FALSE), IFERROR(VLOOKUP($A241,'Telstra ExDa'!$B$2:$K$310, 0,FALSE), IFERROR(VLOOKUP($A241,'Vocus RVC ExDa'!$C$2:$R$155, 0,FALSE), IFERROR(VLOOKUP($A241,'Fusion ExDa'!$B$2:$D$16, 0,FALSE), IFERROR(VLOOKUP($A241,'Exetel ExDa'!$C$2:$N$14, 11,FALSE), IFERROR(VLOOKUP($A241,'Infinet ExDa'!$B$2:$E$14, 0,FALSE), "Not Found")))))))) -> Not Found | N241: =IFERROR(VLOOKUP($A241,'AAPT ExDa'!$B$2:$U$99, 0,FALSE), IFERROR(VLOOKUP($A241,'ABB ExDa'!$A$2:$N$184, 13,FALSE), IFERROR(VLOOKUP($A241,'Vocus SIT ExDa'!$B$2:$J$173, 0,FALSE), IFERROR(VLOOKUP($A241,'Telstra ExDa'!$B$2:$K$310, 0,FALSE), IFERROR(VLOOKUP($A241,'Vocus RVC ExDa'!$C$2:$R$155, 0,FALSE), IFERROR(VLOOKUP($A241,'Fusion ExDa'!$B$2:$D$16, 0,FALSE), IFERROR(VLOOKUP($A241,'Exetel ExDa'!$C$2:$N$14, 0,FALSE), IFERROR(VLOOKUP($A241,'Infinet ExDa'!$B$2:$E$14, 0,FALSE), "Not Found")))))))) -> Onebill
A242: 0 | B242: =IFERROR(VLOOKUP(A242,'Exetel ExDa'!$C$2:$N$14,4,FALSE),"No Data") -> No Data | C242: =IFERROR(VLOOKUP(A242,'AAPT ExDa'!$B$2:$U$99, 2,FALSE), IFERROR(VLOOKUP(A242,'ABB ExDa'!$A$2:$N$184, 2,FALSE), IFERROR(VLOOKUP(A242,'Vocus SIT ExDa'!$B$2:$J$173, 7,FALSE), IFERROR(VLOOKUP(A242,'Telstra ExDa'!$B$2:$K$310, 2,FALSE), IFERROR(VLOOKUP(A242,'Vocus RVC ExDa'!$C$2:$R$155, 3,FALSE), IFERROR(VLOOKUP(A242,'Fusion ExDa'!$B$2:$D$16, 2,FALSE), IFERROR(VLOOKUP(A242,'Exetel ExDa'!$C$2:$N$14, 2,FALSE), IFERROR(VLOOKUP(A242,'Infinet ExDa'!$B$2:$E$14, 2,FALSE), "Not Found")))))))) -> Not Found | D242: =IFERROR(VLOOKUP($A242,'AAPT ExDa'!$B$2:$U$99, 15,FALSE), IFERROR(VLOOKUP($A242,'ABB ExDa'!$A$2:$N$184, 4,FALSE), IFERROR(VLOOKUP($A242,'Vocus SIT ExDa'!$B$2:$J$173, 5,FALSE), IFERROR(VLOOKUP($A242,'Telstra ExDa'!$B$2:$K$310, 8,FALSE), IFERROR(VLOOKUP($A242,'Vocus RVC ExDa'!$C$2:$R$155, 6,FALSE), IFERROR(VLOOKUP($A242,'Fusion ExDa'!$B$2:$D$16, 4,FALSE), IFERROR(VLOOKUP($A242,'Exetel ExDa'!$C$2:$N$14, 3,FALSE), IFERROR(VLOOKUP($A242,'Infinet ExDa'!$B$2:$E$14, 3,FALSE), "Not Found")))))))) -> Not Found | E242: =IFERROR(VLOOKUP($A242,'AAPT ExDa'!$B$2:$U$99, 3,FALSE), IFERROR(VLOOKUP($A242,'ABB ExDa'!$A$2:$N$184, 5,FALSE), IFERROR(VLOOKUP($A242,'Vocus SIT ExDa'!$B$2:$J$173, 2,FALSE), IFERROR(VLOOKUP($A242,'Telstra ExDa'!$B$2:$K$310, 4,FALSE), IFERROR(VLOOKUP($A242,'Vocus RVC ExDa'!$C$2:$R$155, 8,FALSE), IFERROR(VLOOKUP($A242,'Fusion ExDa'!$B$2:$D$16, 4,FALSE), IFERROR(VLOOKUP($A242,'Exetel ExDa'!$C$2:$N$14, 5,FALSE), IFERROR(VLOOKUP($A242,'Infinet ExDa'!$B$2:$E$14, 3,FALSE), "Not Found")))))))) -> Not Found | F242: =IFERROR(VLOOKUP($A242,'AAPT ExDa'!$B$2:$U$99, 4,FALSE), IFERROR(VLOOKUP($A242,'ABB ExDa'!$A$2:$N$184, 6,FALSE), IFERROR(VLOOKUP($A242,'Vocus SIT ExDa'!$B$2:$J$173, 3,FALSE), IFERROR(VLOOKUP($A242,'Telstra ExDa'!$B$2:$K$310, 5,FALSE), IFERROR(VLOOKUP($A242,'Vocus RVC ExDa'!$C$2:$R$155, 9,FALSE), IFERROR(VLOOKUP($A242,'Fusion ExDa'!$B$2:$D$16, 0,FALSE), IFERROR(VLOOKUP($A242,'Exetel ExDa'!$C$2:$N$14, 6,FALSE), IFERROR(VLOOKUP($A242,'Infinet ExDa'!$B$2:$E$14, 0,FALSE), "Not Found")))))))) -> Not Found | G242: =IFERROR(VLOOKUP($A242,'AAPT ExDa'!$B$2:$U$99, 5,FALSE), IFERROR(VLOOKUP($A242,'ABB ExDa'!$A$2:$N$184, 8,FALSE), IFERROR(VLOOKUP($A242,'Vocus SIT ExDa'!$B$2:$J$173, 6,FALSE), IFERROR(VLOOKUP($A242,'Telstra ExDa'!$B$2:$K$310, 0,FALSE), IFERROR(VLOOKUP($A242,'Vocus RVC ExDa'!$C$2:$R$155, 15,FALSE), IFERROR(VLOOKUP($A242,'Fusion ExDa'!$B$2:$D$16, 0,FALSE), IFERROR(VLOOKUP($A242,'Exetel ExDa'!$C$2:$N$14, 7,FALSE), IFERROR(VLOOKUP($A242,'Infinet ExDa'!$B$2:$E$14, 0,FALSE), "Not Found")))))))) -> Not Found | H242: =IFERROR(VLOOKUP($A242,'AAPT ExDa'!$B$2:$U$99, 6,FALSE), IFERROR(VLOOKUP($A242,'ABB ExDa'!$A$2:$N$184, 0,FALSE), IFERROR(VLOOKUP($A242,'Vocus SIT ExDa'!$B$2:$J$173, 0,FALSE), IFERROR(VLOOKUP($A242,'Telstra ExDa'!$B$2:$K$310, 0,FALSE), IFERROR(VLOOKUP($A242,'Vocus RVC ExDa'!$C$2:$R$155, 16,FALSE), IFERROR(VLOOKUP($A242,'Fusion ExDa'!$B$2:$D$16, 0,FALSE), IFERROR(VLOOKUP($A242,'Exetel ExDa'!$C$2:$N$14, 0,FALSE), IFERROR(VLOOKUP($A242,'Infinet ExDa'!$B$2:$E$14, 0,FALSE), "Not Found")))))))) -> Not Found | I242: =IFERROR(VLOOKUP($A242,'AAPT ExDa'!$B$2:$U$99, 0,FALSE), IFERROR(VLOOKUP($A242,'ABB ExDa'!$A$2:$N$184, 0,FALSE), IFERROR(VLOOKUP($A242,'Vocus SIT ExDa'!$B$2:$J$173, 0,FALSE), IFERROR(VLOOKUP($A242,'Telstra ExDa'!$B$2:$K$310, 0,FALSE), IFERROR(VLOOKUP($A242,'Vocus RVC ExDa'!$C$2:$R$155, 0,FALSE), IFERROR(VLOOKUP($A242,'Fusion ExDa'!$B$2:$D$16, 0,FALSE), IFERROR(VLOOKUP($A242,'Exetel ExDa'!$C$2:$N$14, 8,FALSE), IFERROR(VLOOKUP($A242,'Infinet ExDa'!$B$2:$E$14, 0,FALSE), "Not Found")))))))) -> Not Found | J242: =IFERROR(VLOOKUP($A242,'AAPT ExDa'!$B$2:$U$99, 7,FALSE), IFERROR(VLOOKUP($A242,'ABB ExDa'!$A$2:$N$184, 2,FALSE), IFERROR(VLOOKUP($A242,'Vocus SIT ExDa'!$B$2:$J$173, 0,FALSE), IFERROR(VLOOKUP($A242,'Telstra ExDa'!$B$2:$K$310, 7,FALSE), IFERROR(VLOOKUP($A242,'Vocus RVC ExDa'!$C$2:$R$155, 2,FALSE), IFERROR(VLOOKUP($A242,'Fusion ExDa'!$B$2:$D$16, 3,FALSE), IFERROR(VLOOKUP($A242,'Exetel ExDa'!$C$2:$N$14, 0,FALSE), IFERROR(VLOOKUP($A242,'Infinet ExDa'!$B$2:$E$14, 0,FALSE), "Not Found")))))))) -> Not Found | K242: =IFERROR(VLOOKUP($A242,'AAPT ExDa'!$B$2:$U$99, 12,FALSE), IFERROR(VLOOKUP($A242,'ABB ExDa'!$A$2:$N$184, 0,FALSE), IFERROR(VLOOKUP($A242,'Vocus SIT ExDa'!$B$2:$J$173, 0,FALSE), IFERROR(VLOOKUP($A242,'Telstra ExDa'!$B$2:$K$310, 0,FALSE), IFERROR(VLOOKUP($A242,'Vocus RVC ExDa'!$C$2:$R$155, 0,FALSE), IFERROR(VLOOKUP($A242,'Fusion ExDa'!$B$2:$D$16, 0,FALSE), IFERROR(VLOOKUP($A242,'Exetel ExDa'!$C$2:$N$14, 12,FALSE), IFERROR(VLOOKUP($A242,'Infinet ExDa'!$B$2:$E$14, 0,FALSE), "Not Found")))))))) -> Not Found | L242: =IFERROR(VLOOKUP($A242,'AAPT ExDa'!$B$2:$U$99, 11,FALSE), IFERROR(VLOOKUP($A242,'ABB ExDa'!$A$2:$N$184, 9,FALSE), IFERROR(VLOOKUP($A242,'Vocus SIT ExDa'!$B$2:$J$173, 8,FALSE), IFERROR(VLOOKUP($A242,'Telstra ExDa'!$B$2:$K$310, 0,FALSE), IFERROR(VLOOKUP($A242,'Vocus RVC ExDa'!$C$2:$R$155, 0,FALSE), IFERROR(VLOOKUP($A242,'Fusion ExDa'!$B$2:$D$16, 0,FALSE), IFERROR(VLOOKUP($A242,'Exetel ExDa'!$C$2:$N$14, 9,FALSE), IFERROR(VLOOKUP($A242,'Infinet ExDa'!$B$2:$E$14, 0,FALSE), "Not Found")))))))) -> Not Found | M242: =IFERROR(VLOOKUP($A242,'AAPT ExDa'!$B$2:$U$99, 0,FALSE), IFERROR(VLOOKUP($A242,'ABB ExDa'!$A$2:$N$184, 0,FALSE), IFERROR(VLOOKUP($A242,'Vocus SIT ExDa'!$B$2:$J$173, 0,FALSE), IFERROR(VLOOKUP($A242,'Telstra ExDa'!$B$2:$K$310, 0,FALSE), IFERROR(VLOOKUP($A242,'Vocus RVC ExDa'!$C$2:$R$155, 0,FALSE), IFERROR(VLOOKUP($A242,'Fusion ExDa'!$B$2:$D$16, 0,FALSE), IFERROR(VLOOKUP($A242,'Exetel ExDa'!$C$2:$N$14, 11,FALSE), IFERROR(VLOOKUP($A242,'Infinet ExDa'!$B$2:$E$14, 0,FALSE), "Not Found")))))))) -> Not Found | N242: =IFERROR(VLOOKUP($A242,'AAPT ExDa'!$B$2:$U$99, 0,FALSE), IFERROR(VLOOKUP($A242,'ABB ExDa'!$A$2:$N$184, 13,FALSE), IFERROR(VLOOKUP($A242,'Vocus SIT ExDa'!$B$2:$J$173, 0,FALSE), IFERROR(VLOOKUP($A242,'Telstra ExDa'!$B$2:$K$310, 0,FALSE), IFERROR(VLOOKUP($A242,'Vocus RVC ExDa'!$C$2:$R$155, 0,FALSE), IFERROR(VLOOKUP($A242,'Fusion ExDa'!$B$2:$D$16, 0,FALSE), IFERROR(VLOOKUP($A242,'Exetel ExDa'!$C$2:$N$14, 0,FALSE), IFERROR(VLOOKUP($A242,'Infinet ExDa'!$B$2:$E$14, 0,FALSE), "Not Found")))))))) -> Not Found
A243: Sparrow Early Learning Coolamon | B243: =IFERROR(VLOOKUP(A243,'Exetel ExDa'!$C$2:$N$14,4,FALSE),"No Data") -> No Data | C243: =IFERROR(VLOOKUP(A243,'AAPT ExDa'!$B$2:$U$99, 2,FALSE), IFERROR(VLOOKUP(A243,'ABB ExDa'!$A$2:$N$184, 2,FALSE), IFERROR(VLOOKUP(A243,'Vocus SIT ExDa'!$B$2:$J$173, 7,FALSE), IFERROR(VLOOKUP(A243,'Telstra ExDa'!$B$2:$K$310, 2,FALSE), IFERROR(VLOOKUP(A243,'Vocus RVC ExDa'!$C$2:$R$155, 3,FALSE), IFERROR(VLOOKUP(A243,'Fusion ExDa'!$B$2:$D$16, 2,FALSE), IFERROR(VLOOKUP(A243,'Exetel ExDa'!$C$2:$N$14, 2,FALSE), IFERROR(VLOOKUP(A243,'Infinet ExDa'!$B$2:$E$14, 2,FALSE), "Not Found")))))))) -> 136 COOLAMON BVD, ELLENBROOK WA | D243: =IFERROR(VLOOKUP($A243,'AAPT ExDa'!$B$2:$U$99, 15,FALSE), IFERROR(VLOOKUP($A243,'ABB ExDa'!$A$2:$N$184, 4,FALSE), IFERROR(VLOOKUP($A243,'Vocus SIT ExDa'!$B$2:$J$173, 5,FALSE), IFERROR(VLOOKUP($A243,'Telstra ExDa'!$B$2:$K$310, 8,FALSE), IFERROR(VLOOKUP($A243,'Vocus RVC ExDa'!$C$2:$R$155, 6,FALSE), IFERROR(VLOOKUP($A243,'Fusion ExDa'!$B$2:$D$16, 4,FALSE), IFERROR(VLOOKUP($A243,'Exetel ExDa'!$C$2:$N$14, 3,FALSE), IFERROR(VLOOKUP($A243,'Infinet ExDa'!$B$2:$E$14, 3,FALSE), "Not Found")))))))) -> ABB | E243: =IFERROR(VLOOKUP($A243,'AAPT ExDa'!$B$2:$U$99, 3,FALSE), IFERROR(VLOOKUP($A243,'ABB ExDa'!$A$2:$N$184, 5,FALSE), IFERROR(VLOOKUP($A243,'Vocus SIT ExDa'!$B$2:$J$173, 2,FALSE), IFERROR(VLOOKUP($A243,'Telstra ExDa'!$B$2:$K$310, 4,FALSE), IFERROR(VLOOKUP($A243,'Vocus RVC ExDa'!$C$2:$R$155, 8,FALSE), IFERROR(VLOOKUP($A243,'Fusion ExDa'!$B$2:$D$16, 4,FALSE), IFERROR(VLOOKUP($A243,'Exetel ExDa'!$C$2:$N$14, 5,FALSE), IFERROR(VLOOKUP($A243,'Infinet ExDa'!$B$2:$E$14, 3,FALSE), "Not Found")))))))) -> NBN 100/40 | F243: =IFERROR(VLOOKUP($A243,'AAPT ExDa'!$B$2:$U$99, 4,FALSE), IFERROR(VLOOKUP($A243,'ABB ExDa'!$A$2:$N$184, 6,FALSE), IFERROR(VLOOKUP($A243,'Vocus SIT ExDa'!$B$2:$J$173, 3,FALSE), IFERROR(VLOOKUP($A243,'Telstra ExDa'!$B$2:$K$310, 5,FALSE), IFERROR(VLOOKUP($A243,'Vocus RVC ExDa'!$C$2:$R$155, 9,FALSE), IFERROR(VLOOKUP($A243,'Fusion ExDa'!$B$2:$D$16, 0,FALSE), IFERROR(VLOOKUP($A243,'Exetel ExDa'!$C$2:$N$14, 6,FALSE), IFERROR(VLOOKUP($A243,'Infinet ExDa'!$B$2:$E$14, 0,FALSE), "Not Found")))))))) -> Fibre | G243: =IFERROR(VLOOKUP($A243,'AAPT ExDa'!$B$2:$U$99, 5,FALSE), IFERROR(VLOOKUP($A243,'ABB ExDa'!$A$2:$N$184, 8,FALSE), IFERROR(VLOOKUP($A243,'Vocus SIT ExDa'!$B$2:$J$173, 6,FALSE), IFERROR(VLOOKUP($A243,'Telstra ExDa'!$B$2:$K$310, 0,FALSE), IFERROR(VLOOKUP($A243,'Vocus RVC ExDa'!$C$2:$R$155, 15,FALSE), IFERROR(VLOOKUP($A243,'Fusion ExDa'!$B$2:$D$16, 0,FALSE), IFERROR(VLOOKUP($A243,'Exetel ExDa'!$C$2:$N$14, 7,FALSE), IFERROR(VLOOKUP($A243,'Infinet ExDa'!$B$2:$E$14, 0,FALSE), "Not Found")))))))) -> 157.211.4.130 | H243: =IFERROR(VLOOKUP($A243,'AAPT ExDa'!$B$2:$U$99, 6,FALSE), IFERROR(VLOOKUP($A243,'ABB ExDa'!$A$2:$N$184, 0,FALSE), IFERROR(VLOOKUP($A243,'Vocus SIT ExDa'!$B$2:$J$173, 0,FALSE), IFERROR(VLOOKUP($A243,'Telstra ExDa'!$B$2:$K$310, 0,FALSE), IFERROR(VLOOKUP($A243,'Vocus RVC ExDa'!$C$2:$R$155, 16,FALSE), IFERROR(VLOOKUP($A243,'Fusion ExDa'!$B$2:$D$16, 0,FALSE), IFERROR(VLOOKUP($A243,'Exetel ExDa'!$C$2:$N$14, 0,FALSE), IFERROR(VLOOKUP($A243,'Infinet ExDa'!$B$2:$E$14, 0,FALSE), "Not Found")))))))) -> Not Found | I243: =IFERROR(VLOOKUP($A243,'AAPT ExDa'!$B$2:$U$99, 0,FALSE), IFERROR(VLOOKUP($A243,'ABB ExDa'!$A$2:$N$184, 0,FALSE), IFERROR(VLOOKUP($A243,'Vocus SIT ExDa'!$B$2:$J$173, 0,FALSE), IFERROR(VLOOKUP($A243,'Telstra ExDa'!$B$2:$K$310, 0,FALSE), IFERROR(VLOOKUP($A243,'Vocus RVC ExDa'!$C$2:$R$155, 0,FALSE), IFERROR(VLOOKUP($A243,'Fusion ExDa'!$B$2:$D$16, 0,FALSE), IFERROR(VLOOKUP($A243,'Exetel ExDa'!$C$2:$N$14, 8,FALSE), IFERROR(VLOOKUP($A243,'Infinet ExDa'!$B$2:$E$14, 0,FALSE), "Not Found")))))))) -> Not Found | J243: =IFERROR(VLOOKUP($A243,'AAPT ExDa'!$B$2:$U$99, 7,FALSE), IFERROR(VLOOKUP($A243,'ABB ExDa'!$A$2:$N$184, 2,FALSE), IFERROR(VLOOKUP($A243,'Vocus SIT ExDa'!$B$2:$J$173, 0,FALSE), IFERROR(VLOOKUP($A243,'Telstra ExDa'!$B$2:$K$310, 7,FALSE), IFERROR(VLOOKUP($A243,'Vocus RVC ExDa'!$C$2:$R$155, 2,FALSE), IFERROR(VLOOKUP($A243,'Fusion ExDa'!$B$2:$D$16, 3,FALSE), IFERROR(VLOOKUP($A243,'Exetel ExDa'!$C$2:$N$14, 0,FALSE), IFERROR(VLOOKUP($A243,'Infinet ExDa'!$B$2:$E$14, 0,FALSE), "Not Found")))))))) -> 136 COOLAMON BVD, ELLENBROOK WA | K243: =IFERROR(VLOOKUP($A243,'AAPT ExDa'!$B$2:$U$99, 12,FALSE), IFERROR(VLOOKUP($A243,'ABB ExDa'!$A$2:$N$184, 0,FALSE), IFERROR(VLOOKUP($A243,'Vocus SIT ExDa'!$B$2:$J$173, 0,FALSE), IFERROR(VLOOKUP($A243,'Telstra ExDa'!$B$2:$K$310, 0,FALSE), IFERROR(VLOOKUP($A243,'Vocus RVC ExDa'!$C$2:$R$155, 0,FALSE), IFERROR(VLOOKUP($A243,'Fusion ExDa'!$B$2:$D$16, 0,FALSE), IFERROR(VLOOKUP($A243,'Exetel ExDa'!$C$2:$N$14, 12,FALSE), IFERROR(VLOOKUP($A243,'Infinet ExDa'!$B$2:$E$14, 0,FALSE), "Not Found")))))))) -> Not Found | L243: =IFERROR(VLOOKUP($A243,'AAPT ExDa'!$B$2:$U$99, 11,FALSE), IFERROR(VLOOKUP($A243,'ABB ExDa'!$A$2:$N$184, 9,FALSE), IFERROR(VLOOKUP($A243,'Vocus SIT ExDa'!$B$2:$J$173, 8,FALSE), IFERROR(VLOOKUP($A243,'Telstra ExDa'!$B$2:$K$310, 0,FALSE), IFERROR(VLOOKUP($A243,'Vocus RVC ExDa'!$C$2:$R$155, 0,FALSE), IFERROR(VLOOKUP($A243,'Fusion ExDa'!$B$2:$D$16, 0,FALSE), IFERROR(VLOOKUP($A243,'Exetel ExDa'!$C$2:$N$14, 9,FALSE), IFERROR(VLOOKUP($A243,'Infinet ExDa'!$B$2:$E$14, 0,FALSE), "Not Found")))))))) -> 23 Oct 2025 | M243: =IFERROR(VLOOKUP($A243,'AAPT ExDa'!$B$2:$U$99, 0,FALSE), IFERROR(VLOOKUP($A243,'ABB ExDa'!$A$2:$N$184, 0,FALSE), IFERROR(VLOOKUP($A243,'Vocus SIT ExDa'!$B$2:$J$173, 0,FALSE), IFERROR(VLOOKUP($A243,'Telstra ExDa'!$B$2:$K$310, 0,FALSE), IFERROR(VLOOKUP($A243,'Vocus RVC ExDa'!$C$2:$R$155, 0,FALSE), IFERROR(VLOOKUP($A243,'Fusion ExDa'!$B$2:$D$16, 0,FALSE), IFERROR(VLOOKUP($A243,'Exetel ExDa'!$C$2:$N$14, 11,FALSE), IFERROR(VLOOKUP($A243,'Infinet ExDa'!$B$2:$E$14, 0,FALSE), "Not Found")))))))) -> Not Found | N243: =IFERROR(VLOOKUP($A243,'AAPT ExDa'!$B$2:$U$99, 0,FALSE), IFERROR(VLOOKUP($A243,'ABB ExDa'!$A$2:$N$184, 13,FALSE), IFERROR(VLOOKUP($A243,'Vocus SIT ExDa'!$B$2:$J$173, 0,FALSE), IFERROR(VLOOKUP($A243,'Telstra ExDa'!$B$2:$K$310, 0,FALSE), IFERROR(VLOOKUP($A243,'Vocus RVC ExDa'!$C$2:$R$155, 0,FALSE), IFERROR(VLOOKUP($A243,'Fusion ExDa'!$B$2:$D$16, 0,FALSE), IFERROR(VLOOKUP($A243,'Exetel ExDa'!$C$2:$N$14, 0,FALSE), IFERROR(VLOOKUP($A243,'Infinet ExDa'!$B$2:$E$14, 0,FALSE), "Not Found")))))))) -> 0
A244: The Yiros Shop Molendinar | B244: =IFERROR(VLOOKUP(A244,'Exetel ExDa'!$C$2:$N$14,4,FALSE),"No Data") -> No Data | C244: =IFERROR(VLOOKUP(A244,'AAPT ExDa'!$B$2:$U$99, 2,FALSE), IFERROR(VLOOKUP(A244,'ABB ExDa'!$A$2:$N$184, 2,FALSE), IFERROR(VLOOKUP(A244,'Vocus SIT ExDa'!$B$2:$J$173, 7,FALSE), IFERROR(VLOOKUP(A244,'Telstra ExDa'!$B$2:$K$310, 2,FALSE), IFERROR(VLOOKUP(A244,'Vocus RVC ExDa'!$C$2:$R$155, 3,FALSE), IFERROR(VLOOKUP(A244,'Fusion ExDa'!$B$2:$D$16, 2,FALSE), IFERROR(VLOOKUP(A244,'Exetel ExDa'!$C$2:$N$14, 2,FALSE), IFERROR(VLOOKUP(A244,'Infinet ExDa'!$B$2:$E$14, 2,FALSE), "Not Found")))))))) -> SHOP FAST FOOD, 383 SOUTHPORT NERANG RD, MOLENDINAR QLD | D244: =IFERROR(VLOOKUP($A244,'AAPT ExDa'!$B$2:$U$99, 15,FALSE), IFERROR(VLOOKUP($A244,'ABB ExDa'!$A$2:$N$184, 4,FALSE), IFERROR(VLOOKUP($A244,'Vocus SIT ExDa'!$B$2:$J$173, 5,FALSE), IFERROR(VLOOKUP($A244,'Telstra ExDa'!$B$2:$K$310, 8,FALSE), IFERROR(VLOOKUP($A244,'Vocus RVC ExDa'!$C$2:$R$155, 6,FALSE), IFERROR(VLOOKUP($A244,'Fusion ExDa'!$B$2:$D$16, 4,FALSE), IFERROR(VLOOKUP($A244,'Exetel ExDa'!$C$2:$N$14, 3,FALSE), IFERROR(VLOOKUP($A244,'Infinet ExDa'!$B$2:$E$14, 3,FALSE), "Not Found")))))))) -> ABB | E244: =IFERROR(VLOOKUP($A244,'AAPT ExDa'!$B$2:$U$99, 3,FALSE), IFERROR(VLOOKUP($A244,'ABB ExDa'!$A$2:$N$184, 5,FALSE), IFERROR(VLOOKUP($A244,'Vocus SIT ExDa'!$B$2:$J$173, 2,FALSE), IFERROR(VLOOKUP($A244,'Telstra ExDa'!$B$2:$K$310, 4,FALSE), IFERROR(VLOOKUP($A244,'Vocus RVC ExDa'!$C$2:$R$155, 8,FALSE), IFERROR(VLOOKUP($A244,'Fusion ExDa'!$B$2:$D$16, 4,FALSE), IFERROR(VLOOKUP($A244,'Exetel ExDa'!$C$2:$N$14, 5,FALSE), IFERROR(VLOOKUP($A244,'Infinet ExDa'!$B$2:$E$14, 3,FALSE), "Not Found")))))))) -> NBN 100/40 | F244: =IFERROR(VLOOKUP($A244,'AAPT ExDa'!$B$2:$U$99, 4,FALSE), IFERROR(VLOOKUP($A244,'ABB ExDa'!$A$2:$N$184, 6,FALSE), IFERROR(VLOOKUP($A244,'Vocus SIT ExDa'!$B$2:$J$173, 3,FALSE), IFERROR(VLOOKUP($A244,'Telstra ExDa'!$B$2:$K$310, 5,FALSE), IFERROR(VLOOKUP($A244,'Vocus RVC ExDa'!$C$2:$R$155, 9,FALSE), IFERROR(VLOOKUP($A244,'Fusion ExDa'!$B$2:$D$16, 0,FALSE), IFERROR(VLOOKUP($A244,'Exetel ExDa'!$C$2:$N$14, 6,FALSE), IFERROR(VLOOKUP($A244,'Infinet ExDa'!$B$2:$E$14, 0,FALSE), "Not Found")))))))) -> Fibre | G244: =IFERROR(VLOOKUP($A244,'AAPT ExDa'!$B$2:$U$99, 5,FALSE), IFERROR(VLOOKUP($A244,'ABB ExDa'!$A$2:$N$184, 8,FALSE), IFERROR(VLOOKUP($A244,'Vocus SIT ExDa'!$B$2:$J$173, 6,FALSE), IFERROR(VLOOKUP($A244,'Telstra ExDa'!$B$2:$K$310, 0,FALSE), IFERROR(VLOOKUP($A244,'Vocus RVC ExDa'!$C$2:$R$155, 15,FALSE), IFERROR(VLOOKUP($A244,'Fusion ExDa'!$B$2:$D$16, 0,FALSE), IFERROR(VLOOKUP($A244,'Exetel ExDa'!$C$2:$N$14, 7,FALSE), IFERROR(VLOOKUP($A244,'Infinet ExDa'!$B$2:$E$14, 0,FALSE), "Not Found")))))))) -> 157.211.2.255 | H244: =IFERROR(VLOOKUP($A244,'AAPT ExDa'!$B$2:$U$99, 6,FALSE), IFERROR(VLOOKUP($A244,'ABB ExDa'!$A$2:$N$184, 0,FALSE), IFERROR(VLOOKUP($A244,'Vocus SIT ExDa'!$B$2:$J$173, 0,FALSE), IFERROR(VLOOKUP($A244,'Telstra ExDa'!$B$2:$K$310, 0,FALSE), IFERROR(VLOOKUP($A244,'Vocus RVC ExDa'!$C$2:$R$155, 16,FALSE), IFERROR(VLOOKUP($A244,'Fusion ExDa'!$B$2:$D$16, 0,FALSE), IFERROR(VLOOKUP($A244,'Exetel ExDa'!$C$2:$N$14, 0,FALSE), IFERROR(VLOOKUP($A244,'Infinet ExDa'!$B$2:$E$14, 0,FALSE), "Not Found")))))))) -> Not Found | I244: =IFERROR(VLOOKUP($A244,'AAPT ExDa'!$B$2:$U$99, 0,FALSE), IFERROR(VLOOKUP($A244,'ABB ExDa'!$A$2:$N$184, 0,FALSE), IFERROR(VLOOKUP($A244,'Vocus SIT ExDa'!$B$2:$J$173, 0,FALSE), IFERROR(VLOOKUP($A244,'Telstra ExDa'!$B$2:$K$310, 0,FALSE), IFERROR(VLOOKUP($A244,'Vocus RVC ExDa'!$C$2:$R$155, 0,FALSE), IFERROR(VLOOKUP($A244,'Fusion ExDa'!$B$2:$D$16, 0,FALSE), IFERROR(VLOOKUP($A244,'Exetel ExDa'!$C$2:$N$14, 8,FALSE), IFERROR(VLOOKUP($A244,'Infinet ExDa'!$B$2:$E$14, 0,FALSE), "Not Found")))))))) -> Not Found | J244: =IFERROR(VLOOKUP($A244,'AAPT ExDa'!$B$2:$U$99, 7,FALSE), IFERROR(VLOOKUP($A244,'ABB ExDa'!$A$2:$N$184, 2,FALSE), IFERROR(VLOOKUP($A244,'Vocus SIT ExDa'!$B$2:$J$173, 0,FALSE), IFERROR(VLOOKUP($A244,'Telstra ExDa'!$B$2:$K$310, 7,FALSE), IFERROR(VLOOKUP($A244,'Vocus RVC ExDa'!$C$2:$R$155, 2,FALSE), IFERROR(VLOOKUP($A244,'Fusion ExDa'!$B$2:$D$16, 3,FALSE), IFERROR(VLOOKUP($A244,'Exetel ExDa'!$C$2:$N$14, 0,FALSE), IFERROR(VLOOKUP($A244,'Infinet ExDa'!$B$2:$E$14, 0,FALSE), "Not Found")))))))) -> SHOP FAST FOOD, 383 SOUTHPORT NERANG RD, MOLENDINAR QLD | K244: =IFERROR(VLOOKUP($A244,'AAPT ExDa'!$B$2:$U$99, 12,FALSE), IFERROR(VLOOKUP($A244,'ABB ExDa'!$A$2:$N$184, 0,FALSE), IFERROR(VLOOKUP($A244,'Vocus SIT ExDa'!$B$2:$J$173, 0,FALSE), IFERROR(VLOOKUP($A244,'Telstra ExDa'!$B$2:$K$310, 0,FALSE), IFERROR(VLOOKUP($A244,'Vocus RVC ExDa'!$C$2:$R$155, 0,FALSE), IFERROR(VLOOKUP($A244,'Fusion ExDa'!$B$2:$D$16, 0,FALSE), IFERROR(VLOOKUP($A244,'Exetel ExDa'!$C$2:$N$14, 12,FALSE), IFERROR(VLOOKUP($A244,'Infinet ExDa'!$B$2:$E$14, 0,FALSE), "Not Found")))))))) -> Not Found | L244: =IFERROR(VLOOKUP($A244,'AAPT ExDa'!$B$2:$U$99, 11,FALSE), IFERROR(VLOOKUP($A244,'ABB ExDa'!$A$2:$N$184, 9,FALSE), IFERROR(VLOOKUP($A244,'Vocus SIT ExDa'!$B$2:$J$173, 8,FALSE), IFERROR(VLOOKUP($A244,'Telstra ExDa'!$B$2:$K$310, 0,FALSE), IFERROR(VLOOKUP($A244,'Vocus RVC ExDa'!$C$2:$R$155, 0,FALSE), IFERROR(VLOOKUP($A244,'Fusion ExDa'!$B$2:$D$16, 0,FALSE), IFERROR(VLOOKUP($A244,'Exetel ExDa'!$C$2:$N$14, 9,FALSE), IFERROR(VLOOKUP($A244,'Infinet ExDa'!$B$2:$E$14, 0,FALSE), "Not Found")))))))) -> 27 Oct 2025 | M244: =IFERROR(VLOOKUP($A244,'AAPT ExDa'!$B$2:$U$99, 0,FALSE), IFERROR(VLOOKUP($A244,'ABB ExDa'!$A$2:$N$184, 0,FALSE), IFERROR(VLOOKUP($A244,'Vocus SIT ExDa'!$B$2:$J$173, 0,FALSE), IFERROR(VLOOKUP($A244,'Telstra ExDa'!$B$2:$K$310, 0,FALSE), IFERROR(VLOOKUP($A244,'Vocus RVC ExDa'!$C$2:$R$155, 0,FALSE), IFERROR(VLOOKUP($A244,'Fusion ExDa'!$B$2:$D$16, 0,FALSE), IFERROR(VLOOKUP($A244,'Exetel ExDa'!$C$2:$N$14, 11,FALSE), IFERROR(VLOOKUP($A244,'Infinet ExDa'!$B$2:$E$14, 0,FALSE), "Not Found")))))))) -> Not Found | N244: =IFERROR(VLOOKUP($A244,'AAPT ExDa'!$B$2:$U$99, 0,FALSE), IFERROR(VLOOKUP($A244,'ABB ExDa'!$A$2:$N$184, 13,FALSE), IFERROR(VLOOKUP($A244,'Vocus SIT ExDa'!$B$2:$J$173, 0,FALSE), IFERROR(VLOOKUP($A244,'Telstra ExDa'!$B$2:$K$310, 0,FALSE), IFERROR(VLOOKUP($A244,'Vocus RVC ExDa'!$C$2:$R$155, 0,FALSE), IFERROR(VLOOKUP($A244,'Fusion ExDa'!$B$2:$D$16, 0,FALSE), IFERROR(VLOOKUP($A244,'Exetel ExDa'!$C$2:$N$14, 0,FALSE), IFERROR(VLOOKUP($A244,'Infinet ExDa'!$B$2:$E$14, 0,FALSE), "Not Found")))))))) -> Onebill
A245: Zambrero Brabham | B245: =IFERROR(VLOOKUP(A245,'Exetel ExDa'!$C$2:$N$14,4,FALSE),"No Data") -> No Data | C245: =IFERROR(VLOOKUP(A245,'AAPT ExDa'!$B$2:$U$99, 2,FALSE), IFERROR(VLOOKUP(A245,'ABB ExDa'!$A$2:$N$184, 2,FALSE), IFERROR(VLOOKUP(A245,'Vocus SIT ExDa'!$B$2:$J$173, 7,FALSE), IFERROR(VLOOKUP(A245,'Telstra ExDa'!$B$2:$K$310, 2,FALSE), IFERROR(VLOOKUP(A245,'Vocus RVC ExDa'!$C$2:$R$155, 3,FALSE), IFERROR(VLOOKUP(A245,'Fusion ExDa'!$B$2:$D$16, 2,FALSE), IFERROR(VLOOKUP(A245,'Exetel ExDa'!$C$2:$N$14, 2,FALSE), IFERROR(VLOOKUP(A245,'Infinet ExDa'!$B$2:$E$14, 2,FALSE), "Not Found")))))))) -> TNCY 8, 100 EVERGLADES AV, BRABHAM WA | D245: =IFERROR(VLOOKUP($A245,'AAPT ExDa'!$B$2:$U$99, 15,FALSE), IFERROR(VLOOKUP($A245,'ABB ExDa'!$A$2:$N$184, 4,FALSE), IFERROR(VLOOKUP($A245,'Vocus SIT ExDa'!$B$2:$J$173, 5,FALSE), IFERROR(VLOOKUP($A245,'Telstra ExDa'!$B$2:$K$310, 8,FALSE), IFERROR(VLOOKUP($A245,'Vocus RVC ExDa'!$C$2:$R$155, 6,FALSE), IFERROR(VLOOKUP($A245,'Fusion ExDa'!$B$2:$D$16, 4,FALSE), IFERROR(VLOOKUP($A245,'Exetel ExDa'!$C$2:$N$14, 3,FALSE), IFERROR(VLOOKUP($A245,'Infinet ExDa'!$B$2:$E$14, 3,FALSE), "Not Found")))))))) -> ABB | E245: =IFERROR(VLOOKUP($A245,'AAPT ExDa'!$B$2:$U$99, 3,FALSE), IFERROR(VLOOKUP($A245,'ABB ExDa'!$A$2:$N$184, 5,FALSE), IFERROR(VLOOKUP($A245,'Vocus SIT ExDa'!$B$2:$J$173, 2,FALSE), IFERROR(VLOOKUP($A245,'Telstra ExDa'!$B$2:$K$310, 4,FALSE), IFERROR(VLOOKUP($A245,'Vocus RVC ExDa'!$C$2:$R$155, 8,FALSE), IFERROR(VLOOKUP($A245,'Fusion ExDa'!$B$2:$D$16, 4,FALSE), IFERROR(VLOOKUP($A245,'Exetel ExDa'!$C$2:$N$14, 5,FALSE), IFERROR(VLOOKUP($A245,'Infinet ExDa'!$B$2:$E$14, 3,FALSE), "Not Found")))))))) -> NBN 25/10 | F245: =IFERROR(VLOOKUP($A245,'AAPT ExDa'!$B$2:$U$99, 4,FALSE), IFERROR(VLOOKUP($A245,'ABB ExDa'!$A$2:$N$184, 6,FALSE), IFERROR(VLOOKUP($A245,'Vocus SIT ExDa'!$B$2:$J$173, 3,FALSE), IFERROR(VLOOKUP($A245,'Telstra ExDa'!$B$2:$K$310, 5,FALSE), IFERROR(VLOOKUP($A245,'Vocus RVC ExDa'!$C$2:$R$155, 9,FALSE), IFERROR(VLOOKUP($A245,'Fusion ExDa'!$B$2:$D$16, 0,FALSE), IFERROR(VLOOKUP($A245,'Exetel ExDa'!$C$2:$N$14, 6,FALSE), IFERROR(VLOOKUP($A245,'Infinet ExDa'!$B$2:$E$14, 0,FALSE), "Not Found")))))))) -> Fibre | G245: =IFERROR(VLOOKUP($A245,'AAPT ExDa'!$B$2:$U$99, 5,FALSE), IFERROR(VLOOKUP($A245,'ABB ExDa'!$A$2:$N$184, 8,FALSE), IFERROR(VLOOKUP($A245,'Vocus SIT ExDa'!$B$2:$J$173, 6,FALSE), IFERROR(VLOOKUP($A245,'Telstra ExDa'!$B$2:$K$310, 0,FALSE), IFERROR(VLOOKUP($A245,'Vocus RVC ExDa'!$C$2:$R$155, 15,FALSE), IFERROR(VLOOKUP($A245,'Fusion ExDa'!$B$2:$D$16, 0,FALSE), IFERROR(VLOOKUP($A245,'Exetel ExDa'!$C$2:$N$14, 7,FALSE), IFERROR(VLOOKUP($A245,'Infinet ExDa'!$B$2:$E$14, 0,FALSE), "Not Found")))))))) -> 144.6.136.50 | H245: =IFERROR(VLOOKUP($A245,'AAPT ExDa'!$B$2:$U$99, 6,FALSE), IFERROR(VLOOKUP($A245,'ABB ExDa'!$A$2:$N$184, 0,FALSE), IFERROR(VLOOKUP($A245,'Vocus SIT ExDa'!$B$2:$J$173, 0,FALSE), IFERROR(VLOOKUP($A245,'Telstra ExDa'!$B$2:$K$310, 0,FALSE), IFERROR(VLOOKUP($A245,'Vocus RVC ExDa'!$C$2:$R$155, 16,FALSE), IFERROR(VLOOKUP($A245,'Fusion ExDa'!$B$2:$D$16, 0,FALSE), IFERROR(VLOOKUP($A245,'Exetel ExDa'!$C$2:$N$14, 0,FALSE), IFERROR(VLOOKUP($A245,'Infinet ExDa'!$B$2:$E$14, 0,FALSE), "Not Found")))))))) -> Not Found | I245: =IFERROR(VLOOKUP($A245,'AAPT ExDa'!$B$2:$U$99, 0,FALSE), IFERROR(VLOOKUP($A245,'ABB ExDa'!$A$2:$N$184, 0,FALSE), IFERROR(VLOOKUP($A245,'Vocus SIT ExDa'!$B$2:$J$173, 0,FALSE), IFERROR(VLOOKUP($A245,'Telstra ExDa'!$B$2:$K$310, 0,FALSE), IFERROR(VLOOKUP($A245,'Vocus RVC ExDa'!$C$2:$R$155, 0,FALSE), IFERROR(VLOOKUP($A245,'Fusion ExDa'!$B$2:$D$16, 0,FALSE), IFERROR(VLOOKUP($A245,'Exetel ExDa'!$C$2:$N$14, 8,FALSE), IFERROR(VLOOKUP($A245,'Infinet ExDa'!$B$2:$E$14, 0,FALSE), "Not Found")))))))) -> Not Found | J245: =IFERROR(VLOOKUP($A245,'AAPT ExDa'!$B$2:$U$99, 7,FALSE), IFERROR(VLOOKUP($A245,'ABB ExDa'!$A$2:$N$184, 2,FALSE), IFERROR(VLOOKUP($A245,'Vocus SIT ExDa'!$B$2:$J$173, 0,FALSE), IFERROR(VLOOKUP($A245,'Telstra ExDa'!$B$2:$K$310, 7,FALSE), IFERROR(VLOOKUP($A245,'Vocus RVC ExDa'!$C$2:$R$155, 2,FALSE), IFERROR(VLOOKUP($A245,'Fusion ExDa'!$B$2:$D$16, 3,FALSE), IFERROR(VLOOKUP($A245,'Exetel ExDa'!$C$2:$N$14, 0,FALSE), IFERROR(VLOOKUP($A245,'Infinet ExDa'!$B$2:$E$14, 0,FALSE), "Not Found")))))))) -> TNCY 8, 100 EVERGLADES AV, BRABHAM WA | K245: =IFERROR(VLOOKUP($A245,'AAPT ExDa'!$B$2:$U$99, 12,FALSE), IFERROR(VLOOKUP($A245,'ABB ExDa'!$A$2:$N$184, 0,FALSE), IFERROR(VLOOKUP($A245,'Vocus SIT ExDa'!$B$2:$J$173, 0,FALSE), IFERROR(VLOOKUP($A245,'Telstra ExDa'!$B$2:$K$310, 0,FALSE), IFERROR(VLOOKUP($A245,'Vocus RVC ExDa'!$C$2:$R$155, 0,FALSE), IFERROR(VLOOKUP($A245,'Fusion ExDa'!$B$2:$D$16, 0,FALSE), IFERROR(VLOOKUP($A245,'Exetel ExDa'!$C$2:$N$14, 12,FALSE), IFERROR(VLOOKUP($A245,'Infinet ExDa'!$B$2:$E$14, 0,FALSE), "Not Found")))))))) -> Not Found | L245: =IFERROR(VLOOKUP($A245,'AAPT ExDa'!$B$2:$U$99, 11,FALSE), IFERROR(VLOOKUP($A245,'ABB ExDa'!$A$2:$N$184, 9,FALSE), IFERROR(VLOOKUP($A245,'Vocus SIT ExDa'!$B$2:$J$173, 8,FALSE), IFERROR(VLOOKUP($A245,'Telstra ExDa'!$B$2:$K$310, 0,FALSE), IFERROR(VLOOKUP($A245,'Vocus RVC ExDa'!$C$2:$R$155, 0,FALSE), IFERROR(VLOOKUP($A245,'Fusion ExDa'!$B$2:$D$16, 0,FALSE), IFERROR(VLOOKUP($A245,'Exetel ExDa'!$C$2:$N$14, 9,FALSE), IFERROR(VLOOKUP($A245,'Infinet ExDa'!$B$2:$E$14, 0,FALSE), "Not Found")))))))) -> 28 Oct 2025 | M245: =IFERROR(VLOOKUP($A245,'AAPT ExDa'!$B$2:$U$99, 0,FALSE), IFERROR(VLOOKUP($A245,'ABB ExDa'!$A$2:$N$184, 0,FALSE), IFERROR(VLOOKUP($A245,'Vocus SIT ExDa'!$B$2:$J$173, 0,FALSE), IFERROR(VLOOKUP($A245,'Telstra ExDa'!$B$2:$K$310, 0,FALSE), IFERROR(VLOOKUP($A245,'Vocus RVC ExDa'!$C$2:$R$155, 0,FALSE), IFERROR(VLOOKUP($A245,'Fusion ExDa'!$B$2:$D$16, 0,FALSE), IFERROR(VLOOKUP($A245,'Exetel ExDa'!$C$2:$N$14, 11,FALSE), IFERROR(VLOOKUP($A245,'Infinet ExDa'!$B$2:$E$14, 0,FALSE), "Not Found")))))))) -> Not Found | N245: =IFERROR(VLOOKUP($A245,'AAPT ExDa'!$B$2:$U$99, 0,FALSE), IFERROR(VLOOKUP($A245,'ABB ExDa'!$A$2:$N$184, 13,FALSE), IFERROR(VLOOKUP($A245,'Vocus SIT ExDa'!$B$2:$J$173, 0,FALSE), IFERROR(VLOOKUP($A245,'Telstra ExDa'!$B$2:$K$310, 0,FALSE), IFERROR(VLOOKUP($A245,'Vocus RVC ExDa'!$C$2:$R$155, 0,FALSE), IFERROR(VLOOKUP($A245,'Fusion ExDa'!$B$2:$D$16, 0,FALSE), IFERROR(VLOOKUP($A245,'Exetel ExDa'!$C$2:$N$14, 0,FALSE), IFERROR(VLOOKUP($A245,'Infinet ExDa'!$B$2:$E$14, 0,FALSE), "Not Found")))))))) -> Onebill
A246: Sparrow Early Learning Alkimos | B246: =IFERROR(VLOOKUP(A246,'Exetel ExDa'!$C$2:$N$14,4,FALSE),"No Data") -> No Data | C246: =IFERROR(VLOOKUP(A246,'AAPT ExDa'!$B$2:$U$99, 2,FALSE), IFERROR(VLOOKUP(A246,'ABB ExDa'!$A$2:$N$184, 2,FALSE), IFERROR(VLOOKUP(A246,'Vocus SIT ExDa'!$B$2:$J$173, 7,FALSE), IFERROR(VLOOKUP(A246,'Telstra ExDa'!$B$2:$K$310, 2,FALSE), IFERROR(VLOOKUP(A246,'Vocus RVC ExDa'!$C$2:$R$155, 3,FALSE), IFERROR(VLOOKUP(A246,'Fusion ExDa'!$B$2:$D$16, 2,FALSE), IFERROR(VLOOKUP(A246,'Exetel ExDa'!$C$2:$N$14, 2,FALSE), IFERROR(VLOOKUP(A246,'Infinet ExDa'!$B$2:$E$14, 2,FALSE), "Not Found")))))))) -> Unit 3, 3 BULWARK AVENUE, ALKIMOS WA | D246: =IFERROR(VLOOKUP($A246,'AAPT ExDa'!$B$2:$U$99, 15,FALSE), IFERROR(VLOOKUP($A246,'ABB ExDa'!$A$2:$N$184, 4,FALSE), IFERROR(VLOOKUP($A246,'Vocus SIT ExDa'!$B$2:$J$173, 5,FALSE), IFERROR(VLOOKUP($A246,'Telstra ExDa'!$B$2:$K$310, 8,FALSE), IFERROR(VLOOKUP($A246,'Vocus RVC ExDa'!$C$2:$R$155, 6,FALSE), IFERROR(VLOOKUP($A246,'Fusion ExDa'!$B$2:$D$16, 4,FALSE), IFERROR(VLOOKUP($A246,'Exetel ExDa'!$C$2:$N$14, 3,FALSE), IFERROR(VLOOKUP($A246,'Infinet ExDa'!$B$2:$E$14, 3,FALSE), "Not Found")))))))) -> ABB | E246: =IFERROR(VLOOKUP($A246,'AAPT ExDa'!$B$2:$U$99, 3,FALSE), IFERROR(VLOOKUP($A246,'ABB ExDa'!$A$2:$N$184, 5,FALSE), IFERROR(VLOOKUP($A246,'Vocus SIT ExDa'!$B$2:$J$173, 2,FALSE), IFERROR(VLOOKUP($A246,'Telstra ExDa'!$B$2:$K$310, 4,FALSE), IFERROR(VLOOKUP($A246,'Vocus RVC ExDa'!$C$2:$R$155, 8,FALSE), IFERROR(VLOOKUP($A246,'Fusion ExDa'!$B$2:$D$16, 4,FALSE), IFERROR(VLOOKUP($A246,'Exetel ExDa'!$C$2:$N$14, 5,FALSE), IFERROR(VLOOKUP($A246,'Infinet ExDa'!$B$2:$E$14, 3,FALSE), "Not Found")))))))) -> Opticomm 100/20 | F246: =IFERROR(VLOOKUP($A246,'AAPT ExDa'!$B$2:$U$99, 4,FALSE), IFERROR(VLOOKUP($A246,'ABB ExDa'!$A$2:$N$184, 6,FALSE), IFERROR(VLOOKUP($A246,'Vocus SIT ExDa'!$B$2:$J$173, 3,FALSE), IFERROR(VLOOKUP($A246,'Telstra ExDa'!$B$2:$K$310, 5,FALSE), IFERROR(VLOOKUP($A246,'Vocus RVC ExDa'!$C$2:$R$155, 9,FALSE), IFERROR(VLOOKUP($A246,'Fusion ExDa'!$B$2:$D$16, 0,FALSE), IFERROR(VLOOKUP($A246,'Exetel ExDa'!$C$2:$N$14, 6,FALSE), IFERROR(VLOOKUP($A246,'Infinet ExDa'!$B$2:$E$14, 0,FALSE), "Not Found")))))))) -> 159.196.138.252 | G246: =IFERROR(VLOOKUP($A246,'AAPT ExDa'!$B$2:$U$99, 5,FALSE), IFERROR(VLOOKUP($A246,'ABB ExDa'!$A$2:$N$184, 8,FALSE), IFERROR(VLOOKUP($A246,'Vocus SIT ExDa'!$B$2:$J$173, 6,FALSE), IFERROR(VLOOKUP($A246,'Telstra ExDa'!$B$2:$K$310, 0,FALSE), IFERROR(VLOOKUP($A246,'Vocus RVC ExDa'!$C$2:$R$155, 15,FALSE), IFERROR(VLOOKUP($A246,'Fusion ExDa'!$B$2:$D$16, 0,FALSE), IFERROR(VLOOKUP($A246,'Exetel ExDa'!$C$2:$N$14, 7,FALSE), IFERROR(VLOOKUP($A246,'Infinet ExDa'!$B$2:$E$14, 0,FALSE), "Not Found")))))))) -> 0 | H246: =IFERROR(VLOOKUP($A246,'AAPT ExDa'!$B$2:$U$99, 6,FALSE), IFERROR(VLOOKUP($A246,'ABB ExDa'!$A$2:$N$184, 0,FALSE), IFERROR(VLOOKUP($A246,'Vocus SIT ExDa'!$B$2:$J$173, 0,FALSE), IFERROR(VLOOKUP($A246,'Telstra ExDa'!$B$2:$K$310, 0,FALSE), IFERROR(VLOOKUP($A246,'Vocus RVC ExDa'!$C$2:$R$155, 16,FALSE), IFERROR(VLOOKUP($A246,'Fusion ExDa'!$B$2:$D$16, 0,FALSE), IFERROR(VLOOKUP($A246,'Exetel ExDa'!$C$2:$N$14, 0,FALSE), IFERROR(VLOOKUP($A246,'Infinet ExDa'!$B$2:$E$14, 0,FALSE), "Not Found")))))))) -> Not Found | I246: =IFERROR(VLOOKUP($A246,'AAPT ExDa'!$B$2:$U$99, 0,FALSE), IFERROR(VLOOKUP($A246,'ABB ExDa'!$A$2:$N$184, 0,FALSE), IFERROR(VLOOKUP($A246,'Vocus SIT ExDa'!$B$2:$J$173, 0,FALSE), IFERROR(VLOOKUP($A246,'Telstra ExDa'!$B$2:$K$310, 0,FALSE), IFERROR(VLOOKUP($A246,'Vocus RVC ExDa'!$C$2:$R$155, 0,FALSE), IFERROR(VLOOKUP($A246,'Fusion ExDa'!$B$2:$D$16, 0,FALSE), IFERROR(VLOOKUP($A246,'Exetel ExDa'!$C$2:$N$14, 8,FALSE), IFERROR(VLOOKUP($A246,'Infinet ExDa'!$B$2:$E$14, 0,FALSE), "Not Found")))))))) -> Not Found | J246: =IFERROR(VLOOKUP($A246,'AAPT ExDa'!$B$2:$U$99, 7,FALSE), IFERROR(VLOOKUP($A246,'ABB ExDa'!$A$2:$N$184, 2,FALSE), IFERROR(VLOOKUP($A246,'Vocus SIT ExDa'!$B$2:$J$173, 0,FALSE), IFERROR(VLOOKUP($A246,'Telstra ExDa'!$B$2:$K$310, 7,FALSE), IFERROR(VLOOKUP($A246,'Vocus RVC ExDa'!$C$2:$R$155, 2,FALSE), IFERROR(VLOOKUP($A246,'Fusion ExDa'!$B$2:$D$16, 3,FALSE), IFERROR(VLOOKUP($A246,'Exetel ExDa'!$C$2:$N$14, 0,FALSE), IFERROR(VLOOKUP($A246,'Infinet ExDa'!$B$2:$E$14, 0,FALSE), "Not Found")))))))) -> Unit 3, 3 BULWARK AVENUE, ALKIMOS WA | K246: =IFERROR(VLOOKUP($A246,'AAPT ExDa'!$B$2:$U$99, 12,FALSE), IFERROR(VLOOKUP($A246,'ABB ExDa'!$A$2:$N$184, 0,FALSE), IFERROR(VLOOKUP($A246,'Vocus SIT ExDa'!$B$2:$J$173, 0,FALSE), IFERROR(VLOOKUP($A246,'Telstra ExDa'!$B$2:$K$310, 0,FALSE), IFERROR(VLOOKUP($A246,'Vocus RVC ExDa'!$C$2:$R$155, 0,FALSE), IFERROR(VLOOKUP($A246,'Fusion ExDa'!$B$2:$D$16, 0,FALSE), IFERROR(VLOOKUP($A246,'Exetel ExDa'!$C$2:$N$14, 12,FALSE), IFERROR(VLOOKUP($A246,'Infinet ExDa'!$B$2:$E$14, 0,FALSE), "Not Found")))))))) -> Not Found | L246: =IFERROR(VLOOKUP($A246,'AAPT ExDa'!$B$2:$U$99, 11,FALSE), IFERROR(VLOOKUP($A246,'ABB ExDa'!$A$2:$N$184, 9,FALSE), IFERROR(VLOOKUP($A246,'Vocus SIT ExDa'!$B$2:$J$173, 8,FALSE), IFERROR(VLOOKUP($A246,'Telstra ExDa'!$B$2:$K$310, 0,FALSE), IFERROR(VLOOKUP($A246,'Vocus RVC ExDa'!$C$2:$R$155, 0,FALSE), IFERROR(VLOOKUP($A246,'Fusion ExDa'!$B$2:$D$16, 0,FALSE), IFERROR(VLOOKUP($A246,'Exetel ExDa'!$C$2:$N$14, 9,FALSE), IFERROR(VLOOKUP($A246,'Infinet ExDa'!$B$2:$E$14, 0,FALSE), "Not Found")))))))) -> 0 | M246: =IFERROR(VLOOKUP($A246,'AAPT ExDa'!$B$2:$U$99, 0,FALSE), IFERROR(VLOOKUP($A246,'ABB ExDa'!$A$2:$N$184, 0,FALSE), IFERROR(VLOOKUP($A246,'Vocus SIT ExDa'!$B$2:$J$173, 0,FALSE), IFERROR(VLOOKUP($A246,'Telstra ExDa'!$B$2:$K$310, 0,FALSE), IFERROR(VLOOKUP($A246,'Vocus RVC ExDa'!$C$2:$R$155, 0,FALSE), IFERROR(VLOOKUP($A246,'Fusion ExDa'!$B$2:$D$16, 0,FALSE), IFERROR(VLOOKUP($A246,'Exetel ExDa'!$C$2:$N$14, 11,FALSE), IFERROR(VLOOKUP($A246,'Infinet ExDa'!$B$2:$E$14, 0,FALSE), "Not Found")))))))) -> Not Found | N246: =IFERROR(VLOOKUP($A246,'AAPT ExDa'!$B$2:$U$99, 0,FALSE), IFERROR(VLOOKUP($A246,'ABB ExDa'!$A$2:$N$184, 13,FALSE), IFERROR(VLOOKUP($A246,'Vocus SIT ExDa'!$B$2:$J$173, 0,FALSE), IFERROR(VLOOKUP($A246,'Telstra ExDa'!$B$2:$K$310, 0,FALSE), IFERROR(VLOOKUP($A246,'Vocus RVC ExDa'!$C$2:$R$155, 0,FALSE), IFERROR(VLOOKUP($A246,'Fusion ExDa'!$B$2:$D$16, 0,FALSE), IFERROR(VLOOKUP($A246,'Exetel ExDa'!$C$2:$N$14, 0,FALSE), IFERROR(VLOOKUP($A246,'Infinet ExDa'!$B$2:$E$14, 0,FALSE), "Not Found")))))))) -> 0
A247: Healthy Dynamics | B247: =IFERROR(VLOOKUP(A247,'Exetel ExDa'!$C$2:$N$14,4,FALSE),"No Data") -> No Data | C247: =IFERROR(VLOOKUP(A247,'AAPT ExDa'!$B$2:$U$99, 2,FALSE), IFERROR(VLOOKUP(A247,'ABB ExDa'!$A$2:$N$184, 2,FALSE), IFERROR(VLOOKUP(A247,'Vocus SIT ExDa'!$B$2:$J$173, 7,FALSE), IFERROR(VLOOKUP(A247,'Telstra ExDa'!$B$2:$K$310, 2,FALSE), IFERROR(VLOOKUP(A247,'Vocus RVC ExDa'!$C$2:$R$155, 3,FALSE), IFERROR(VLOOKUP(A247,'Fusion ExDa'!$B$2:$D$16, 2,FALSE), IFERROR(VLOOKUP(A247,'Exetel ExDa'!$C$2:$N$14, 2,FALSE), IFERROR(VLOOKUP(A247,'Infinet ExDa'!$B$2:$E$14, 2,FALSE), "Not Found")))))))) -> Unit 1, 304 MONTAGUE ROAD, WEST END QLD | D247: =IFERROR(VLOOKUP($A247,'AAPT ExDa'!$B$2:$U$99, 15,FALSE), IFERROR(VLOOKUP($A247,'ABB ExDa'!$A$2:$N$184, 4,FALSE), IFERROR(VLOOKUP($A247,'Vocus SIT ExDa'!$B$2:$J$173, 5,FALSE), IFERROR(VLOOKUP($A247,'Telstra ExDa'!$B$2:$K$310, 8,FALSE), IFERROR(VLOOKUP($A247,'Vocus RVC ExDa'!$C$2:$R$155, 6,FALSE), IFERROR(VLOOKUP($A247,'Fusion ExDa'!$B$2:$D$16, 4,FALSE), IFERROR(VLOOKUP($A247,'Exetel ExDa'!$C$2:$N$14, 3,FALSE), IFERROR(VLOOKUP($A247,'Infinet ExDa'!$B$2:$E$14, 3,FALSE), "Not Found")))))))) -> ABB | E247: =IFERROR(VLOOKUP($A247,'AAPT ExDa'!$B$2:$U$99, 3,FALSE), IFERROR(VLOOKUP($A247,'ABB ExDa'!$A$2:$N$184, 5,FALSE), IFERROR(VLOOKUP($A247,'Vocus SIT ExDa'!$B$2:$J$173, 2,FALSE), IFERROR(VLOOKUP($A247,'Telstra ExDa'!$B$2:$K$310, 4,FALSE), IFERROR(VLOOKUP($A247,'Vocus RVC ExDa'!$C$2:$R$155, 8,FALSE), IFERROR(VLOOKUP($A247,'Fusion ExDa'!$B$2:$D$16, 4,FALSE), IFERROR(VLOOKUP($A247,'Exetel ExDa'!$C$2:$N$14, 5,FALSE), IFERROR(VLOOKUP($A247,'Infinet ExDa'!$B$2:$E$14, 3,FALSE), "Not Found")))))))) -> Opticomm 100/40 | F247: =IFERROR(VLOOKUP($A247,'AAPT ExDa'!$B$2:$U$99, 4,FALSE), IFERROR(VLOOKUP($A247,'ABB ExDa'!$A$2:$N$184, 6,FALSE), IFERROR(VLOOKUP($A247,'Vocus SIT ExDa'!$B$2:$J$173, 3,FALSE), IFERROR(VLOOKUP($A247,'Telstra ExDa'!$B$2:$K$310, 5,FALSE), IFERROR(VLOOKUP($A247,'Vocus RVC ExDa'!$C$2:$R$155, 9,FALSE), IFERROR(VLOOKUP($A247,'Fusion ExDa'!$B$2:$D$16, 0,FALSE), IFERROR(VLOOKUP($A247,'Exetel ExDa'!$C$2:$N$14, 6,FALSE), IFERROR(VLOOKUP($A247,'Infinet ExDa'!$B$2:$E$14, 0,FALSE), "Not Found")))))))) -> 167.179.181.116 | G247: =IFERROR(VLOOKUP($A247,'AAPT ExDa'!$B$2:$U$99, 5,FALSE), IFERROR(VLOOKUP($A247,'ABB ExDa'!$A$2:$N$184, 8,FALSE), IFERROR(VLOOKUP($A247,'Vocus SIT ExDa'!$B$2:$J$173, 6,FALSE), IFERROR(VLOOKUP($A247,'Telstra ExDa'!$B$2:$K$310, 0,FALSE), IFERROR(VLOOKUP($A247,'Vocus RVC ExDa'!$C$2:$R$155, 15,FALSE), IFERROR(VLOOKUP($A247,'Fusion ExDa'!$B$2:$D$16, 0,FALSE), IFERROR(VLOOKUP($A247,'Exetel ExDa'!$C$2:$N$14, 7,FALSE), IFERROR(VLOOKUP($A247,'Infinet ExDa'!$B$2:$E$14, 0,FALSE), "Not Found")))))))) -> 0 | H247: =IFERROR(VLOOKUP($A247,'AAPT ExDa'!$B$2:$U$99, 6,FALSE), IFERROR(VLOOKUP($A247,'ABB ExDa'!$A$2:$N$184, 0,FALSE), IFERROR(VLOOKUP($A247,'Vocus SIT ExDa'!$B$2:$J$173, 0,FALSE), IFERROR(VLOOKUP($A247,'Telstra ExDa'!$B$2:$K$310, 0,FALSE), IFERROR(VLOOKUP($A247,'Vocus RVC ExDa'!$C$2:$R$155, 16,FALSE), IFERROR(VLOOKUP($A247,'Fusion ExDa'!$B$2:$D$16, 0,FALSE), IFERROR(VLOOKUP($A247,'Exetel ExDa'!$C$2:$N$14, 0,FALSE), IFERROR(VLOOKUP($A247,'Infinet ExDa'!$B$2:$E$14, 0,FALSE), "Not Found")))))))) -> Not Found | I247: =IFERROR(VLOOKUP($A247,'AAPT ExDa'!$B$2:$U$99, 0,FALSE), IFERROR(VLOOKUP($A247,'ABB ExDa'!$A$2:$N$184, 0,FALSE), IFERROR(VLOOKUP($A247,'Vocus SIT ExDa'!$B$2:$J$173, 0,FALSE), IFERROR(VLOOKUP($A247,'Telstra ExDa'!$B$2:$K$310, 0,FALSE), IFERROR(VLOOKUP($A247,'Vocus RVC ExDa'!$C$2:$R$155, 0,FALSE), IFERROR(VLOOKUP($A247,'Fusion ExDa'!$B$2:$D$16, 0,FALSE), IFERROR(VLOOKUP($A247,'Exetel ExDa'!$C$2:$N$14, 8,FALSE), IFERROR(VLOOKUP($A247,'Infinet ExDa'!$B$2:$E$14, 0,FALSE), "Not Found")))))))) -> Not Found | J247: =IFERROR(VLOOKUP($A247,'AAPT ExDa'!$B$2:$U$99, 7,FALSE), IFERROR(VLOOKUP($A247,'ABB ExDa'!$A$2:$N$184, 2,FALSE), IFERROR(VLOOKUP($A247,'Vocus SIT ExDa'!$B$2:$J$173, 0,FALSE), IFERROR(VLOOKUP($A247,'Telstra ExDa'!$B$2:$K$310, 7,FALSE), IFERROR(VLOOKUP($A247,'Vocus RVC ExDa'!$C$2:$R$155, 2,FALSE), IFERROR(VLOOKUP($A247,'Fusion ExDa'!$B$2:$D$16, 3,FALSE), IFERROR(VLOOKUP($A247,'Exetel ExDa'!$C$2:$N$14, 0,FALSE), IFERROR(VLOOKUP($A247,'Infinet ExDa'!$B$2:$E$14, 0,FALSE), "Not Found")))))))) -> Unit 1, 304 MONTAGUE ROAD, WEST END QLD | K247: =IFERROR(VLOOKUP($A247,'AAPT ExDa'!$B$2:$U$99, 12,FALSE), IFERROR(VLOOKUP($A247,'ABB ExDa'!$A$2:$N$184, 0,FALSE), IFERROR(VLOOKUP($A247,'Vocus SIT ExDa'!$B$2:$J$173, 0,FALSE), IFERROR(VLOOKUP($A247,'Telstra ExDa'!$B$2:$K$310, 0,FALSE), IFERROR(VLOOKUP($A247,'Vocus RVC ExDa'!$C$2:$R$155, 0,FALSE), IFERROR(VLOOKUP($A247,'Fusion ExDa'!$B$2:$D$16, 0,FALSE), IFERROR(VLOOKUP($A247,'Exetel ExDa'!$C$2:$N$14, 12,FALSE), IFERROR(VLOOKUP($A247,'Infinet ExDa'!$B$2:$E$14, 0,FALSE), "Not Found")))))))) -> Not Found | L247: =IFERROR(VLOOKUP($A247,'AAPT ExDa'!$B$2:$U$99, 11,FALSE), IFERROR(VLOOKUP($A247,'ABB ExDa'!$A$2:$N$184, 9,FALSE), IFERROR(VLOOKUP($A247,'Vocus SIT ExDa'!$B$2:$J$173, 8,FALSE), IFERROR(VLOOKUP($A247,'Telstra ExDa'!$B$2:$K$310, 0,FALSE), IFERROR(VLOOKUP($A247,'Vocus RVC ExDa'!$C$2:$R$155, 0,FALSE), IFERROR(VLOOKUP($A247,'Fusion ExDa'!$B$2:$D$16, 0,FALSE), IFERROR(VLOOKUP($A247,'Exetel ExDa'!$C$2:$N$14, 9,FALSE), IFERROR(VLOOKUP($A247,'Infinet ExDa'!$B$2:$E$14, 0,FALSE), "Not Found")))))))) -> 0 | M247: =IFERROR(VLOOKUP($A247,'AAPT ExDa'!$B$2:$U$99, 0,FALSE), IFERROR(VLOOKUP($A247,'ABB ExDa'!$A$2:$N$184, 0,FALSE), IFERROR(VLOOKUP($A247,'Vocus SIT ExDa'!$B$2:$J$173, 0,FALSE), IFERROR(VLOOKUP($A247,'Telstra ExDa'!$B$2:$K$310, 0,FALSE), IFERROR(VLOOKUP($A247,'Vocus RVC ExDa'!$C$2:$R$155, 0,FALSE), IFERROR(VLOOKUP($A247,'Fusion ExDa'!$B$2:$D$16, 0,FALSE), IFERROR(VLOOKUP($A247,'Exetel ExDa'!$C$2:$N$14, 11,FALSE), IFERROR(VLOOKUP($A247,'Infinet ExDa'!$B$2:$E$14, 0,FALSE), "Not Found")))))))) -> Not Found | N247: =IFERROR(VLOOKUP($A247,'AAPT ExDa'!$B$2:$U$99, 0,FALSE), IFERROR(VLOOKUP($A247,'ABB ExDa'!$A$2:$N$184, 13,FALSE), IFERROR(VLOOKUP($A247,'Vocus SIT ExDa'!$B$2:$J$173, 0,FALSE), IFERROR(VLOOKUP($A247,'Telstra ExDa'!$B$2:$K$310, 0,FALSE), IFERROR(VLOOKUP($A247,'Vocus RVC ExDa'!$C$2:$R$155, 0,FALSE), IFERROR(VLOOKUP($A247,'Fusion ExDa'!$B$2:$D$16, 0,FALSE), IFERROR(VLOOKUP($A247,'Exetel ExDa'!$C$2:$N$14, 0,FALSE), IFERROR(VLOOKUP($A247,'Infinet ExDa'!$B$2:$E$14, 0,FALSE), "Not Found")))))))) -> 0
A248: Nodo Southbank | B248: =IFERROR(VLOOKUP(A248,'Exetel ExDa'!$C$2:$N$14,4,FALSE),"No Data") -> No Data | C248: =IFERROR(VLOOKUP(A248,'AAPT ExDa'!$B$2:$U$99, 2,FALSE), IFERROR(VLOOKUP(A248,'ABB ExDa'!$A$2:$N$184, 2,FALSE), IFERROR(VLOOKUP(A248,'Vocus SIT ExDa'!$B$2:$J$173, 7,FALSE), IFERROR(VLOOKUP(A248,'Telstra ExDa'!$B$2:$K$310, 2,FALSE), IFERROR(VLOOKUP(A248,'Vocus RVC ExDa'!$C$2:$R$155, 3,FALSE), IFERROR(VLOOKUP(A248,'Fusion ExDa'!$B$2:$D$16, 2,FALSE), IFERROR(VLOOKUP(A248,'Exetel ExDa'!$C$2:$N$14, 2,FALSE), IFERROR(VLOOKUP(A248,'Infinet ExDa'!$B$2:$E$14, 2,FALSE), "Not Found")))))))) -> Shop 65, 114 GREY STREET, SOUTH BRISBANE QLD | D248: =IFERROR(VLOOKUP($A248,'AAPT ExDa'!$B$2:$U$99, 15,FALSE), IFERROR(VLOOKUP($A248,'ABB ExDa'!$A$2:$N$184, 4,FALSE), IFERROR(VLOOKUP($A248,'Vocus SIT ExDa'!$B$2:$J$173, 5,FALSE), IFERROR(VLOOKUP($A248,'Telstra ExDa'!$B$2:$K$310, 8,FALSE), IFERROR(VLOOKUP($A248,'Vocus RVC ExDa'!$C$2:$R$155, 6,FALSE), IFERROR(VLOOKUP($A248,'Fusion ExDa'!$B$2:$D$16, 4,FALSE), IFERROR(VLOOKUP($A248,'Exetel ExDa'!$C$2:$N$14, 3,FALSE), IFERROR(VLOOKUP($A248,'Infinet ExDa'!$B$2:$E$14, 3,FALSE), "Not Found")))))))) -> ABB | E248: =IFERROR(VLOOKUP($A248,'AAPT ExDa'!$B$2:$U$99, 3,FALSE), IFERROR(VLOOKUP($A248,'ABB ExDa'!$A$2:$N$184, 5,FALSE), IFERROR(VLOOKUP($A248,'Vocus SIT ExDa'!$B$2:$J$173, 2,FALSE), IFERROR(VLOOKUP($A248,'Telstra ExDa'!$B$2:$K$310, 4,FALSE), IFERROR(VLOOKUP($A248,'Vocus RVC ExDa'!$C$2:$R$155, 8,FALSE), IFERROR(VLOOKUP($A248,'Fusion ExDa'!$B$2:$D$16, 4,FALSE), IFERROR(VLOOKUP($A248,'Exetel ExDa'!$C$2:$N$14, 5,FALSE), IFERROR(VLOOKUP($A248,'Infinet ExDa'!$B$2:$E$14, 3,FALSE), "Not Found")))))))) -> Opticomm 25/10 | F248: =IFERROR(VLOOKUP($A248,'AAPT ExDa'!$B$2:$U$99, 4,FALSE), IFERROR(VLOOKUP($A248,'ABB ExDa'!$A$2:$N$184, 6,FALSE), IFERROR(VLOOKUP($A248,'Vocus SIT ExDa'!$B$2:$J$173, 3,FALSE), IFERROR(VLOOKUP($A248,'Telstra ExDa'!$B$2:$K$310, 5,FALSE), IFERROR(VLOOKUP($A248,'Vocus RVC ExDa'!$C$2:$R$155, 9,FALSE), IFERROR(VLOOKUP($A248,'Fusion ExDa'!$B$2:$D$16, 0,FALSE), IFERROR(VLOOKUP($A248,'Exetel ExDa'!$C$2:$N$14, 6,FALSE), IFERROR(VLOOKUP($A248,'Infinet ExDa'!$B$2:$E$14, 0,FALSE), "Not Found")))))))) -> 167.179.183.221 | G248: =IFERROR(VLOOKUP($A248,'AAPT ExDa'!$B$2:$U$99, 5,FALSE), IFERROR(VLOOKUP($A248,'ABB ExDa'!$A$2:$N$184, 8,FALSE), IFERROR(VLOOKUP($A248,'Vocus SIT ExDa'!$B$2:$J$173, 6,FALSE), IFERROR(VLOOKUP($A248,'Telstra ExDa'!$B$2:$K$310, 0,FALSE), IFERROR(VLOOKUP($A248,'Vocus RVC ExDa'!$C$2:$R$155, 15,FALSE), IFERROR(VLOOKUP($A248,'Fusion ExDa'!$B$2:$D$16, 0,FALSE), IFERROR(VLOOKUP($A248,'Exetel ExDa'!$C$2:$N$14, 7,FALSE), IFERROR(VLOOKUP($A248,'Infinet ExDa'!$B$2:$E$14, 0,FALSE), "Not Found")))))))) -> no usage yet | H248: =IFERROR(VLOOKUP($A248,'AAPT ExDa'!$B$2:$U$99, 6,FALSE), IFERROR(VLOOKUP($A248,'ABB ExDa'!$A$2:$N$184, 0,FALSE), IFERROR(VLOOKUP($A248,'Vocus SIT ExDa'!$B$2:$J$173, 0,FALSE), IFERROR(VLOOKUP($A248,'Telstra ExDa'!$B$2:$K$310, 0,FALSE), IFERROR(VLOOKUP($A248,'Vocus RVC ExDa'!$C$2:$R$155, 16,FALSE), IFERROR(VLOOKUP($A248,'Fusion ExDa'!$B$2:$D$16, 0,FALSE), IFERROR(VLOOKUP($A248,'Exetel ExDa'!$C$2:$N$14, 0,FALSE), IFERROR(VLOOKUP($A248,'Infinet ExDa'!$B$2:$E$14, 0,FALSE), "Not Found")))))))) -> Not Found | I248: =IFERROR(VLOOKUP($A248,'AAPT ExDa'!$B$2:$U$99, 0,FALSE), IFERROR(VLOOKUP($A248,'ABB ExDa'!$A$2:$N$184, 0,FALSE), IFERROR(VLOOKUP($A248,'Vocus SIT ExDa'!$B$2:$J$173, 0,FALSE), IFERROR(VLOOKUP($A248,'Telstra ExDa'!$B$2:$K$310, 0,FALSE), IFERROR(VLOOKUP($A248,'Vocus RVC ExDa'!$C$2:$R$155, 0,FALSE), IFERROR(VLOOKUP($A248,'Fusion ExDa'!$B$2:$D$16, 0,FALSE), IFERROR(VLOOKUP($A248,'Exetel ExDa'!$C$2:$N$14, 8,FALSE), IFERROR(VLOOKUP($A248,'Infinet ExDa'!$B$2:$E$14, 0,FALSE), "Not Found")))))))) -> Not Found | J248: =IFERROR(VLOOKUP($A248,'AAPT ExDa'!$B$2:$U$99, 7,FALSE), IFERROR(VLOOKUP($A248,'ABB ExDa'!$A$2:$N$184, 2,FALSE), IFERROR(VLOOKUP($A248,'Vocus SIT ExDa'!$B$2:$J$173, 0,FALSE), IFERROR(VLOOKUP($A248,'Telstra ExDa'!$B$2:$K$310, 7,FALSE), IFERROR(VLOOKUP($A248,'Vocus RVC ExDa'!$C$2:$R$155, 2,FALSE), IFERROR(VLOOKUP($A248,'Fusion ExDa'!$B$2:$D$16, 3,FALSE), IFERROR(VLOOKUP($A248,'Exetel ExDa'!$C$2:$N$14, 0,FALSE), IFERROR(VLOOKUP($A248,'Infinet ExDa'!$B$2:$E$14, 0,FALSE), "Not Found")))))))) -> Shop 65, 114 GREY STREET, SOUTH BRISBANE QLD | K248: =IFERROR(VLOOKUP($A248,'AAPT ExDa'!$B$2:$U$99, 12,FALSE), IFERROR(VLOOKUP($A248,'ABB ExDa'!$A$2:$N$184, 0,FALSE), IFERROR(VLOOKUP($A248,'Vocus SIT ExDa'!$B$2:$J$173, 0,FALSE), IFERROR(VLOOKUP($A248,'Telstra ExDa'!$B$2:$K$310, 0,FALSE), IFERROR(VLOOKUP($A248,'Vocus RVC ExDa'!$C$2:$R$155, 0,FALSE), IFERROR(VLOOKUP($A248,'Fusion ExDa'!$B$2:$D$16, 0,FALSE), IFERROR(VLOOKUP($A248,'Exetel ExDa'!$C$2:$N$14, 12,FALSE), IFERROR(VLOOKUP($A248,'Infinet ExDa'!$B$2:$E$14, 0,FALSE), "Not Found")))))))) -> Not Found | L248: =IFERROR(VLOOKUP($A248,'AAPT ExDa'!$B$2:$U$99, 11,FALSE), IFERROR(VLOOKUP($A248,'ABB ExDa'!$A$2:$N$184, 9,FALSE), IFERROR(VLOOKUP($A248,'Vocus SIT ExDa'!$B$2:$J$173, 8,FALSE), IFERROR(VLOOKUP($A248,'Telstra ExDa'!$B$2:$K$310, 0,FALSE), IFERROR(VLOOKUP($A248,'Vocus RVC ExDa'!$C$2:$R$155, 0,FALSE), IFERROR(VLOOKUP($A248,'Fusion ExDa'!$B$2:$D$16, 0,FALSE), IFERROR(VLOOKUP($A248,'Exetel ExDa'!$C$2:$N$14, 9,FALSE), IFERROR(VLOOKUP($A248,'Infinet ExDa'!$B$2:$E$14, 0,FALSE), "Not Found")))))))) -> 0 | M248: =IFERROR(VLOOKUP($A248,'AAPT ExDa'!$B$2:$U$99, 0,FALSE), IFERROR(VLOOKUP($A248,'ABB ExDa'!$A$2:$N$184, 0,FALSE), IFERROR(VLOOKUP($A248,'Vocus SIT ExDa'!$B$2:$J$173, 0,FALSE), IFERROR(VLOOKUP($A248,'Telstra ExDa'!$B$2:$K$310, 0,FALSE), IFERROR(VLOOKUP($A248,'Vocus RVC ExDa'!$C$2:$R$155, 0,FALSE), IFERROR(VLOOKUP($A248,'Fusion ExDa'!$B$2:$D$16, 0,FALSE), IFERROR(VLOOKUP($A248,'Exetel ExDa'!$C$2:$N$14, 11,FALSE), IFERROR(VLOOKUP($A248,'Infinet ExDa'!$B$2:$E$14, 0,FALSE), "Not Found")))))))) -> Not Found | N248: =IFERROR(VLOOKUP($A248,'AAPT ExDa'!$B$2:$U$99, 0,FALSE), IFERROR(VLOOKUP($A248,'ABB ExDa'!$A$2:$N$184, 13,FALSE), IFERROR(VLOOKUP($A248,'Vocus SIT ExDa'!$B$2:$J$173, 0,FALSE), IFERROR(VLOOKUP($A248,'Telstra ExDa'!$B$2:$K$310, 0,FALSE), IFERROR(VLOOKUP($A248,'Vocus RVC ExDa'!$C$2:$R$155, 0,FALSE), IFERROR(VLOOKUP($A248,'Fusion ExDa'!$B$2:$D$16, 0,FALSE), IFERROR(VLOOKUP($A248,'Exetel ExDa'!$C$2:$N$14, 0,FALSE), IFERROR(VLOOKUP($A248,'Infinet ExDa'!$B$2:$E$14, 0,FALSE), "Not Found")))))))) -> Onebill
A249: Zambrero Mater | B249: =IFERROR(VLOOKUP(A249,'Exetel ExDa'!$C$2:$N$14,4,FALSE),"No Data") -> No Data | C249: =IFERROR(VLOOKUP(A249,'AAPT ExDa'!$B$2:$U$99, 2,FALSE), IFERROR(VLOOKUP(A249,'ABB ExDa'!$A$2:$N$184, 2,FALSE), IFERROR(VLOOKUP(A249,'Vocus SIT ExDa'!$B$2:$J$173, 7,FALSE), IFERROR(VLOOKUP(A249,'Telstra ExDa'!$B$2:$K$310, 2,FALSE), IFERROR(VLOOKUP(A249,'Vocus RVC ExDa'!$C$2:$R$155, 3,FALSE), IFERROR(VLOOKUP(A249,'Fusion ExDa'!$B$2:$D$16, 2,FALSE), IFERROR(VLOOKUP(A249,'Exetel ExDa'!$C$2:$N$14, 2,FALSE), IFERROR(VLOOKUP(A249,'Infinet ExDa'!$B$2:$E$14, 2,FALSE), "Not Found")))))))) -> Unit 126, 50 Marshall STREET, Burnett Heads QLD | D249: =IFERROR(VLOOKUP($A249,'AAPT ExDa'!$B$2:$U$99, 15,FALSE), IFERROR(VLOOKUP($A249,'ABB ExDa'!$A$2:$N$184, 4,FALSE), IFERROR(VLOOKUP($A249,'Vocus SIT ExDa'!$B$2:$J$173, 5,FALSE), IFERROR(VLOOKUP($A249,'Telstra ExDa'!$B$2:$K$310, 8,FALSE), IFERROR(VLOOKUP($A249,'Vocus RVC ExDa'!$C$2:$R$155, 6,FALSE), IFERROR(VLOOKUP($A249,'Fusion ExDa'!$B$2:$D$16, 4,FALSE), IFERROR(VLOOKUP($A249,'Exetel ExDa'!$C$2:$N$14, 3,FALSE), IFERROR(VLOOKUP($A249,'Infinet ExDa'!$B$2:$E$14, 3,FALSE), "Not Found")))))))) -> ABB | E249: =IFERROR(VLOOKUP($A249,'AAPT ExDa'!$B$2:$U$99, 3,FALSE), IFERROR(VLOOKUP($A249,'ABB ExDa'!$A$2:$N$184, 5,FALSE), IFERROR(VLOOKUP($A249,'Vocus SIT ExDa'!$B$2:$J$173, 2,FALSE), IFERROR(VLOOKUP($A249,'Telstra ExDa'!$B$2:$K$310, 4,FALSE), IFERROR(VLOOKUP($A249,'Vocus RVC ExDa'!$C$2:$R$155, 8,FALSE), IFERROR(VLOOKUP($A249,'Fusion ExDa'!$B$2:$D$16, 4,FALSE), IFERROR(VLOOKUP($A249,'Exetel ExDa'!$C$2:$N$14, 5,FALSE), IFERROR(VLOOKUP($A249,'Infinet ExDa'!$B$2:$E$14, 3,FALSE), "Not Found")))))))) -> Opticomm 50/20 | F249: =IFERROR(VLOOKUP($A249,'AAPT ExDa'!$B$2:$U$99, 4,FALSE), IFERROR(VLOOKUP($A249,'ABB ExDa'!$A$2:$N$184, 6,FALSE), IFERROR(VLOOKUP($A249,'Vocus SIT ExDa'!$B$2:$J$173, 3,FALSE), IFERROR(VLOOKUP($A249,'Telstra ExDa'!$B$2:$K$310, 5,FALSE), IFERROR(VLOOKUP($A249,'Vocus RVC ExDa'!$C$2:$R$155, 9,FALSE), IFERROR(VLOOKUP($A249,'Fusion ExDa'!$B$2:$D$16, 0,FALSE), IFERROR(VLOOKUP($A249,'Exetel ExDa'!$C$2:$N$14, 6,FALSE), IFERROR(VLOOKUP($A249,'Infinet ExDa'!$B$2:$E$14, 0,FALSE), "Not Found")))))))) -> 167.179.164.35 | G249: =IFERROR(VLOOKUP($A249,'AAPT ExDa'!$B$2:$U$99, 5,FALSE), IFERROR(VLOOKUP($A249,'ABB ExDa'!$A$2:$N$184, 8,FALSE), IFERROR(VLOOKUP($A249,'Vocus SIT ExDa'!$B$2:$J$173, 6,FALSE), IFERROR(VLOOKUP($A249,'Telstra ExDa'!$B$2:$K$310, 0,FALSE), IFERROR(VLOOKUP($A249,'Vocus RVC ExDa'!$C$2:$R$155, 15,FALSE), IFERROR(VLOOKUP($A249,'Fusion ExDa'!$B$2:$D$16, 0,FALSE), IFERROR(VLOOKUP($A249,'Exetel ExDa'!$C$2:$N$14, 7,FALSE), IFERROR(VLOOKUP($A249,'Infinet ExDa'!$B$2:$E$14, 0,FALSE), "Not Found")))))))) -> 0 | H249: =IFERROR(VLOOKUP($A249,'AAPT ExDa'!$B$2:$U$99, 6,FALSE), IFERROR(VLOOKUP($A249,'ABB ExDa'!$A$2:$N$184, 0,FALSE), IFERROR(VLOOKUP($A249,'Vocus SIT ExDa'!$B$2:$J$173, 0,FALSE), IFERROR(VLOOKUP($A249,'Telstra ExDa'!$B$2:$K$310, 0,FALSE), IFERROR(VLOOKUP($A249,'Vocus RVC ExDa'!$C$2:$R$155, 16,FALSE), IFERROR(VLOOKUP($A249,'Fusion ExDa'!$B$2:$D$16, 0,FALSE), IFERROR(VLOOKUP($A249,'Exetel ExDa'!$C$2:$N$14, 0,FALSE), IFERROR(VLOOKUP($A249,'Infinet ExDa'!$B$2:$E$14, 0,FALSE), "Not Found")))))))) -> Not Found | I249: =IFERROR(VLOOKUP($A249,'AAPT ExDa'!$B$2:$U$99, 0,FALSE), IFERROR(VLOOKUP($A249,'ABB ExDa'!$A$2:$N$184, 0,FALSE), IFERROR(VLOOKUP($A249,'Vocus SIT ExDa'!$B$2:$J$173, 0,FALSE), IFERROR(VLOOKUP($A249,'Telstra ExDa'!$B$2:$K$310, 0,FALSE), IFERROR(VLOOKUP($A249,'Vocus RVC ExDa'!$C$2:$R$155, 0,FALSE), IFERROR(VLOOKUP($A249,'Fusion ExDa'!$B$2:$D$16, 0,FALSE), IFERROR(VLOOKUP($A249,'Exetel ExDa'!$C$2:$N$14, 8,FALSE), IFERROR(VLOOKUP($A249,'Infinet ExDa'!$B$2:$E$14, 0,FALSE), "Not Found")))))))) -> Not Found | J249: =IFERROR(VLOOKUP($A249,'AAPT ExDa'!$B$2:$U$99, 7,FALSE), IFERROR(VLOOKUP($A249,'ABB ExDa'!$A$2:$N$184, 2,FALSE), IFERROR(VLOOKUP($A249,'Vocus SIT ExDa'!$B$2:$J$173, 0,FALSE), IFERROR(VLOOKUP($A249,'Telstra ExDa'!$B$2:$K$310, 7,FALSE), IFERROR(VLOOKUP($A249,'Vocus RVC ExDa'!$C$2:$R$155, 2,FALSE), IFERROR(VLOOKUP($A249,'Fusion ExDa'!$B$2:$D$16, 3,FALSE), IFERROR(VLOOKUP($A249,'Exetel ExDa'!$C$2:$N$14, 0,FALSE), IFERROR(VLOOKUP($A249,'Infinet ExDa'!$B$2:$E$14, 0,FALSE), "Not Found")))))))) -> Unit 126, 50 Marshall STREET, Burnett Heads QLD | K249: =IFERROR(VLOOKUP($A249,'AAPT ExDa'!$B$2:$U$99, 12,FALSE), IFERROR(VLOOKUP($A249,'ABB ExDa'!$A$2:$N$184, 0,FALSE), IFERROR(VLOOKUP($A249,'Vocus SIT ExDa'!$B$2:$J$173, 0,FALSE), IFERROR(VLOOKUP($A249,'Telstra ExDa'!$B$2:$K$310, 0,FALSE), IFERROR(VLOOKUP($A249,'Vocus RVC ExDa'!$C$2:$R$155, 0,FALSE), IFERROR(VLOOKUP($A249,'Fusion ExDa'!$B$2:$D$16, 0,FALSE), IFERROR(VLOOKUP($A249,'Exetel ExDa'!$C$2:$N$14, 12,FALSE), IFERROR(VLOOKUP($A249,'Infinet ExDa'!$B$2:$E$14, 0,FALSE), "Not Found")))))))) -> Not Found | L249: =IFERROR(VLOOKUP($A249,'AAPT ExDa'!$B$2:$U$99, 11,FALSE), IFERROR(VLOOKUP($A249,'ABB ExDa'!$A$2:$N$184, 9,FALSE), IFERROR(VLOOKUP($A249,'Vocus SIT ExDa'!$B$2:$J$173, 8,FALSE), IFERROR(VLOOKUP($A249,'Telstra ExDa'!$B$2:$K$310, 0,FALSE), IFERROR(VLOOKUP($A249,'Vocus RVC ExDa'!$C$2:$R$155, 0,FALSE), IFERROR(VLOOKUP($A249,'Fusion ExDa'!$B$2:$D$16, 0,FALSE), IFERROR(VLOOKUP($A249,'Exetel ExDa'!$C$2:$N$14, 9,FALSE), IFERROR(VLOOKUP($A249,'Infinet ExDa'!$B$2:$E$14, 0,FALSE), "Not Found")))))))) -> 0 | M249: =IFERROR(VLOOKUP($A249,'AAPT ExDa'!$B$2:$U$99, 0,FALSE), IFERROR(VLOOKUP($A249,'ABB ExDa'!$A$2:$N$184, 0,FALSE), IFERROR(VLOOKUP($A249,'Vocus SIT ExDa'!$B$2:$J$173, 0,FALSE), IFERROR(VLOOKUP($A249,'Telstra ExDa'!$B$2:$K$310, 0,FALSE), IFERROR(VLOOKUP($A249,'Vocus RVC ExDa'!$C$2:$R$155, 0,FALSE), IFERROR(VLOOKUP($A249,'Fusion ExDa'!$B$2:$D$16, 0,FALSE), IFERROR(VLOOKUP($A249,'Exetel ExDa'!$C$2:$N$14, 11,FALSE), IFERROR(VLOOKUP($A249,'Infinet ExDa'!$B$2:$E$14, 0,FALSE), "Not Found")))))))) -> Not Found | N249: =IFERROR(VLOOKUP($A249,'AAPT ExDa'!$B$2:$U$99, 0,FALSE), IFERROR(VLOOKUP($A249,'ABB ExDa'!$A$2:$N$184, 13,FALSE), IFERROR(VLOOKUP($A249,'Vocus SIT ExDa'!$B$2:$J$173, 0,FALSE), IFERROR(VLOOKUP($A249,'Telstra ExDa'!$B$2:$K$310, 0,FALSE), IFERROR(VLOOKUP($A249,'Vocus RVC ExDa'!$C$2:$R$155, 0,FALSE), IFERROR(VLOOKUP($A249,'Fusion ExDa'!$B$2:$D$16, 0,FALSE), IFERROR(VLOOKUP($A249,'Exetel ExDa'!$C$2:$N$14, 0,FALSE), IFERROR(VLOOKUP($A249,'Infinet ExDa'!$B$2:$E$14, 0,FALSE), "Not Found")))))))) -> Onebill
A250: Renovo Solutions | B250: =IFERROR(VLOOKUP(A250,'Exetel ExDa'!$C$2:$N$14,4,FALSE),"No Data") -> No Data | C250: =IFERROR(VLOOKUP(A250,'AAPT ExDa'!$B$2:$U$99, 2,FALSE), IFERROR(VLOOKUP(A250,'ABB ExDa'!$A$2:$N$184, 2,FALSE), IFERROR(VLOOKUP(A250,'Vocus SIT ExDa'!$B$2:$J$173, 7,FALSE), IFERROR(VLOOKUP(A250,'Telstra ExDa'!$B$2:$K$310, 2,FALSE), IFERROR(VLOOKUP(A250,'Vocus RVC ExDa'!$C$2:$R$155, 3,FALSE), IFERROR(VLOOKUP(A250,'Fusion ExDa'!$B$2:$D$16, 2,FALSE), IFERROR(VLOOKUP(A250,'Exetel ExDa'!$C$2:$N$14, 2,FALSE), IFERROR(VLOOKUP(A250,'Infinet ExDa'!$B$2:$E$14, 2,FALSE), "Not Found")))))))) -> 42 MANNING ST, SOUTH BRISBANE QLD | D250: =IFERROR(VLOOKUP($A250,'AAPT ExDa'!$B$2:$U$99, 15,FALSE), IFERROR(VLOOKUP($A250,'ABB ExDa'!$A$2:$N$184, 4,FALSE), IFERROR(VLOOKUP($A250,'Vocus SIT ExDa'!$B$2:$J$173, 5,FALSE), IFERROR(VLOOKUP($A250,'Telstra ExDa'!$B$2:$K$310, 8,FALSE), IFERROR(VLOOKUP($A250,'Vocus RVC ExDa'!$C$2:$R$155, 6,FALSE), IFERROR(VLOOKUP($A250,'Fusion ExDa'!$B$2:$D$16, 4,FALSE), IFERROR(VLOOKUP($A250,'Exetel ExDa'!$C$2:$N$14, 3,FALSE), IFERROR(VLOOKUP($A250,'Infinet ExDa'!$B$2:$E$14, 3,FALSE), "Not Found")))))))) -> ABB | E250: =IFERROR(VLOOKUP($A250,'AAPT ExDa'!$B$2:$U$99, 3,FALSE), IFERROR(VLOOKUP($A250,'ABB ExDa'!$A$2:$N$184, 5,FALSE), IFERROR(VLOOKUP($A250,'Vocus SIT ExDa'!$B$2:$J$173, 2,FALSE), IFERROR(VLOOKUP($A250,'Telstra ExDa'!$B$2:$K$310, 4,FALSE), IFERROR(VLOOKUP($A250,'Vocus RVC ExDa'!$C$2:$R$155, 8,FALSE), IFERROR(VLOOKUP($A250,'Fusion ExDa'!$B$2:$D$16, 4,FALSE), IFERROR(VLOOKUP($A250,'Exetel ExDa'!$C$2:$N$14, 5,FALSE), IFERROR(VLOOKUP($A250,'Infinet ExDa'!$B$2:$E$14, 3,FALSE), "Not Found")))))))) -> 1000Mbps Low CoS | F250: =IFERROR(VLOOKUP($A250,'AAPT ExDa'!$B$2:$U$99, 4,FALSE), IFERROR(VLOOKUP($A250,'ABB ExDa'!$A$2:$N$184, 6,FALSE), IFERROR(VLOOKUP($A250,'Vocus SIT ExDa'!$B$2:$J$173, 3,FALSE), IFERROR(VLOOKUP($A250,'Telstra ExDa'!$B$2:$K$310, 5,FALSE), IFERROR(VLOOKUP($A250,'Vocus RVC ExDa'!$C$2:$R$155, 9,FALSE), IFERROR(VLOOKUP($A250,'Fusion ExDa'!$B$2:$D$16, 0,FALSE), IFERROR(VLOOKUP($A250,'Exetel ExDa'!$C$2:$N$14, 6,FALSE), IFERROR(VLOOKUP($A250,'Infinet ExDa'!$B$2:$E$14, 0,FALSE), "Not Found")))))))) -> 180.181.211.122 | G250: =IFERROR(VLOOKUP($A250,'AAPT ExDa'!$B$2:$U$99, 5,FALSE), IFERROR(VLOOKUP($A250,'ABB ExDa'!$A$2:$N$184, 8,FALSE), IFERROR(VLOOKUP($A250,'Vocus SIT ExDa'!$B$2:$J$173, 6,FALSE), IFERROR(VLOOKUP($A250,'Telstra ExDa'!$B$2:$K$310, 0,FALSE), IFERROR(VLOOKUP($A250,'Vocus RVC ExDa'!$C$2:$R$155, 15,FALSE), IFERROR(VLOOKUP($A250,'Fusion ExDa'!$B$2:$D$16, 0,FALSE), IFERROR(VLOOKUP($A250,'Exetel ExDa'!$C$2:$N$14, 7,FALSE), IFERROR(VLOOKUP($A250,'Infinet ExDa'!$B$2:$E$14, 0,FALSE), "Not Found")))))))) -> 0 | H250: =IFERROR(VLOOKUP($A250,'AAPT ExDa'!$B$2:$U$99, 6,FALSE), IFERROR(VLOOKUP($A250,'ABB ExDa'!$A$2:$N$184, 0,FALSE), IFERROR(VLOOKUP($A250,'Vocus SIT ExDa'!$B$2:$J$173, 0,FALSE), IFERROR(VLOOKUP($A250,'Telstra ExDa'!$B$2:$K$310, 0,FALSE), IFERROR(VLOOKUP($A250,'Vocus RVC ExDa'!$C$2:$R$155, 16,FALSE), IFERROR(VLOOKUP($A250,'Fusion ExDa'!$B$2:$D$16, 0,FALSE), IFERROR(VLOOKUP($A250,'Exetel ExDa'!$C$2:$N$14, 0,FALSE), IFERROR(VLOOKUP($A250,'Infinet ExDa'!$B$2:$E$14, 0,FALSE), "Not Found")))))))) -> Not Found | I250: =IFERROR(VLOOKUP($A250,'AAPT ExDa'!$B$2:$U$99, 0,FALSE), IFERROR(VLOOKUP($A250,'ABB ExDa'!$A$2:$N$184, 0,FALSE), IFERROR(VLOOKUP($A250,'Vocus SIT ExDa'!$B$2:$J$173, 0,FALSE), IFERROR(VLOOKUP($A250,'Telstra ExDa'!$B$2:$K$310, 0,FALSE), IFERROR(VLOOKUP($A250,'Vocus RVC ExDa'!$C$2:$R$155, 0,FALSE), IFERROR(VLOOKUP($A250,'Fusion ExDa'!$B$2:$D$16, 0,FALSE), IFERROR(VLOOKUP($A250,'Exetel ExDa'!$C$2:$N$14, 8,FALSE), IFERROR(VLOOKUP($A250,'Infinet ExDa'!$B$2:$E$14, 0,FALSE), "Not Found")))))))) -> Not Found | J250: =IFERROR(VLOOKUP($A250,'AAPT ExDa'!$B$2:$U$99, 7,FALSE), IFERROR(VLOOKUP($A250,'ABB ExDa'!$A$2:$N$184, 2,FALSE), IFERROR(VLOOKUP($A250,'Vocus SIT ExDa'!$B$2:$J$173, 0,FALSE), IFERROR(VLOOKUP($A250,'Telstra ExDa'!$B$2:$K$310, 7,FALSE), IFERROR(VLOOKUP($A250,'Vocus RVC ExDa'!$C$2:$R$155, 2,FALSE), IFERROR(VLOOKUP($A250,'Fusion ExDa'!$B$2:$D$16, 3,FALSE), IFERROR(VLOOKUP($A250,'Exetel ExDa'!$C$2:$N$14, 0,FALSE), IFERROR(VLOOKUP($A250,'Infinet ExDa'!$B$2:$E$14, 0,FALSE), "Not Found")))))))) -> 42 MANNING ST, SOUTH BRISBANE QLD | K250: =IFERROR(VLOOKUP($A250,'AAPT ExDa'!$B$2:$U$99, 12,FALSE), IFERROR(VLOOKUP($A250,'ABB ExDa'!$A$2:$N$184, 0,FALSE), IFERROR(VLOOKUP($A250,'Vocus SIT ExDa'!$B$2:$J$173, 0,FALSE), IFERROR(VLOOKUP($A250,'Telstra ExDa'!$B$2:$K$310, 0,FALSE), IFERROR(VLOOKUP($A250,'Vocus RVC ExDa'!$C$2:$R$155, 0,FALSE), IFERROR(VLOOKUP($A250,'Fusion ExDa'!$B$2:$D$16, 0,FALSE), IFERROR(VLOOKUP($A250,'Exetel ExDa'!$C$2:$N$14, 12,FALSE), IFERROR(VLOOKUP($A250,'Infinet ExDa'!$B$2:$E$14, 0,FALSE), "Not Found")))))))) -> Not Found | L250: =IFERROR(VLOOKUP($A250,'AAPT ExDa'!$B$2:$U$99, 11,FALSE), IFERROR(VLOOKUP($A250,'ABB ExDa'!$A$2:$N$184, 9,FALSE), IFERROR(VLOOKUP($A250,'Vocus SIT ExDa'!$B$2:$J$173, 8,FALSE), IFERROR(VLOOKUP($A250,'Telstra ExDa'!$B$2:$K$310, 0,FALSE), IFERROR(VLOOKUP($A250,'Vocus RVC ExDa'!$C$2:$R$155, 0,FALSE), IFERROR(VLOOKUP($A250,'Fusion ExDa'!$B$2:$D$16, 0,FALSE), IFERROR(VLOOKUP($A250,'Exetel ExDa'!$C$2:$N$14, 9,FALSE), IFERROR(VLOOKUP($A250,'Infinet ExDa'!$B$2:$E$14, 0,FALSE), "Not Found")))))))) -> 0 | M250: =IFERROR(VLOOKUP($A250,'AAPT ExDa'!$B$2:$U$99, 0,FALSE), IFERROR(VLOOKUP($A250,'ABB ExDa'!$A$2:$N$184, 0,FALSE), IFERROR(VLOOKUP($A250,'Vocus SIT ExDa'!$B$2:$J$173, 0,FALSE), IFERROR(VLOOKUP($A250,'Telstra ExDa'!$B$2:$K$310, 0,FALSE), IFERROR(VLOOKUP($A250,'Vocus RVC ExDa'!$C$2:$R$155, 0,FALSE), IFERROR(VLOOKUP($A250,'Fusion ExDa'!$B$2:$D$16, 0,FALSE), IFERROR(VLOOKUP($A250,'Exetel ExDa'!$C$2:$N$14, 11,FALSE), IFERROR(VLOOKUP($A250,'Infinet ExDa'!$B$2:$E$14, 0,FALSE), "Not Found")))))))) -> Not Found | N250: =IFERROR(VLOOKUP($A250,'AAPT ExDa'!$B$2:$U$99, 0,FALSE), IFERROR(VLOOKUP($A250,'ABB ExDa'!$A$2:$N$184, 13,FALSE), IFERROR(VLOOKUP($A250,'Vocus SIT ExDa'!$B$2:$J$173, 0,FALSE), IFERROR(VLOOKUP($A250,'Telstra ExDa'!$B$2:$K$310, 0,FALSE), IFERROR(VLOOKUP($A250,'Vocus RVC ExDa'!$C$2:$R$155, 0,FALSE), IFERROR(VLOOKUP($A250,'Fusion ExDa'!$B$2:$D$16, 0,FALSE), IFERROR(VLOOKUP($A250,'Exetel ExDa'!$C$2:$N$14, 0,FALSE), IFERROR(VLOOKUP($A250,'Infinet ExDa'!$B$2:$E$14, 0,FALSE), "Not Found")))))))) -> 0
A251: GBA Rockhampton | B251: =IFERROR(VLOOKUP(A251,'Exetel ExDa'!$C$2:$N$14,4,FALSE),"No Data") -> No Data | C251: =IFERROR(VLOOKUP(A251,'AAPT ExDa'!$B$2:$U$99, 2,FALSE), IFERROR(VLOOKUP(A251,'ABB ExDa'!$A$2:$N$184, 2,FALSE), IFERROR(VLOOKUP(A251,'Vocus SIT ExDa'!$B$2:$J$173, 7,FALSE), IFERROR(VLOOKUP(A251,'Telstra ExDa'!$B$2:$K$310, 2,FALSE), IFERROR(VLOOKUP(A251,'Vocus RVC ExDa'!$C$2:$R$155, 3,FALSE), IFERROR(VLOOKUP(A251,'Fusion ExDa'!$B$2:$D$16, 2,FALSE), IFERROR(VLOOKUP(A251,'Exetel ExDa'!$C$2:$N$14, 2,FALSE), IFERROR(VLOOKUP(A251,'Infinet ExDa'!$B$2:$E$14, 2,FALSE), "Not Found")))))))) -> SE 2, 74 VICTORIA PDE, ROCKHAMPTON CITY QLD | D251: =IFERROR(VLOOKUP($A251,'AAPT ExDa'!$B$2:$U$99, 15,FALSE), IFERROR(VLOOKUP($A251,'ABB ExDa'!$A$2:$N$184, 4,FALSE), IFERROR(VLOOKUP($A251,'Vocus SIT ExDa'!$B$2:$J$173, 5,FALSE), IFERROR(VLOOKUP($A251,'Telstra ExDa'!$B$2:$K$310, 8,FALSE), IFERROR(VLOOKUP($A251,'Vocus RVC ExDa'!$C$2:$R$155, 6,FALSE), IFERROR(VLOOKUP($A251,'Fusion ExDa'!$B$2:$D$16, 4,FALSE), IFERROR(VLOOKUP($A251,'Exetel ExDa'!$C$2:$N$14, 3,FALSE), IFERROR(VLOOKUP($A251,'Infinet ExDa'!$B$2:$E$14, 3,FALSE), "Not Found")))))))) -> ABB | E251: =IFERROR(VLOOKUP($A251,'AAPT ExDa'!$B$2:$U$99, 3,FALSE), IFERROR(VLOOKUP($A251,'ABB ExDa'!$A$2:$N$184, 5,FALSE), IFERROR(VLOOKUP($A251,'Vocus SIT ExDa'!$B$2:$J$173, 2,FALSE), IFERROR(VLOOKUP($A251,'Telstra ExDa'!$B$2:$K$310, 4,FALSE), IFERROR(VLOOKUP($A251,'Vocus RVC ExDa'!$C$2:$R$155, 8,FALSE), IFERROR(VLOOKUP($A251,'Fusion ExDa'!$B$2:$D$16, 4,FALSE), IFERROR(VLOOKUP($A251,'Exetel ExDa'!$C$2:$N$14, 5,FALSE), IFERROR(VLOOKUP($A251,'Infinet ExDa'!$B$2:$E$14, 3,FALSE), "Not Found")))))))) -> NBN 100/40 | F251: =IFERROR(VLOOKUP($A251,'AAPT ExDa'!$B$2:$U$99, 4,FALSE), IFERROR(VLOOKUP($A251,'ABB ExDa'!$A$2:$N$184, 6,FALSE), IFERROR(VLOOKUP($A251,'Vocus SIT ExDa'!$B$2:$J$173, 3,FALSE), IFERROR(VLOOKUP($A251,'Telstra ExDa'!$B$2:$K$310, 5,FALSE), IFERROR(VLOOKUP($A251,'Vocus RVC ExDa'!$C$2:$R$155, 9,FALSE), IFERROR(VLOOKUP($A251,'Fusion ExDa'!$B$2:$D$16, 0,FALSE), IFERROR(VLOOKUP($A251,'Exetel ExDa'!$C$2:$N$14, 6,FALSE), IFERROR(VLOOKUP($A251,'Infinet ExDa'!$B$2:$E$14, 0,FALSE), "Not Found")))))))) -> FTTN | G251: =IFERROR(VLOOKUP($A251,'AAPT ExDa'!$B$2:$U$99, 5,FALSE), IFERROR(VLOOKUP($A251,'ABB ExDa'!$A$2:$N$184, 8,FALSE), IFERROR(VLOOKUP($A251,'Vocus SIT ExDa'!$B$2:$J$173, 6,FALSE), IFERROR(VLOOKUP($A251,'Telstra ExDa'!$B$2:$K$310, 0,FALSE), IFERROR(VLOOKUP($A251,'Vocus RVC ExDa'!$C$2:$R$155, 15,FALSE), IFERROR(VLOOKUP($A251,'Fusion ExDa'!$B$2:$D$16, 0,FALSE), IFERROR(VLOOKUP($A251,'Exetel ExDa'!$C$2:$N$14, 7,FALSE), IFERROR(VLOOKUP($A251,'Infinet ExDa'!$B$2:$E$14, 0,FALSE), "Not Found")))))))) -> 144.6.127.36 | H251: =IFERROR(VLOOKUP($A251,'AAPT ExDa'!$B$2:$U$99, 6,FALSE), IFERROR(VLOOKUP($A251,'ABB ExDa'!$A$2:$N$184, 0,FALSE), IFERROR(VLOOKUP($A251,'Vocus SIT ExDa'!$B$2:$J$173, 0,FALSE), IFERROR(VLOOKUP($A251,'Telstra ExDa'!$B$2:$K$310, 0,FALSE), IFERROR(VLOOKUP($A251,'Vocus RVC ExDa'!$C$2:$R$155, 16,FALSE), IFERROR(VLOOKUP($A251,'Fusion ExDa'!$B$2:$D$16, 0,FALSE), IFERROR(VLOOKUP($A251,'Exetel ExDa'!$C$2:$N$14, 0,FALSE), IFERROR(VLOOKUP($A251,'Infinet ExDa'!$B$2:$E$14, 0,FALSE), "Not Found")))))))) -> Not Found | I251: =IFERROR(VLOOKUP($A251,'AAPT ExDa'!$B$2:$U$99, 0,FALSE), IFERROR(VLOOKUP($A251,'ABB ExDa'!$A$2:$N$184, 0,FALSE), IFERROR(VLOOKUP($A251,'Vocus SIT ExDa'!$B$2:$J$173, 0,FALSE), IFERROR(VLOOKUP($A251,'Telstra ExDa'!$B$2:$K$310, 0,FALSE), IFERROR(VLOOKUP($A251,'Vocus RVC ExDa'!$C$2:$R$155, 0,FALSE), IFERROR(VLOOKUP($A251,'Fusion ExDa'!$B$2:$D$16, 0,FALSE), IFERROR(VLOOKUP($A251,'Exetel ExDa'!$C$2:$N$14, 8,FALSE), IFERROR(VLOOKUP($A251,'Infinet ExDa'!$B$2:$E$14, 0,FALSE), "Not Found")))))))) -> Not Found | J251: =IFERROR(VLOOKUP($A251,'AAPT ExDa'!$B$2:$U$99, 7,FALSE), IFERROR(VLOOKUP($A251,'ABB ExDa'!$A$2:$N$184, 2,FALSE), IFERROR(VLOOKUP($A251,'Vocus SIT ExDa'!$B$2:$J$173, 0,FALSE), IFERROR(VLOOKUP($A251,'Telstra ExDa'!$B$2:$K$310, 7,FALSE), IFERROR(VLOOKUP($A251,'Vocus RVC ExDa'!$C$2:$R$155, 2,FALSE), IFERROR(VLOOKUP($A251,'Fusion ExDa'!$B$2:$D$16, 3,FALSE), IFERROR(VLOOKUP($A251,'Exetel ExDa'!$C$2:$N$14, 0,FALSE), IFERROR(VLOOKUP($A251,'Infinet ExDa'!$B$2:$E$14, 0,FALSE), "Not Found")))))))) -> SE 2, 74 VICTORIA PDE, ROCKHAMPTON CITY QLD | K251: =IFERROR(VLOOKUP($A251,'AAPT ExDa'!$B$2:$U$99, 12,FALSE), IFERROR(VLOOKUP($A251,'ABB ExDa'!$A$2:$N$184, 0,FALSE), IFERROR(VLOOKUP($A251,'Vocus SIT ExDa'!$B$2:$J$173, 0,FALSE), IFERROR(VLOOKUP($A251,'Telstra ExDa'!$B$2:$K$310, 0,FALSE), IFERROR(VLOOKUP($A251,'Vocus RVC ExDa'!$C$2:$R$155, 0,FALSE), IFERROR(VLOOKUP($A251,'Fusion ExDa'!$B$2:$D$16, 0,FALSE), IFERROR(VLOOKUP($A251,'Exetel ExDa'!$C$2:$N$14, 12,FALSE), IFERROR(VLOOKUP($A251,'Infinet ExDa'!$B$2:$E$14, 0,FALSE), "Not Found")))))))) -> Not Found | L251: =IFERROR(VLOOKUP($A251,'AAPT ExDa'!$B$2:$U$99, 11,FALSE), IFERROR(VLOOKUP($A251,'ABB ExDa'!$A$2:$N$184, 9,FALSE), IFERROR(VLOOKUP($A251,'Vocus SIT ExDa'!$B$2:$J$173, 8,FALSE), IFERROR(VLOOKUP($A251,'Telstra ExDa'!$B$2:$K$310, 0,FALSE), IFERROR(VLOOKUP($A251,'Vocus RVC ExDa'!$C$2:$R$155, 0,FALSE), IFERROR(VLOOKUP($A251,'Fusion ExDa'!$B$2:$D$16, 0,FALSE), IFERROR(VLOOKUP($A251,'Exetel ExDa'!$C$2:$N$14, 9,FALSE), IFERROR(VLOOKUP($A251,'Infinet ExDa'!$B$2:$E$14, 0,FALSE), "Not Found")))))))) -> 26 July 2024 | M251: =IFERROR(VLOOKUP($A251,'AAPT ExDa'!$B$2:$U$99, 0,FALSE), IFERROR(VLOOKUP($A251,'ABB ExDa'!$A$2:$N$184, 0,FALSE), IFERROR(VLOOKUP($A251,'Vocus SIT ExDa'!$B$2:$J$173, 0,FALSE), IFERROR(VLOOKUP($A251,'Telstra ExDa'!$B$2:$K$310, 0,FALSE), IFERROR(VLOOKUP($A251,'Vocus RVC ExDa'!$C$2:$R$155, 0,FALSE), IFERROR(VLOOKUP($A251,'Fusion ExDa'!$B$2:$D$16, 0,FALSE), IFERROR(VLOOKUP($A251,'Exetel ExDa'!$C$2:$N$14, 11,FALSE), IFERROR(VLOOKUP($A251,'Infinet ExDa'!$B$2:$E$14, 0,FALSE), "Not Found")))))))) -> Not Found | N251: =IFERROR(VLOOKUP($A251,'AAPT ExDa'!$B$2:$U$99, 0,FALSE), IFERROR(VLOOKUP($A251,'ABB ExDa'!$A$2:$N$184, 13,FALSE), IFERROR(VLOOKUP($A251,'Vocus SIT ExDa'!$B$2:$J$173, 0,FALSE), IFERROR(VLOOKUP($A251,'Telstra ExDa'!$B$2:$K$310, 0,FALSE), IFERROR(VLOOKUP($A251,'Vocus RVC ExDa'!$C$2:$R$155, 0,FALSE), IFERROR(VLOOKUP($A251,'Fusion ExDa'!$B$2:$D$16, 0,FALSE), IFERROR(VLOOKUP($A251,'Exetel ExDa'!$C$2:$N$14, 0,FALSE), IFERROR(VLOOKUP($A251,'Infinet ExDa'!$B$2:$E$14, 0,FALSE), "Not Found")))))))) -> Sasboss
A252: GBA Emerald | B252: =IFERROR(VLOOKUP(A252,'Exetel ExDa'!$C$2:$N$14,4,FALSE),"No Data") -> No Data | C252: =IFERROR(VLOOKUP(A252,'AAPT ExDa'!$B$2:$U$99, 2,FALSE), IFERROR(VLOOKUP(A252,'ABB ExDa'!$A$2:$N$184, 2,FALSE), IFERROR(VLOOKUP(A252,'Vocus SIT ExDa'!$B$2:$J$173, 7,FALSE), IFERROR(VLOOKUP(A252,'Telstra ExDa'!$B$2:$K$310, 2,FALSE), IFERROR(VLOOKUP(A252,'Vocus RVC ExDa'!$C$2:$R$155, 3,FALSE), IFERROR(VLOOKUP(A252,'Fusion ExDa'!$B$2:$D$16, 2,FALSE), IFERROR(VLOOKUP(A252,'Exetel ExDa'!$C$2:$N$14, 2,FALSE), IFERROR(VLOOKUP(A252,'Infinet ExDa'!$B$2:$E$14, 2,FALSE), "Not Found")))))))) -> 5 CHURCH LANE, EMERALD QLD | D252: =IFERROR(VLOOKUP($A252,'AAPT ExDa'!$B$2:$U$99, 15,FALSE), IFERROR(VLOOKUP($A252,'ABB ExDa'!$A$2:$N$184, 4,FALSE), IFERROR(VLOOKUP($A252,'Vocus SIT ExDa'!$B$2:$J$173, 5,FALSE), IFERROR(VLOOKUP($A252,'Telstra ExDa'!$B$2:$K$310, 8,FALSE), IFERROR(VLOOKUP($A252,'Vocus RVC ExDa'!$C$2:$R$155, 6,FALSE), IFERROR(VLOOKUP($A252,'Fusion ExDa'!$B$2:$D$16, 4,FALSE), IFERROR(VLOOKUP($A252,'Exetel ExDa'!$C$2:$N$14, 3,FALSE), IFERROR(VLOOKUP($A252,'Infinet ExDa'!$B$2:$E$14, 3,FALSE), "Not Found")))))))) -> ABB | E252: =IFERROR(VLOOKUP($A252,'AAPT ExDa'!$B$2:$U$99, 3,FALSE), IFERROR(VLOOKUP($A252,'ABB ExDa'!$A$2:$N$184, 5,FALSE), IFERROR(VLOOKUP($A252,'Vocus SIT ExDa'!$B$2:$J$173, 2,FALSE), IFERROR(VLOOKUP($A252,'Telstra ExDa'!$B$2:$K$310, 4,FALSE), IFERROR(VLOOKUP($A252,'Vocus RVC ExDa'!$C$2:$R$155, 8,FALSE), IFERROR(VLOOKUP($A252,'Fusion ExDa'!$B$2:$D$16, 4,FALSE), IFERROR(VLOOKUP($A252,'Exetel ExDa'!$C$2:$N$14, 5,FALSE), IFERROR(VLOOKUP($A252,'Infinet ExDa'!$B$2:$E$14, 3,FALSE), "Not Found")))))))) -> 1000Mbps Low CoS | F252: =IFERROR(VLOOKUP($A252,'AAPT ExDa'!$B$2:$U$99, 4,FALSE), IFERROR(VLOOKUP($A252,'ABB ExDa'!$A$2:$N$184, 6,FALSE), IFERROR(VLOOKUP($A252,'Vocus SIT ExDa'!$B$2:$J$173, 3,FALSE), IFERROR(VLOOKUP($A252,'Telstra ExDa'!$B$2:$K$310, 5,FALSE), IFERROR(VLOOKUP($A252,'Vocus RVC ExDa'!$C$2:$R$155, 9,FALSE), IFERROR(VLOOKUP($A252,'Fusion ExDa'!$B$2:$D$16, 0,FALSE), IFERROR(VLOOKUP($A252,'Exetel ExDa'!$C$2:$N$14, 6,FALSE), IFERROR(VLOOKUP($A252,'Infinet ExDa'!$B$2:$E$14, 0,FALSE), "Not Found")))))))) -> 180.181.210.204 | G252: =IFERROR(VLOOKUP($A252,'AAPT ExDa'!$B$2:$U$99, 5,FALSE), IFERROR(VLOOKUP($A252,'ABB ExDa'!$A$2:$N$184, 8,FALSE), IFERROR(VLOOKUP($A252,'Vocus SIT ExDa'!$B$2:$J$173, 6,FALSE), IFERROR(VLOOKUP($A252,'Telstra ExDa'!$B$2:$K$310, 0,FALSE), IFERROR(VLOOKUP($A252,'Vocus RVC ExDa'!$C$2:$R$155, 15,FALSE), IFERROR(VLOOKUP($A252,'Fusion ExDa'!$B$2:$D$16, 0,FALSE), IFERROR(VLOOKUP($A252,'Exetel ExDa'!$C$2:$N$14, 7,FALSE), IFERROR(VLOOKUP($A252,'Infinet ExDa'!$B$2:$E$14, 0,FALSE), "Not Found")))))))) -> 12 Months | H252: =IFERROR(VLOOKUP($A252,'AAPT ExDa'!$B$2:$U$99, 6,FALSE), IFERROR(VLOOKUP($A252,'ABB ExDa'!$A$2:$N$184, 0,FALSE), IFERROR(VLOOKUP($A252,'Vocus SIT ExDa'!$B$2:$J$173, 0,FALSE), IFERROR(VLOOKUP($A252,'Telstra ExDa'!$B$2:$K$310, 0,FALSE), IFERROR(VLOOKUP($A252,'Vocus RVC ExDa'!$C$2:$R$155, 16,FALSE), IFERROR(VLOOKUP($A252,'Fusion ExDa'!$B$2:$D$16, 0,FALSE), IFERROR(VLOOKUP($A252,'Exetel ExDa'!$C$2:$N$14, 0,FALSE), IFERROR(VLOOKUP($A252,'Infinet ExDa'!$B$2:$E$14, 0,FALSE), "Not Found")))))))) -> Not Found | I252: =IFERROR(VLOOKUP($A252,'AAPT ExDa'!$B$2:$U$99, 0,FALSE), IFERROR(VLOOKUP($A252,'ABB ExDa'!$A$2:$N$184, 0,FALSE), IFERROR(VLOOKUP($A252,'Vocus SIT ExDa'!$B$2:$J$173, 0,FALSE), IFERROR(VLOOKUP($A252,'Telstra ExDa'!$B$2:$K$310, 0,FALSE), IFERROR(VLOOKUP($A252,'Vocus RVC ExDa'!$C$2:$R$155, 0,FALSE), IFERROR(VLOOKUP($A252,'Fusion ExDa'!$B$2:$D$16, 0,FALSE), IFERROR(VLOOKUP($A252,'Exetel ExDa'!$C$2:$N$14, 8,FALSE), IFERROR(VLOOKUP($A252,'Infinet ExDa'!$B$2:$E$14, 0,FALSE), "Not Found")))))))) -> Not Found | J252: =IFERROR(VLOOKUP($A252,'AAPT ExDa'!$B$2:$U$99, 7,FALSE), IFERROR(VLOOKUP($A252,'ABB ExDa'!$A$2:$N$184, 2,FALSE), IFERROR(VLOOKUP($A252,'Vocus SIT ExDa'!$B$2:$J$173, 0,FALSE), IFERROR(VLOOKUP($A252,'Telstra ExDa'!$B$2:$K$310, 7,FALSE), IFERROR(VLOOKUP($A252,'Vocus RVC ExDa'!$C$2:$R$155, 2,FALSE), IFERROR(VLOOKUP($A252,'Fusion ExDa'!$B$2:$D$16, 3,FALSE), IFERROR(VLOOKUP($A252,'Exetel ExDa'!$C$2:$N$14, 0,FALSE), IFERROR(VLOOKUP($A252,'Infinet ExDa'!$B$2:$E$14, 0,FALSE), "Not Found")))))))) -> 5 CHURCH LANE, EMERALD QLD | K252: =IFERROR(VLOOKUP($A252,'AAPT ExDa'!$B$2:$U$99, 12,FALSE), IFERROR(VLOOKUP($A252,'ABB ExDa'!$A$2:$N$184, 0,FALSE), IFERROR(VLOOKUP($A252,'Vocus SIT ExDa'!$B$2:$J$173, 0,FALSE), IFERROR(VLOOKUP($A252,'Telstra ExDa'!$B$2:$K$310, 0,FALSE), IFERROR(VLOOKUP($A252,'Vocus RVC ExDa'!$C$2:$R$155, 0,FALSE), IFERROR(VLOOKUP($A252,'Fusion ExDa'!$B$2:$D$16, 0,FALSE), IFERROR(VLOOKUP($A252,'Exetel ExDa'!$C$2:$N$14, 12,FALSE), IFERROR(VLOOKUP($A252,'Infinet ExDa'!$B$2:$E$14, 0,FALSE), "Not Found")))))))) -> Not Found | L252: =IFERROR(VLOOKUP($A252,'AAPT ExDa'!$B$2:$U$99, 11,FALSE), IFERROR(VLOOKUP($A252,'ABB ExDa'!$A$2:$N$184, 9,FALSE), IFERROR(VLOOKUP($A252,'Vocus SIT ExDa'!$B$2:$J$173, 8,FALSE), IFERROR(VLOOKUP($A252,'Telstra ExDa'!$B$2:$K$310, 0,FALSE), IFERROR(VLOOKUP($A252,'Vocus RVC ExDa'!$C$2:$R$155, 0,FALSE), IFERROR(VLOOKUP($A252,'Fusion ExDa'!$B$2:$D$16, 0,FALSE), IFERROR(VLOOKUP($A252,'Exetel ExDa'!$C$2:$N$14, 9,FALSE), IFERROR(VLOOKUP($A252,'Infinet ExDa'!$B$2:$E$14, 0,FALSE), "Not Found")))))))) -> 13 June 2026 | M252: =IFERROR(VLOOKUP($A252,'AAPT ExDa'!$B$2:$U$99, 0,FALSE), IFERROR(VLOOKUP($A252,'ABB ExDa'!$A$2:$N$184, 0,FALSE), IFERROR(VLOOKUP($A252,'Vocus SIT ExDa'!$B$2:$J$173, 0,FALSE), IFERROR(VLOOKUP($A252,'Telstra ExDa'!$B$2:$K$310, 0,FALSE), IFERROR(VLOOKUP($A252,'Vocus RVC ExDa'!$C$2:$R$155, 0,FALSE), IFERROR(VLOOKUP($A252,'Fusion ExDa'!$B$2:$D$16, 0,FALSE), IFERROR(VLOOKUP($A252,'Exetel ExDa'!$C$2:$N$14, 11,FALSE), IFERROR(VLOOKUP($A252,'Infinet ExDa'!$B$2:$E$14, 0,FALSE), "Not Found")))))))) -> Not Found | N252: =IFERROR(VLOOKUP($A252,'AAPT ExDa'!$B$2:$U$99, 0,FALSE), IFERROR(VLOOKUP($A252,'ABB ExDa'!$A$2:$N$184, 13,FALSE), IFERROR(VLOOKUP($A252,'Vocus SIT ExDa'!$B$2:$J$173, 0,FALSE), IFERROR(VLOOKUP($A252,'Telstra ExDa'!$B$2:$K$310, 0,FALSE), IFERROR(VLOOKUP($A252,'Vocus RVC ExDa'!$C$2:$R$155, 0,FALSE), IFERROR(VLOOKUP($A252,'Fusion ExDa'!$B$2:$D$16, 0,FALSE), IFERROR(VLOOKUP($A252,'Exetel ExDa'!$C$2:$N$14, 0,FALSE), IFERROR(VLOOKUP($A252,'Infinet ExDa'!$B$2:$E$14, 0,FALSE), "Not Found")))))))) -> 0
A253: Bell Criminal Lawyers | B253: =IFERROR(VLOOKUP(A253,'Exetel ExDa'!$C$2:$N$14,4,FALSE),"No Data") -> No Data | C253: =IFERROR(VLOOKUP(A253,'AAPT ExDa'!$B$2:$U$99, 2,FALSE), IFERROR(VLOOKUP(A253,'ABB ExDa'!$A$2:$N$184, 2,FALSE), IFERROR(VLOOKUP(A253,'Vocus SIT ExDa'!$B$2:$J$173, 7,FALSE), IFERROR(VLOOKUP(A253,'Telstra ExDa'!$B$2:$K$310, 2,FALSE), IFERROR(VLOOKUP(A253,'Vocus RVC ExDa'!$C$2:$R$155, 3,FALSE), IFERROR(VLOOKUP(A253,'Fusion ExDa'!$B$2:$D$16, 2,FALSE), IFERROR(VLOOKUP(A253,'Exetel ExDa'!$C$2:$N$14, 2,FALSE), IFERROR(VLOOKUP(A253,'Infinet ExDa'!$B$2:$E$14, 2,FALSE), "Not Found")))))))) -> BP HOUSE OFFC 10C, 193 NORTH QY, BRISBANE CITY QLD | D253: =IFERROR(VLOOKUP($A253,'AAPT ExDa'!$B$2:$U$99, 15,FALSE), IFERROR(VLOOKUP($A253,'ABB ExDa'!$A$2:$N$184, 4,FALSE), IFERROR(VLOOKUP($A253,'Vocus SIT ExDa'!$B$2:$J$173, 5,FALSE), IFERROR(VLOOKUP($A253,'Telstra ExDa'!$B$2:$K$310, 8,FALSE), IFERROR(VLOOKUP($A253,'Vocus RVC ExDa'!$C$2:$R$155, 6,FALSE), IFERROR(VLOOKUP($A253,'Fusion ExDa'!$B$2:$D$16, 4,FALSE), IFERROR(VLOOKUP($A253,'Exetel ExDa'!$C$2:$N$14, 3,FALSE), IFERROR(VLOOKUP($A253,'Infinet ExDa'!$B$2:$E$14, 3,FALSE), "Not Found")))))))) -> ABB | E253: =IFERROR(VLOOKUP($A253,'AAPT ExDa'!$B$2:$U$99, 3,FALSE), IFERROR(VLOOKUP($A253,'ABB ExDa'!$A$2:$N$184, 5,FALSE), IFERROR(VLOOKUP($A253,'Vocus SIT ExDa'!$B$2:$J$173, 2,FALSE), IFERROR(VLOOKUP($A253,'Telstra ExDa'!$B$2:$K$310, 4,FALSE), IFERROR(VLOOKUP($A253,'Vocus RVC ExDa'!$C$2:$R$155, 8,FALSE), IFERROR(VLOOKUP($A253,'Fusion ExDa'!$B$2:$D$16, 4,FALSE), IFERROR(VLOOKUP($A253,'Exetel ExDa'!$C$2:$N$14, 5,FALSE), IFERROR(VLOOKUP($A253,'Infinet ExDa'!$B$2:$E$14, 3,FALSE), "Not Found")))))))) -> 250Mbps Low CoS | F253: =IFERROR(VLOOKUP($A253,'AAPT ExDa'!$B$2:$U$99, 4,FALSE), IFERROR(VLOOKUP($A253,'ABB ExDa'!$A$2:$N$184, 6,FALSE), IFERROR(VLOOKUP($A253,'Vocus SIT ExDa'!$B$2:$J$173, 3,FALSE), IFERROR(VLOOKUP($A253,'Telstra ExDa'!$B$2:$K$310, 5,FALSE), IFERROR(VLOOKUP($A253,'Vocus RVC ExDa'!$C$2:$R$155, 9,FALSE), IFERROR(VLOOKUP($A253,'Fusion ExDa'!$B$2:$D$16, 0,FALSE), IFERROR(VLOOKUP($A253,'Exetel ExDa'!$C$2:$N$14, 6,FALSE), IFERROR(VLOOKUP($A253,'Infinet ExDa'!$B$2:$E$14, 0,FALSE), "Not Found")))))))) -> 144.6.112.116 | G253: =IFERROR(VLOOKUP($A253,'AAPT ExDa'!$B$2:$U$99, 5,FALSE), IFERROR(VLOOKUP($A253,'ABB ExDa'!$A$2:$N$184, 8,FALSE), IFERROR(VLOOKUP($A253,'Vocus SIT ExDa'!$B$2:$J$173, 6,FALSE), IFERROR(VLOOKUP($A253,'Telstra ExDa'!$B$2:$K$310, 0,FALSE), IFERROR(VLOOKUP($A253,'Vocus RVC ExDa'!$C$2:$R$155, 15,FALSE), IFERROR(VLOOKUP($A253,'Fusion ExDa'!$B$2:$D$16, 0,FALSE), IFERROR(VLOOKUP($A253,'Exetel ExDa'!$C$2:$N$14, 7,FALSE), IFERROR(VLOOKUP($A253,'Infinet ExDa'!$B$2:$E$14, 0,FALSE), "Not Found")))))))) -> 36 Months | H253: =IFERROR(VLOOKUP($A253,'AAPT ExDa'!$B$2:$U$99, 6,FALSE), IFERROR(VLOOKUP($A253,'ABB ExDa'!$A$2:$N$184, 0,FALSE), IFERROR(VLOOKUP($A253,'Vocus SIT ExDa'!$B$2:$J$173, 0,FALSE), IFERROR(VLOOKUP($A253,'Telstra ExDa'!$B$2:$K$310, 0,FALSE), IFERROR(VLOOKUP($A253,'Vocus RVC ExDa'!$C$2:$R$155, 16,FALSE), IFERROR(VLOOKUP($A253,'Fusion ExDa'!$B$2:$D$16, 0,FALSE), IFERROR(VLOOKUP($A253,'Exetel ExDa'!$C$2:$N$14, 0,FALSE), IFERROR(VLOOKUP($A253,'Infinet ExDa'!$B$2:$E$14, 0,FALSE), "Not Found")))))))) -> Not Found | I253: =IFERROR(VLOOKUP($A253,'AAPT ExDa'!$B$2:$U$99, 0,FALSE), IFERROR(VLOOKUP($A253,'ABB ExDa'!$A$2:$N$184, 0,FALSE), IFERROR(VLOOKUP($A253,'Vocus SIT ExDa'!$B$2:$J$173, 0,FALSE), IFERROR(VLOOKUP($A253,'Telstra ExDa'!$B$2:$K$310, 0,FALSE), IFERROR(VLOOKUP($A253,'Vocus RVC ExDa'!$C$2:$R$155, 0,FALSE), IFERROR(VLOOKUP($A253,'Fusion ExDa'!$B$2:$D$16, 0,FALSE), IFERROR(VLOOKUP($A253,'Exetel ExDa'!$C$2:$N$14, 8,FALSE), IFERROR(VLOOKUP($A253,'Infinet ExDa'!$B$2:$E$14, 0,FALSE), "Not Found")))))))) -> Not Found | J253: =IFERROR(VLOOKUP($A253,'AAPT ExDa'!$B$2:$U$99, 7,FALSE), IFERROR(VLOOKUP($A253,'ABB ExDa'!$A$2:$N$184, 2,FALSE), IFERROR(VLOOKUP($A253,'Vocus SIT ExDa'!$B$2:$J$173, 0,FALSE), IFERROR(VLOOKUP($A253,'Telstra ExDa'!$B$2:$K$310, 7,FALSE), IFERROR(VLOOKUP($A253,'Vocus RVC ExDa'!$C$2:$R$155, 2,FALSE), IFERROR(VLOOKUP($A253,'Fusion ExDa'!$B$2:$D$16, 3,FALSE), IFERROR(VLOOKUP($A253,'Exetel ExDa'!$C$2:$N$14, 0,FALSE), IFERROR(VLOOKUP($A253,'Infinet ExDa'!$B$2:$E$14, 0,FALSE), "Not Found")))))))) -> BP HOUSE OFFC 10C, 193 NORTH QY, BRISBANE CITY QLD | K253: =IFERROR(VLOOKUP($A253,'AAPT ExDa'!$B$2:$U$99, 12,FALSE), IFERROR(VLOOKUP($A253,'ABB ExDa'!$A$2:$N$184, 0,FALSE), IFERROR(VLOOKUP($A253,'Vocus SIT ExDa'!$B$2:$J$173, 0,FALSE), IFERROR(VLOOKUP($A253,'Telstra ExDa'!$B$2:$K$310, 0,FALSE), IFERROR(VLOOKUP($A253,'Vocus RVC ExDa'!$C$2:$R$155, 0,FALSE), IFERROR(VLOOKUP($A253,'Fusion ExDa'!$B$2:$D$16, 0,FALSE), IFERROR(VLOOKUP($A253,'Exetel ExDa'!$C$2:$N$14, 12,FALSE), IFERROR(VLOOKUP($A253,'Infinet ExDa'!$B$2:$E$14, 0,FALSE), "Not Found")))))))) -> Not Found | L253: =IFERROR(VLOOKUP($A253,'AAPT ExDa'!$B$2:$U$99, 11,FALSE), IFERROR(VLOOKUP($A253,'ABB ExDa'!$A$2:$N$184, 9,FALSE), IFERROR(VLOOKUP($A253,'Vocus SIT ExDa'!$B$2:$J$173, 8,FALSE), IFERROR(VLOOKUP($A253,'Telstra ExDa'!$B$2:$K$310, 0,FALSE), IFERROR(VLOOKUP($A253,'Vocus RVC ExDa'!$C$2:$R$155, 0,FALSE), IFERROR(VLOOKUP($A253,'Fusion ExDa'!$B$2:$D$16, 0,FALSE), IFERROR(VLOOKUP($A253,'Exetel ExDa'!$C$2:$N$14, 9,FALSE), IFERROR(VLOOKUP($A253,'Infinet ExDa'!$B$2:$E$14, 0,FALSE), "Not Found")))))))) -> 22 May 2028 | M253: =IFERROR(VLOOKUP($A253,'AAPT ExDa'!$B$2:$U$99, 0,FALSE), IFERROR(VLOOKUP($A253,'ABB ExDa'!$A$2:$N$184, 0,FALSE), IFERROR(VLOOKUP($A253,'Vocus SIT ExDa'!$B$2:$J$173, 0,FALSE), IFERROR(VLOOKUP($A253,'Telstra ExDa'!$B$2:$K$310, 0,FALSE), IFERROR(VLOOKUP($A253,'Vocus RVC ExDa'!$C$2:$R$155, 0,FALSE), IFERROR(VLOOKUP($A253,'Fusion ExDa'!$B$2:$D$16, 0,FALSE), IFERROR(VLOOKUP($A253,'Exetel ExDa'!$C$2:$N$14, 11,FALSE), IFERROR(VLOOKUP($A253,'Infinet ExDa'!$B$2:$E$14, 0,FALSE), "Not Found")))))))) -> Not Found | N253: =IFERROR(VLOOKUP($A253,'AAPT ExDa'!$B$2:$U$99, 0,FALSE), IFERROR(VLOOKUP($A253,'ABB ExDa'!$A$2:$N$184, 13,FALSE), IFERROR(VLOOKUP($A253,'Vocus SIT ExDa'!$B$2:$J$173, 0,FALSE), IFERROR(VLOOKUP($A253,'Telstra ExDa'!$B$2:$K$310, 0,FALSE), IFERROR(VLOOKUP($A253,'Vocus RVC ExDa'!$C$2:$R$155, 0,FALSE), IFERROR(VLOOKUP($A253,'Fusion ExDa'!$B$2:$D$16, 0,FALSE), IFERROR(VLOOKUP($A253,'Exetel ExDa'!$C$2:$N$14, 0,FALSE), IFERROR(VLOOKUP($A253,'Infinet ExDa'!$B$2:$E$14, 0,FALSE), "Not Found")))))))) -> 0
A254: GBA Barcaldine | B254: =IFERROR(VLOOKUP(A254,'Exetel ExDa'!$C$2:$N$14,4,FALSE),"No Data") -> No Data | C254: =IFERROR(VLOOKUP(A254,'AAPT ExDa'!$B$2:$U$99, 2,FALSE), IFERROR(VLOOKUP(A254,'ABB ExDa'!$A$2:$N$184, 2,FALSE), IFERROR(VLOOKUP(A254,'Vocus SIT ExDa'!$B$2:$J$173, 7,FALSE), IFERROR(VLOOKUP(A254,'Telstra ExDa'!$B$2:$K$310, 2,FALSE), IFERROR(VLOOKUP(A254,'Vocus RVC ExDa'!$C$2:$R$155, 3,FALSE), IFERROR(VLOOKUP(A254,'Fusion ExDa'!$B$2:$D$16, 2,FALSE), IFERROR(VLOOKUP(A254,'Exetel ExDa'!$C$2:$N$14, 2,FALSE), IFERROR(VLOOKUP(A254,'Infinet ExDa'!$B$2:$E$14, 2,FALSE), "Not Found")))))))) -> 73 ELM ST, BARCALDINE QLD | D254: =IFERROR(VLOOKUP($A254,'AAPT ExDa'!$B$2:$U$99, 15,FALSE), IFERROR(VLOOKUP($A254,'ABB ExDa'!$A$2:$N$184, 4,FALSE), IFERROR(VLOOKUP($A254,'Vocus SIT ExDa'!$B$2:$J$173, 5,FALSE), IFERROR(VLOOKUP($A254,'Telstra ExDa'!$B$2:$K$310, 8,FALSE), IFERROR(VLOOKUP($A254,'Vocus RVC ExDa'!$C$2:$R$155, 6,FALSE), IFERROR(VLOOKUP($A254,'Fusion ExDa'!$B$2:$D$16, 4,FALSE), IFERROR(VLOOKUP($A254,'Exetel ExDa'!$C$2:$N$14, 3,FALSE), IFERROR(VLOOKUP($A254,'Infinet ExDa'!$B$2:$E$14, 3,FALSE), "Not Found")))))))) -> ABB | E254: =IFERROR(VLOOKUP($A254,'AAPT ExDa'!$B$2:$U$99, 3,FALSE), IFERROR(VLOOKUP($A254,'ABB ExDa'!$A$2:$N$184, 5,FALSE), IFERROR(VLOOKUP($A254,'Vocus SIT ExDa'!$B$2:$J$173, 2,FALSE), IFERROR(VLOOKUP($A254,'Telstra ExDa'!$B$2:$K$310, 4,FALSE), IFERROR(VLOOKUP($A254,'Vocus RVC ExDa'!$C$2:$R$155, 8,FALSE), IFERROR(VLOOKUP($A254,'Fusion ExDa'!$B$2:$D$16, 4,FALSE), IFERROR(VLOOKUP($A254,'Exetel ExDa'!$C$2:$N$14, 5,FALSE), IFERROR(VLOOKUP($A254,'Infinet ExDa'!$B$2:$E$14, 3,FALSE), "Not Found")))))))) -> NBN 100/40 | F254: =IFERROR(VLOOKUP($A254,'AAPT ExDa'!$B$2:$U$99, 4,FALSE), IFERROR(VLOOKUP($A254,'ABB ExDa'!$A$2:$N$184, 6,FALSE), IFERROR(VLOOKUP($A254,'Vocus SIT ExDa'!$B$2:$J$173, 3,FALSE), IFERROR(VLOOKUP($A254,'Telstra ExDa'!$B$2:$K$310, 5,FALSE), IFERROR(VLOOKUP($A254,'Vocus RVC ExDa'!$C$2:$R$155, 9,FALSE), IFERROR(VLOOKUP($A254,'Fusion ExDa'!$B$2:$D$16, 0,FALSE), IFERROR(VLOOKUP($A254,'Exetel ExDa'!$C$2:$N$14, 6,FALSE), IFERROR(VLOOKUP($A254,'Infinet ExDa'!$B$2:$E$14, 0,FALSE), "Not Found")))))))) -> FTTN | G254: =IFERROR(VLOOKUP($A254,'AAPT ExDa'!$B$2:$U$99, 5,FALSE), IFERROR(VLOOKUP($A254,'ABB ExDa'!$A$2:$N$184, 8,FALSE), IFERROR(VLOOKUP($A254,'Vocus SIT ExDa'!$B$2:$J$173, 6,FALSE), IFERROR(VLOOKUP($A254,'Telstra ExDa'!$B$2:$K$310, 0,FALSE), IFERROR(VLOOKUP($A254,'Vocus RVC ExDa'!$C$2:$R$155, 15,FALSE), IFERROR(VLOOKUP($A254,'Fusion ExDa'!$B$2:$D$16, 0,FALSE), IFERROR(VLOOKUP($A254,'Exetel ExDa'!$C$2:$N$14, 7,FALSE), IFERROR(VLOOKUP($A254,'Infinet ExDa'!$B$2:$E$14, 0,FALSE), "Not Found")))))))) -> 144.6.127.34 | H254: =IFERROR(VLOOKUP($A254,'AAPT ExDa'!$B$2:$U$99, 6,FALSE), IFERROR(VLOOKUP($A254,'ABB ExDa'!$A$2:$N$184, 0,FALSE), IFERROR(VLOOKUP($A254,'Vocus SIT ExDa'!$B$2:$J$173, 0,FALSE), IFERROR(VLOOKUP($A254,'Telstra ExDa'!$B$2:$K$310, 0,FALSE), IFERROR(VLOOKUP($A254,'Vocus RVC ExDa'!$C$2:$R$155, 16,FALSE), IFERROR(VLOOKUP($A254,'Fusion ExDa'!$B$2:$D$16, 0,FALSE), IFERROR(VLOOKUP($A254,'Exetel ExDa'!$C$2:$N$14, 0,FALSE), IFERROR(VLOOKUP($A254,'Infinet ExDa'!$B$2:$E$14, 0,FALSE), "Not Found")))))))) -> Not Found | I254: =IFERROR(VLOOKUP($A254,'AAPT ExDa'!$B$2:$U$99, 0,FALSE), IFERROR(VLOOKUP($A254,'ABB ExDa'!$A$2:$N$184, 0,FALSE), IFERROR(VLOOKUP($A254,'Vocus SIT ExDa'!$B$2:$J$173, 0,FALSE), IFERROR(VLOOKUP($A254,'Telstra ExDa'!$B$2:$K$310, 0,FALSE), IFERROR(VLOOKUP($A254,'Vocus RVC ExDa'!$C$2:$R$155, 0,FALSE), IFERROR(VLOOKUP($A254,'Fusion ExDa'!$B$2:$D$16, 0,FALSE), IFERROR(VLOOKUP($A254,'Exetel ExDa'!$C$2:$N$14, 8,FALSE), IFERROR(VLOOKUP($A254,'Infinet ExDa'!$B$2:$E$14, 0,FALSE), "Not Found")))))))) -> Not Found | J254: =IFERROR(VLOOKUP($A254,'AAPT ExDa'!$B$2:$U$99, 7,FALSE), IFERROR(VLOOKUP($A254,'ABB ExDa'!$A$2:$N$184, 2,FALSE), IFERROR(VLOOKUP($A254,'Vocus SIT ExDa'!$B$2:$J$173, 0,FALSE), IFERROR(VLOOKUP($A254,'Telstra ExDa'!$B$2:$K$310, 7,FALSE), IFERROR(VLOOKUP($A254,'Vocus RVC ExDa'!$C$2:$R$155, 2,FALSE), IFERROR(VLOOKUP($A254,'Fusion ExDa'!$B$2:$D$16, 3,FALSE), IFERROR(VLOOKUP($A254,'Exetel ExDa'!$C$2:$N$14, 0,FALSE), IFERROR(VLOOKUP($A254,'Infinet ExDa'!$B$2:$E$14, 0,FALSE), "Not Found")))))))) -> 73 ELM ST, BARCALDINE QLD | K254: =IFERROR(VLOOKUP($A254,'AAPT ExDa'!$B$2:$U$99, 12,FALSE), IFERROR(VLOOKUP($A254,'ABB ExDa'!$A$2:$N$184, 0,FALSE), IFERROR(VLOOKUP($A254,'Vocus SIT ExDa'!$B$2:$J$173, 0,FALSE), IFERROR(VLOOKUP($A254,'Telstra ExDa'!$B$2:$K$310, 0,FALSE), IFERROR(VLOOKUP($A254,'Vocus RVC ExDa'!$C$2:$R$155, 0,FALSE), IFERROR(VLOOKUP($A254,'Fusion ExDa'!$B$2:$D$16, 0,FALSE), IFERROR(VLOOKUP($A254,'Exetel ExDa'!$C$2:$N$14, 12,FALSE), IFERROR(VLOOKUP($A254,'Infinet ExDa'!$B$2:$E$14, 0,FALSE), "Not Found")))))))) -> Not Found | L254: =IFERROR(VLOOKUP($A254,'AAPT ExDa'!$B$2:$U$99, 11,FALSE), IFERROR(VLOOKUP($A254,'ABB ExDa'!$A$2:$N$184, 9,FALSE), IFERROR(VLOOKUP($A254,'Vocus SIT ExDa'!$B$2:$J$173, 8,FALSE), IFERROR(VLOOKUP($A254,'Telstra ExDa'!$B$2:$K$310, 0,FALSE), IFERROR(VLOOKUP($A254,'Vocus RVC ExDa'!$C$2:$R$155, 0,FALSE), IFERROR(VLOOKUP($A254,'Fusion ExDa'!$B$2:$D$16, 0,FALSE), IFERROR(VLOOKUP($A254,'Exetel ExDa'!$C$2:$N$14, 9,FALSE), IFERROR(VLOOKUP($A254,'Infinet ExDa'!$B$2:$E$14, 0,FALSE), "Not Found")))))))) -> 05 Aug 2024 | M254: =IFERROR(VLOOKUP($A254,'AAPT ExDa'!$B$2:$U$99, 0,FALSE), IFERROR(VLOOKUP($A254,'ABB ExDa'!$A$2:$N$184, 0,FALSE), IFERROR(VLOOKUP($A254,'Vocus SIT ExDa'!$B$2:$J$173, 0,FALSE), IFERROR(VLOOKUP($A254,'Telstra ExDa'!$B$2:$K$310, 0,FALSE), IFERROR(VLOOKUP($A254,'Vocus RVC ExDa'!$C$2:$R$155, 0,FALSE), IFERROR(VLOOKUP($A254,'Fusion ExDa'!$B$2:$D$16, 0,FALSE), IFERROR(VLOOKUP($A254,'Exetel ExDa'!$C$2:$N$14, 11,FALSE), IFERROR(VLOOKUP($A254,'Infinet ExDa'!$B$2:$E$14, 0,FALSE), "Not Found")))))))) -> Not Found | N254: =IFERROR(VLOOKUP($A254,'AAPT ExDa'!$B$2:$U$99, 0,FALSE), IFERROR(VLOOKUP($A254,'ABB ExDa'!$A$2:$N$184, 13,FALSE), IFERROR(VLOOKUP($A254,'Vocus SIT ExDa'!$B$2:$J$173, 0,FALSE), IFERROR(VLOOKUP($A254,'Telstra ExDa'!$B$2:$K$310, 0,FALSE), IFERROR(VLOOKUP($A254,'Vocus RVC ExDa'!$C$2:$R$155, 0,FALSE), IFERROR(VLOOKUP($A254,'Fusion ExDa'!$B$2:$D$16, 0,FALSE), IFERROR(VLOOKUP($A254,'Exetel ExDa'!$C$2:$N$14, 0,FALSE), IFERROR(VLOOKUP($A254,'Infinet ExDa'!$B$2:$E$14, 0,FALSE), "Not Found")))))))) -> Sasboss
